Workbook

Sheet Read Me
A1: HIP & GROIN ASSESSMENT AND MANAGEMENT PROGRAMME
A2: Screen → clear the lumbar spine → localise the region → cluster (Doha / Warwick) → load → discharge on capacity and control.
A4: SHEET | B4: WHAT IT DOES | C4: WHEN TO USE IT | D4: FOCUS
A5: Master Matrix | B5: 38 hip and groin conditions on the established column structure: Region → Activity Level → Common Symptoms → Age → Onset → Predominance → Condition → High-Yield Question → Special Test + Imaging → Biomechanical Cause → Desired Activity Goal → Physiotherapy Specific Exercise, then pain mechanism, classification, red-flag status, management emphasis, loading dose, biomechanical corrections, adjuncts, advanced options, outcomes, markers, timeline and referral triggers. | C5: The core reference. Filter column A by region or column O by red-flag status. | D5: All hip and groin pathology
A6: Rx Generator | B6: Pick a condition from the dropdown and the full prescription is pulled live from the Master Matrix. | C6: In clinic, or to print a plan into the patient file. | D6: Live INDEX/MATCH
A7: Assessment Roadmap | B7: The five-gate reasoning sequence, built around clearing the lumbar spine and then localising by region. | C7: Every new patient, in order. | D7: Clinical reasoning
A8: Subjective Exam | B8: Fillable history template with the hip-specific and paediatric screening questions built in. | C8: First consultation. | D8: Fillable
A9: Objective Exam | B9: Fillable examination template: observation, gait, palpation map, range, strength, squeeze test, special tests, lumbar screen. | C9: First consultation and every re-assessment. | D9: Fillable
A10: Special Tests | B10: 30 tests across intra-articular, groin, lateral, posterior, bone stress, paediatric and neural categories. | C10: During the physical examination. | D10: Reference
A11: Clusters & Doha | B11: Six diagnostic clusters, the one-line differentiators, and the Doha classification of athletic groin pain. | C11: When the picture is not yet clear, and in every athletic groin presentation. | D11: Doha 2015; Warwick 2016
A12: Imaging Guide | B12: When to image, which modality answers which question, and the traps. | C12: Before requesting or when reading a report. | D12: Reference
A13: Phased Programme | B13: Phase 0-4 with goals, content, markers and exit criteria, plus the master treatment sequence. | C13: Building and progressing every plan. | D13: Reference
A14: Exercise & Dosage | B14: Loading library with dose and indication, including the Copenhagen adduction programme and neutral-range abductor loading. | C14: Writing the actual programme. | D14: Reference
A15: Adjuncts & Advanced | B15: Education, positional modification, manual therapy, injection, ESWT and surgery, with the sequencing rule. | C15: When loading alone is not enough. | D15: Reference
... A23: References | B23: Guideline and trial sources. | C23: Verifying or citing. | D23: —
A25: CRITICAL POINTS FOR THE HIP
A26: • THE HIP'S DEFINING TRAP IS THE PAEDIATRIC ONE: an adolescent with hip OR KNEE pain and a limp has a slipped capital femoral epiphysis until proven otherwise. Knee pain is a classic presentation of hip pathology in children and is the commonest cause of delayed diagnosis.
A27: • THE SECOND TRAP: the lumbar spine. Screen it in every hip presentation and screen the hip in every lumbar presentation — hip-spine syndrome is common and both may need treating.
A28: • THE THIRD TRAP: measure the LATERAL CENTRE-EDGE ANGLE before anyone has a hip arthroscopy. Isolated labral surgery in a dysplastic hip can accelerate instability and degeneration.
A29: • MEASURE THE ADDUCTOR SQUEEZE in every groin presentation and record the figure — it is simultaneously a diagnostic test, the treatment target and the discharge criterion.
A30: • IN GTPS, REMOVING COMPRESSION MATTERS AS MUCH AS LOADING. Stop hip adduction postures, put a pillow between the knees at night, and do not roll the ITB or stretch into adduction.
A31: • Loss of hip INTERNAL ROTATION at 90 degrees flexion is the earliest measurable change in both FAI syndrome and hip osteoarthritis — measure it in every hip.
A32: • Yellow cells are inputs. Green text is pulled from another sheet. Do not overwrite formula cells.
A33: • This workbook supports clinical reasoning; it does not replace individualised assessment, local protocols or the operating surgeon's protocol.

Sheet Master Matrix
A1: MASTER DIAGNOSTIC & MANAGEMENT MATRIX — 38 HIP & GROIN CONDITIONS
A2: Columns A–L follow the established diagnostics-algorithm structure. Columns M–Y add the management programme. Crimson in column O marks a red-flag or time-sensitive presentation.
A3: Region | B3: Activity Level | C3: Common Symptoms | D3: Age Group | E3: Onset | F3: Predominance | G3: Condition | H3: High-Yield Diagnostic Question | I3: Special Test + Imaging | J3: Underlying Biomechanical Cause | K3: DESIRED ACTIVITY GOAL | L3: PHYSIOTHERAPY SPECIFIC EXERCISE | M3: Pain Mechanism | N3: Classification / Cluster | O3: Red Flag Status | P3: MANAGEMENT EMPHASIS | Q3: Loading Stage & Entry Dose | R3: BIOMECHANICAL CORRECTIONS & KINETIC CHAIN | S3: Manual Therapy, Positional & Adjuncts | T3: Advanced / Surgical Options | U3: Outcome Measures | V3: Re-testable Markers | W3: Expected Timeline | X3: Referral / Surgical Trigger | Y3: Evidence Anchor
A4: Anterior / Groin | B4: Football, ice hockey, dance, martial arts, deep-squat lifting; also sedentary with a sudden activity increase | C4: Anterior groin pain with deep flexion, prolonged sitting and pivoting; catching or clicking | D4: 18-45 | E4: Slow | F4: Male athletes | G4: Femoroacetabular Impingement Syndrome (FAIS) | H4: Do you grip the side of your hip with a C-shape when showing me where it hurts, and does deep squatting or long sitting bring it on? | I4: FADIR (anterior impingement) test + AP pelvis and Dunn lateral radiographs (alpha angle, LCEA); MR arthrogram if labral pathology is suspected | J4: Cam or pincer morphology producing abnormal femoroacetabular contact in flexion and internal rotation; compounded by restricted hip internal rotation, gluteal and deep rotator weakness, anterior pelvic tilt, poor lumbopelvic control, and repetitive deep-flexion loading in sport | K4: Return to deep squatting, pivoting sport and prolonged sitting without groin pain or catching | L4: Gluteus medius and maximus strengthening (side-lying abduction, banded lateral walk, hip thrust, split squat) 3-4 sets 8-12 RM 3x/week; deep external rotator activation; lumbopelvic control (dead bug, Pallof press); modify squat depth and hip flexion range early; posterior chain and hamstring loading; graded return to pivoting and cutting; core and trunk endurance | M4: Nociceptive - mechanical and compressive; nociplastic overlay common when longstanding | N4: Cluster 1 - FAIS (Warwick Agreement 2016): symptoms + clinical signs + imaging findings, ALL THREE required. Morphology alone is not a diagnosis | O4: No | P4: Physiotherapy-led rehabilitation is a legitimate first-line option and should be trialled properly (typically 3-6 months) before surgery. Focus on hip and lumbopelvic strengthening, movement retraining and activity modification. Arthroscopy shows benefit over physiotherapy in trials but the effect size is modest - discuss both pathways transparently | Q4: Stage 1-2. Isometric gluteal and hip work if irritable; progressive gluteal and deep rotator loading 3-4 sets 8-12 RM 3x/week within a non-impinging range; progress to functional and sport-specific loading | R4: Take the hip out of the impinging position: build gluteal and deep external rotator capacity, correct anterior pelvic tilt and lumbopelvic control, restore thoracic and lumbar rotation so the hip rotates less, cap squat depth and deep-flexion volume, correct sitting posture and seat height, and retrain cutting and pivoting mechanics | S4: Manual therapy for hip and lumbopelvic mobility as an adjunct; activity and seating modification; taping is of limited value here | T4: If a well-delivered 3-6 month programme fails: arthroscopic femoroplasty or acetabuloplasty with labral repair and capsular closure. Guided intra-articular injection is diagnostically useful | U4: iHOT-33; HAGOS; HOS; NPRS on the primary provocative task | V4: FADIR response; hip internal rotation range at 90 degrees flexion; sitting tolerance; squat depth before pain; gluteal strength LSI | W4: 3-6 months conservative trial; 6-9 months to sport post arthroscopy | X4: Failure of a genuinely well-delivered 3-6 month programme; mechanical locking; progressive loss of range | Y4: Warwick Agreement on FAI syndrome (BJSM 2016); UK FASHIoN trial
A5: Anterior / Groin | B5: Pivoting and deep-flexion sport; also dancers and those with hypermobility | C5: Sharp catching or clicking groin pain with pivoting, deep flexion or getting out of a car | D5: 18-45 | E5: Sudden/Slow | F5: Female | G5: Acetabular Labral Tear | H5: Does the hip catch, click or give a sharp sensation when you twist or come out of a deep position? | I5: FADIR and FABER; MR arthrogram is the imaging standard; intra-articular anaesthetic injection is a useful diagnostic test | J5: Shear and compressive load on the labrum from cam or pincer morphology, acetabular dysplasia, or capsular laxity and microinstability; repetitive end-range rotation in dance and pivoting sport; gluteal and deep rotator weakness allow uncontrolled femoral translation | K5: Return to pivoting, deep flexion and sport without catching or sharp groin pain | L5: Gluteal and deep external rotator strengthening 3-4 sets 8-12 RM 3x/week; lumbopelvic control work; avoid end-range rotation and deep flexion early; progressive loading through range as symptoms allow; single-leg control and landing retraining; sport-specific pivot progression | M5: Nociceptive - mechanical | N5: Hip-related groin pain (Doha agreement). Note labral change is common in ASYMPTOMATIC hips, especially in athletes - correlate with the clinical picture | O5: Screen: assess for underlying dysplasia (LCEA under 25 degrees) - it changes the surgical decision entirely | P5: Conservative rehabilitation first-line: gluteal and lumbopelvic strengthening, movement retraining and activity modification. Treat the DRIVER (FAI morphology, dysplasia or capsular laxity), not just the tear. Repair rather than debridement where surgery is indicated | Q5: Stage 1-2. Progressive gluteal and deep rotator loading within a non-provocative range; progress range and load as symptoms settle; then functional and sport-specific | R5: Address the mechanical driver: build gluteal and deep external rotator capacity to control femoral head translation, correct lumbopelvic control and anterior pelvic tilt, cap end-range rotation and deep-flexion volume, and retrain pivoting and landing mechanics | S5: Manual therapy as an adjunct; activity modification; avoid aggressive end-range stretching in a hypermobile hip | T5: Arthroscopic labral repair (preferred) or reconstruction with correction of the underlying morphology; NEVER isolated debridement in a dysplastic hip - it accelerates instability | U5: iHOT-33; HAGOS; HOS | V5: Catching frequency; FADIR response; internal rotation range; gluteal strength LSI; pivot tolerance | W5: 3-6 months conservative; 6-9 months to sport post repair | X5: Persistent mechanical symptoms after a well-delivered programme; underlying dysplasia requiring PAO rather than arthroscopy | Y5: Doha agreement (BJSM 2015); labral repair vs debridement literature
A6: Anterior / Groin | B6: Any activity level; walking, stairs and sit-to-stand loaded | C6: Deep groin pain with weight-bearing, morning stiffness under 60 minutes, progressive stiffness | D6: 50+ | E6: Slow | F6: Equal | G6: Hip Osteoarthritis | H6: Is the groin pain worse with walking and standing, and stiff for less than an hour in the morning? | I6: Restricted internal rotation and flexion; positive FABER; weight-bearing AP pelvis radiograph (Tonnis grade, joint space, osteophytes) | J6: Cumulative joint load with cartilage loss; prior FAI morphology, dysplasia or injury accelerate it. Reduced gluteal and quadriceps capacity increases the load the joint absorbs and produces a Trendelenburg gait pattern | K6: Walk, climb stairs and rise from a chair without limiting pain; maintain independence and delay or avoid arthroplasty | L6: Gluteus medius and maximus strengthening (side-lying abduction, bridge, hip thrust, sit-to-stand, step-up) 3-4 sets 8-12 RM 2-3x/week; quadriceps loading; hip range maintenance in flexion and internal rotation; aerobic conditioning 150 min/week (cycling, pool, walking); balance and gait retraining; weight management support | M6: Nociceptive with frequent nociplastic overlay in long-standing disease | N6: Hip-related group - degenerative. Tonnis grading on radiograph. Clinical diagnosis is reasonable without imaging in a typical older presentation | O6: No | P6: EXERCISE + EDUCATION + WEIGHT MANAGEMENT is first-line and strongly recommended (OARSI, NICE NG226, ACR). Reassure that loading is safe and does not wear the joint out. Expect and manage flares. Arthroplasty for end-stage disease after well-delivered conservative care | Q6: Stage 1-2 sustained. Strengthening 2-3x/week plus aerobic exercise plus neuromuscular training; acceptable symptom window of pain <=5/10 settling within 24 h; mode by patient preference | R6: Reduce the load the joint absorbs and improve distribution: gluteal (especially abductor) and quadriceps capacity to correct Trendelenburg gait, improve gait quality and step length, retrain sit-to-stand and stair strategy to a hip-hinge pattern, support weight management, and use a stick in the CONTRALATERAL hand where offloading is needed | S6: Walking aid in the contralateral hand; heat; manual therapy as an adjunct to exercise; footwear and task modification | T6: Guided intra-articular corticosteroid injection for short-term relief to enable loading; total hip arthroplasty for end-stage disease. Hip arthroscopy is NOT indicated in established OA | U6: HOOS; HOOS-12; Oxford Hip Score; 30-second sit-to-stand; 40 m fast-paced walk test; timed stair climb | V6: Internal rotation and flexion range; sit-to-stand repetitions; walking tolerance; abductor strength LSI; morning stiffness duration | W6: 12 weeks for meaningful change; ongoing lifelong self-management | X6: End-stage disease with failed well-delivered conservative care - arthroplasty opinion | Y6: OARSI 2019; NICE NG226 2022; ACR/AF 2019
A7: Anterior / Groin | B7: Football, dance, running, hurdling; repetitive hip flexion | C7: Anterior groin pain on resisted hip flexion, kicking and sprinting; may click deep in the groin | D7: 18-40 | E7: Slow | F7: Equal | G7: Iliopsoas-Related Groin Pain / Iliopsoas Tendinopathy | H7: Does the pain come on when you lift your knee against resistance, or kick? | I7: Pain on resisted hip flexion and on iliopsoas stretch (modified Thomas); local tenderness; ultrasound or MRI if characterising or guiding injection | J7: Repetitive hip flexion load exceeding iliopsoas capacity: kicking, sprinting and hurdling volume; anterior pelvic tilt and hip flexor dominance with gluteal underactivity; restricted hip extension; lumbopelvic control deficits; sudden increase in kicking or running volume | K7: Return to full kicking, sprinting and hurdling volume without anterior groin pain | L7: Isometric hip flexion holds for analgesia if irritable; progressive resisted hip flexion loading (band, cable, weighted straight-leg raise, standing hip flexion) 3-4 sets 8-12 RM 3x/week; eccentric hip flexor work; gluteal and posterior chain strengthening; hip extension mobility; lumbopelvic control; graded kicking and sprint volume progression | M7: Nociceptive - tensile tendon and muscle load | N7: Iliopsoas-related groin pain (Doha agreement) - one of the five defined groin entities | O7: No | P7: Progressive loading of the hip flexor complex plus load management. Address the anterior pelvic tilt and hip-flexor-dominant pattern that created it. Correct kicking and sprint volume | Q7: Stage 1-2. Isometric holds 5 x 30-45 s if irritable; progressive isotonic hip flexion loading 3-4 sets 8-12 RM 3x/week; then eccentric and sport-specific loading | R7: Change the pattern that overloads it: strengthen gluteus maximus so the hip flexors do not dominate, correct anterior pelvic tilt, restore hip extension range, build lumbopelvic control, and grade kicking and sprint volume rather than spiking it | S7: Manual therapy and soft-tissue work as short-term adjuncts; activity modification | T7: Guided injection into the bursa or sheath (not tendon substance) for refractory cases; iliopsoas fractional lengthening is rarely indicated and carries a hip flexor weakness cost | U7: HAGOS; iHOT-33; NPRS on resisted hip flexion | V7: Pain on resisted hip flexion; hip flexor strength LSI; kicking and sprint volume tolerance; hip extension range | W7: 8-12 weeks | X7: Failure after 12 weeks of correct loading; suspicion of intra-articular pathology driving secondary iliopsoas irritation | Y7: Doha agreement (BJSM 2015)
A8: Anterior / Groin | B8: Dancer, gymnast, footballer; often hypermobile | C8: Audible or palpable snap deep in the anterior groin with hip extension from flexion | D8: 15-35 | E8: Slow | F8: Female | G8: Internal Snapping Hip (Coxa Saltans Interna) | H8: Does something snap deep in the front of the hip when you straighten it from a bent position? | I8: Reproducible snap on moving from flexion-abduction-external rotation into extension; dynamic ultrasound confirms iliopsoas tendon snapping over the iliopectineal eminence | J8: The iliopsoas tendon snapping over the iliopectineal eminence or femoral head; driven by iliopsoas tightness or overactivity, anterior pelvic tilt, capsular laxity, and repetitive extreme hip range in dance and gymnastics | K8: Perform full dance or sport range without a painful snap | L8: Iliopsoas and rectus femoris lengthening only if genuinely short; gluteal and deep rotator strengthening 3-4 sets 8-12 RM 3x/week; lumbopelvic control; anterior pelvic tilt correction; movement retraining to reduce the snapping arc; progressive return to full range and sport volume | M8: Nociceptive - mechanical friction; often painless and needing no treatment at all | N8: Hip-related group; distinguish from external snapping (ITB over the greater trochanter, lateral and visible) and intra-articular causes | O8: No | P8: A PAINLESS snap needs no treatment - reassure. A painful snap: address iliopsoas overactivity or tightness, build gluteal control and lumbopelvic stability, and retrain the movement pattern. Surgery is rarely needed | Q8: Stage 1-2. Progressive gluteal and deep rotator loading; iliopsoas loading rather than only stretching; movement retraining through the snapping arc | R8: Reduce the friction mechanism: correct anterior pelvic tilt and hip flexor dominance, build gluteal capacity, address capsular laxity with control rather than stretching, and modify the extreme range positions in dance or gymnastics | S8: Manual therapy for the iliopsoas as an adjunct; activity modification | T8: Guided iliopsoas bursal injection for refractory pain; arthroscopic fractional lengthening is a last resort with a hip flexor weakness cost | U8: iHOT-33; HAGOS; snap frequency and pain | V8: Painful snap frequency; hip flexor and gluteal strength; dance or sport range tolerance | W8: 8-12 weeks | X8: Persistent painful snapping after a well-delivered programme; suspicion of an intra-articular cause | Y8: Doha agreement; snapping hip literature
A9: Anterior / Groin | B9: Football, ice hockey, Australian rules, martial arts - cutting and kicking sport | C9: Groin pain on kicking, cutting and sprinting; tenderness at the adductor origin | D9: 18-35 | E9: Sudden/Slow | F9: Male athletes | G9: Adductor-Related Groin Pain | H9: Is the groin pain reproduced when you squeeze your knees together against resistance? | I9: Adductor tenderness at the origin PLUS pain on resisted adduction (the defining combination); adductor squeeze test at 0, 45 and 90 degrees; imaging only if a significant tear is suspected | J9: Repetitive high-force adduction and eccentric loading during cutting, kicking and change of direction; low adduction:abduction strength ratio, adductor weakness relative to demand, poor lumbopelvic control, and a spike in cutting or kicking volume | K9: Return to full cutting, kicking and sprinting volume without groin pain and with a restored adduction:abduction ratio | L9: COPENHAGEN ADDUCTION EXERCISE is the primary intervention - progress from short-lever to long-lever, 2-3 sets building to 12-15 reps, 2-3x/week; adductor squeeze isometrics 5 x 30-45 s at 0, 45 and 90 degrees for analgesia; gluteal and abdominal loading; lumbopelvic control (Pallof press, dead bug); graded return-to-run and change-of-direction progression | M9: Nociceptive - tensile muscle and tendon load | N9: Cluster - ADDUCTOR-RELATED GROIN PAIN (Doha agreement 2015): the most common of the five defined groin entities | O9: No | P9: Progressive adductor loading, led by the Copenhagen adduction exercise, plus lumbopelvic and gluteal work and graded return to cutting. Adductor strength and the adduction:abduction ratio are BOTH the treatment target and the discharge criterion | Q9: Stage 1-2. Isometric adductor squeezes for analgesia; then Copenhagen adduction progression 2-3x/week; then eccentric and sport-specific change-of-direction loading | R9: Restore the force balance: raise the adduction:abduction strength ratio toward 0.9-1.0, build gluteal and abdominal capacity, improve lumbopelvic control, correct change-of-direction and kicking mechanics, and grade cutting and kicking volume rather than spiking it | S9: Manual therapy and soft-tissue work as short-term adjuncts; compression shorts for comfort | T9: Guided injection is rarely indicated; adductor tenotomy or longus repair only for a complete avulsion or genuinely refractory cases | U9: HAGOS; adductor squeeze force (kg or mmHg); NPRS on cutting | V9: Adductor squeeze force at 0/45/90; ADDUCTION:ABDUCTION RATIO; cutting and kicking tolerance; local tenderness | W9: 6-12 weeks for most; longer for a significant tear | X9: Complete avulsion; failure after 12 weeks of correct loading; suspicion of another Doha entity coexisting | Y9: Doha agreement (BJSM 2015); Copenhagen adduction exercise (Harøy BJSM 2019)
A10: Anterior / Groin | B10: Football, running, Australian rules; high change-of-direction and kicking volume | C10: Central pubic pain with kicking, sprinting and sit-ups; tenderness over the pubic symphysis | D10: 18-35 | E10: Slow | F10: Male athletes | G10: Pubic-Related Groin Pain / Osteitis Pubis | H10: Is the pain right in the middle at the pubic bone, and does it hurt to do a sit-up as well as to kick? | I10: Local tenderness over the pubic symphysis and adjacent bone; MRI shows pubic bone marrow oedema; radiograph may show symphyseal irregularity in chronic cases | J10: Repetitive shear across the pubic symphysis from asymmetric adductor and abdominal forces during kicking and cutting; adductor-abdominal force imbalance, poor lumbopelvic control, restricted hip internal rotation transferring load to the pelvis, and a volume spike | K10: Return to full kicking, sprinting and change-of-direction volume without central pubic pain | L10: Isometric adductor squeezes for analgesia; progressive adductor loading (Copenhagen adduction) 2-3x/week; abdominal and oblique loading; lumbopelvic control work (Pallof press, dead bug, side plank progressions); restore hip internal rotation range; graded return-to-run then change-of-direction then kicking | M10: Nociceptive - bone stress and shear at the symphysis | N10: PUBIC-RELATED GROIN PAIN (Doha agreement). Frequently coexists with adductor-related groin pain - screen for both | O10: Screen: exclude a pubic ramus stress fracture, and in the older or systemically unwell patient exclude infection and inflammatory disease | P10: Load management with progressive adductor and abdominal loading and lumbopelvic control. Restore hip internal rotation, because a stiff hip transfers load to the pelvis. Slow condition - set expectations for 3-6 months | Q10: Stage 1-2. Isometric adductor and abdominal loading for analgesia; progressive adductor and trunk loading 2-3x/week; graded return to run, cut and kick in that order | R10: Rebalance the forces across the symphysis: raise adductor and abdominal capacity together, restore hip internal rotation so the hip absorbs rotation instead of the pelvis, improve lumbopelvic control, correct kicking mechanics, and grade change-of-direction and kicking volume | S10: Compression shorts; manual therapy for hip and lumbopelvic mobility; activity modification | T10: Guided symphyseal injection for refractory cases; surgery (symphyseal curettage or fusion) is rarely indicated | U10: HAGOS; NPRS on kicking and sit-ups; adductor squeeze force | V10: Symphyseal tenderness; adductor squeeze force; hip internal rotation range; kicking tolerance | W10: 3-6 months - a notoriously slow condition | X10: Failure after 3 months; suspicion of a pubic ramus stress fracture, infection or inflammatory disease | Y10: Doha agreement (BJSM 2015)
A11: Anterior / Groin | B11: Football, rugby, ice hockey; high cutting and twisting volume | C11: Diffuse groin and lower abdominal pain with sprinting, cutting, coughing and sneezing; no palpable hernia | D11: 18-35 | E11: Slow | F11: Male athletes | G11: Inguinal-Related Groin Pain (Sportsman's Groin) | H11: Does the groin pain also come on when you cough, sneeze or do a sit-up, without any lump being present? | I11: Tenderness over the inguinal canal and conjoint tendon; pain on resisted sit-up and on Valsalva; NO palpable hernia; MRI to exclude other causes; ultrasound for dynamic posterior wall assessment | J11: Weakness or attenuation of the posterior inguinal wall under repetitive shear from cutting and twisting; abdominal-adductor force imbalance, poor lumbopelvic control, restricted hip range transferring load to the abdominal wall | K11: Return to full sprinting, cutting and contact sport without groin or lower abdominal pain | L11: Progressive abdominal and oblique loading (dead bug, Pallof press, side plank progression, cable chops) 3x/week; adductor loading (Copenhagen adduction); gluteal strengthening; hip mobility work; graded return-to-run and change-of-direction progression before contact | M11: Nociceptive - shear and tensile load on the inguinal wall | N11: INGUINAL-RELATED GROIN PAIN (Doha agreement). A clinical diagnosis of exclusion - no true hernia is present | O11: Screen: exclude a true hernia, intra-abdominal pathology and hip-related causes | P11: Trial progressive abdominal, adductor and lumbopelvic loading for 8-12 weeks. Surgical opinion (posterior wall repair or 'core muscle' surgery) for genuinely refractory cases in athletes - outcomes are good in correctly selected patients | Q11: Stage 1-2. Progressive abdominal, oblique, adductor and gluteal loading 3x/week; graded return to run, cut and contact | R11: Rebalance the abdominal wall load: build abdominal and oblique capacity relative to adductor pull, improve lumbopelvic control, restore hip rotation range so the abdominal wall absorbs less shear, and grade cutting and twisting volume | S11: Compression shorts; manual therapy as an adjunct; activity modification | T11: Surgical posterior wall repair or laparoscopic mesh repair for refractory cases; specialist groin surgeon referral | U11: HAGOS; NPRS on sprinting, coughing and sit-ups | V11: Inguinal tenderness; pain on Valsalva and resisted sit-up; sprint and cutting tolerance | W11: 8-12 weeks conservative trial; 6-8 weeks return post surgery | X11: Failure after 8-12 weeks of correct loading in an athlete - refer to a specialist groin surgeon | Y11: Doha agreement (BJSM 2015)
A12: Anterior / Groin | B12: Sprinting, kicking sport, hurdling; explosive hip flexion | C12: Sudden anterior thigh or hip pain during a sprint or kick; local tenderness and possible bruising | D12: 15-35 | E12: Sudden | F12: Male athletes | G12: Rectus Femoris Strain / AIIS Avulsion | H12: Did the front of the hip or thigh give a sharp pain at the moment of a sprint or a kick? | I12: Pain on resisted hip flexion with the knee flexed; tenderness at the AIIS or muscle belly; radiograph in the adolescent to exclude AIIS apophyseal avulsion; ultrasound or MRI to grade | J12: Eccentric overload of the two-joint rectus femoris during the swing phase of sprinting or the kicking follow-through; hip flexor weakness relative to demand, inadequate warm-up, fatigue, restricted hip extension, and a sprint or kicking volume spike | K12: Return to full sprinting and kicking speed without anterior thigh pain and with symmetrical hip flexor strength | L12: Early: pain-free isometric hip flexion and knee extension holds. Then progressive isotonic hip flexion and knee extension loading 3-4 sets 8-12 RM 3x/week; eccentric hip flexor work (slider, band-resisted decline); gluteal and hamstring loading; hip extension mobility; graded sprint progression with kicking last | M12: Nociceptive - acute muscle strain | N12: Anterior group - musculotendinous. In the SKELETALLY IMMATURE athlete this is an AIIS apophyseal avulsion, not a muscle strain | O12: Screen: in an adolescent, image to exclude apophyseal avulsion - management and timeline differ | P12: Progressive loading with a graded sprint and kicking return. Adolescent avulsion: relative rest, protected weight bearing initially, then graded loading; surgery only for significant displacement | Q12: Stage 1-4. Pain-free isometrics days 0-7; progressive isotonic loading; then eccentric and energy-storage work; then sprint and kicking progression | R12: Address the eccentric deficit: build hip flexor and quadriceps eccentric capacity, restore hip extension range, strengthen gluteals and hamstrings for balance, improve warm-up practice, and grade sprint and kicking volume rather than spiking it | S12: Compression; short-term activity modification; manual therapy as an adjunct | T12: Surgical fixation only for a significantly displaced AIIS avulsion (typically over 2 cm) in a young athlete | U12: HAGOS; hip flexor strength LSI; sprint tolerance | V12: Pain on resisted hip flexion; hip flexor strength LSI; sprint speed tolerance; hip extension range | W12: 3-8 weeks by grade; 6-12 weeks for an adolescent avulsion | X12: Significant apophyseal displacement; failure to progress; suspected complete tear | Y12: Muscle injury classification; apophyseal avulsion literature
A13: Anterior / Groin | B13: Any; associated with tight belts, obesity, pregnancy, or prolonged hip flexion | C13: Burning, numbness and tingling over the anterolateral thigh; NO weakness | D13: 30-60 | E13: Slow | F13: Equal | G13: Meralgia Paraesthetica (Lateral Femoral Cutaneous Nerve) | H13: Is it burning or numbness over the outside of the thigh, with no weakness at all? | I13: Sensory change over the anterolateral thigh in the LFCN distribution; Tinel's sign at the ASIS; pelvic compression test; nerve conduction studies if the picture is unclear; MRI only to exclude a mass | J13: Compression of the lateral femoral cutaneous nerve as it passes near the ASIS beneath the inguinal ligament; tight belts and waistbands, body armour or tool belts, raised body mass, pregnancy, prolonged hip flexion, and anterior pelvic tilt increasing tension over the nerve | K13: Resolve the burning and numbness and return to normal daily activity, work clothing and exercise | L13: Remove the compressive source first. Nerve gliding within symptom tolerance; hip extension mobility; anterior pelvic tilt correction with gluteal and abdominal loading; graded reintroduction of prolonged sitting and hip flexion; general conditioning and weight management support where relevant | M13: Neuropathic - purely sensory | N13: Neural group. PURELY SENSORY - any motor weakness means the diagnosis is wrong, so look again | O13: Screen: any weakness, or bilateral symptoms, means this is not meralgia paraesthetica - reconsider lumbar or systemic causes | P13: Remove the compressive source - this is the entire first-line intervention (belts, waistbands, tool belts, body armour). Then nerve mobility, anterior pelvic tilt correction and weight management support. Most resolve spontaneously once the compression is removed | Q13: Loading is secondary. Nerve gliding within tolerance; gluteal and abdominal loading to correct anterior pelvic tilt; graded reintroduction of sitting and hip flexion | R13: Take the tension and compression off the nerve: remove external compression, correct anterior pelvic tilt and hip flexor tightness that increases nerve tension, modify prolonged hip flexion positions, and support weight management where relevant | S13: Clothing and equipment modification is the highest-yield adjunct; nerve gliding; activity modification | T13: Guided local anaesthetic and corticosteroid injection at the ASIS for refractory symptoms; surgical decompression or neurectomy is rarely needed | U13: NPRS; sensory area mapping; LEFS | V13: Sensory area size; burning intensity; sitting and standing tolerance | W13: Weeks to months once the compression is removed | X13: Any motor weakness (reconsider the diagnosis); refractory symptoms after removing compression | Y13: Meralgia paraesthetica literature
A14: Anterior / Groin | B14: Dance, gymnastics, martial arts, yoga; often generalised hypermobility | C14: Vague anterior groin ache with a sense of the hip giving way or shifting, worse in end-range positions | D14: 15-35 | E14: Slow | F14: Female | G14: Hip Microinstability / Capsular Laxity | H14: Does the hip feel loose or like it shifts, especially in end-range positions - and are you generally flexible? | I14: Positive hip dial test and anterior apprehension in extension-external rotation; Beighton score; radiograph to exclude dysplasia (LCEA); MR arthrogram may show capsular attenuation or labral change | J14: Insufficient passive restraint from a lax or attenuated capsule and iliofemoral ligament, with inadequate dynamic control; repetitive end-range rotation in dance, gymnastics and yoga; generalised hypermobility; may coexist with borderline dysplasia | K14: Regain confident, controlled hip function through full sport or dance range without a sense of shifting | L14: Deep external rotator and gluteal strengthening 3-4 sets 8-12 RM 3x/week; lumbopelvic control (dead bug, Pallof press, side plank); closed-chain single-leg control and proprioception; iliopsoas and adductor co-contraction work; AVOID end-range passive stretching, which worsens it; graded return to end-range sport positions | M14: Nociceptive with apprehension and hypervigilance components | N14: Hip-related group; screen the Beighton score and the LCEA - borderline dysplasia (LCEA 20-25 degrees) changes the surgical decision entirely | O14: Screen: exclude frank acetabular dysplasia (LCEA under 20 degrees) - arthroscopy in a dysplastic hip accelerates instability | P14: REHABILITATION IS FIRST-LINE and usually successful. Build dynamic control the capsule cannot provide. Do NOT stretch. Surgery (capsular plication) only after a genuinely prolonged and well-delivered programme fails, and only once dysplasia has been excluded | Q14: Stage 1-4 over 12-24 weeks. Control work without load, then gluteal and deep rotator capacity, then closed-chain and functional loading, then sport or dance-specific range | R14: Build what the capsule cannot provide: deep external rotator and gluteal capacity, lumbopelvic control, closed-chain proprioception, and correct the habit of pushing into end-range passive positions in dance, yoga and gymnastics | S14: Taping for proprioceptive feedback; AVOID stretching and end-range mobilisation - the capsule is already lax | T14: Arthroscopic capsular plication with labral repair only after prolonged rehabilitation fails; PAO if borderline dysplasia is the dominant driver | U14: iHOT-33; HAGOS; Beighton score | V14: Dial test and apprehension response; single-leg control; gluteal and deep rotator strength; end-range tolerance | W14: 12-24 weeks minimum | X14: Confirmed dysplasia (refer for PAO opinion, not arthroscopy); failure after prolonged well-delivered rehabilitation | Y14: Hip microinstability literature; dysplasia and arthroscopy cautions
... A41: Systemic / Referred | B41: Post-arthroplasty patient of any activity level | C41: New or worsening hip pain after arthroplasty; may include instability, start-up pain, or systemic features | D41: 60+ | E41: Slow/Sudden | F41: Equal | G41: Post-Arthroplasty Complication | H41: Since the hip replacement, has NEW pain developed, or does the hip feel like it wants to give way or come out? | I41: Assess for infection (warmth, fever, wound issues, raised CRP and ESR), loosening (start-up pain, thigh pain, radiographic lucency), dislocation (sudden pain, deformity, shortening) and periprosthetic fracture. Radiograph; bloods; refer to the operating surgeon | J41: Not a rehabilitation problem in itself - infection, aseptic loosening, dislocation, periprosthetic fracture or abductor deficiency. Abductor weakness and violation of positional precautions contribute to dislocation risk | K41: Identify the complication, protect the prosthesis, and restore safe function | L41: NONE until the complication is identified. Post-management: abductor and quadriceps strengthening, gait retraining, balance work and adherence to any positional precautions | M41: Nociceptive; inflammatory if infected | N41: Systemic group; distinguish infection, loosening, dislocation, periprosthetic fracture and abductor deficiency - the management differs completely | O41: YES for suspected infection (warmth, fever, raised inflammatory markers), dislocation (sudden pain and deformity) or periprosthetic fracture - urgent surgical referral | P41: New pain after arthroplasty is a REFERRAL, not a rehabilitation problem, until the cause is established. Contact the operating surgeon. Once cleared, rehabilitation focuses on abductor strength, gait and balance | Q41: None until cleared. Post-clearance: progressive abductor, quadriceps and gluteal loading; balance and gait retraining | R41: Where abductor deficiency is the issue: progressive abductor loading, gait retraining to eliminate Trendelenburg, balance work; reinforce positional precautions relevant to the surgical approach | S41: Walking aid; positional precautions per approach (posterior approach: avoid flexion beyond 90 degrees with adduction and internal rotation) | T41: Revision surgery for loosening, infection or recurrent dislocation; two-stage revision for infection | U41: Oxford Hip Score; HOOS; Timed Up and Go | V41: Pain pattern; walking tolerance; abductor strength; Trendelenburg sign; inflammatory markers | W41: Determined by the complication and its management | X41: Any new post-arthroplasty pain - contact the operating surgeon before rehabilitating | Y41: Periprosthetic infection and loosening pathways

Sheet Rx Generator
A1: PRESCRIPTION GENERATOR
A2: Select a condition in the yellow cell. Every field below is pulled live from the Master Matrix.
A4: SELECT CONDITION → | B4: Greater Trochanteric Pain Syndrome (Gluteal Tendinopathy)
A6: Region | B6: =IFERROR(INDEX('Master Matrix'!A$4:A$41,MATCH($B$4,'Master Matrix'!$G$4:$G$41,0)),"") -> Lateral
A7: Activity level | B7: =IFERROR(INDEX('Master Matrix'!B$4:B$41,MATCH($B$4,'Master Matrix'!$G$4:$G$41,0)),"") -> Any activity level; walking, stairs and side-lying loaded. Peak incidence in post-menopausal women
A8: Common symptoms | B8: =IFERROR(INDEX('Master Matrix'!C$4:C$41,MATCH($B$4,'Master Matrix'!$G$4:$G$41,0)),"") -> Lateral hip pain, worse lying on the side, climbing stairs and single-leg standing
A9: Age group | B9: =IFERROR(INDEX('Master Matrix'!D$4:D$41,MATCH($B$4,'Master Matrix'!$G$4:$G$41,0)),"") -> 40-65
A10: Onset | B10: =IFERROR(INDEX('Master Matrix'!E$4:E$41,MATCH($B$4,'Master Matrix'!$G$4:$G$41,0)),"") -> Slow
A11: Predominance | B11: =IFERROR(INDEX('Master Matrix'!F$4:F$41,MATCH($B$4,'Master Matrix'!$G$4:$G$41,0)),"") -> Female
A12: High-yield diagnostic question | B12: =IFERROR(INDEX('Master Matrix'!H$4:H$41,MATCH($B$4,'Master Matrix'!$G$4:$G$41,0)),"") -> Does it hurt to lie on that side at night, and to climb stairs or stand on one leg?
A13: Special test + imaging | B13: =IFERROR(INDEX('Master Matrix'!I$4:I$41,MATCH($B$4,'Master Matrix'!$G$4:$G$41,0)),"") -> Tenderness over the greater trochanter PLUS pain on single-leg stance held for 30 seconds; positive FADER-R and ADD-R; ultrasound or MRI only if a tear is suspected or surgery is considered
A14: Underlying biomechanical cause | B14: =IFERROR(INDEX('Master Matrix'!J$4:J$41,MATCH($B$4,'Master Matrix'!$G$4:$G$41,0)),"") -> COMPRESSIVE plus tensile overload of the gluteus medius and minimus tendons against the greater trochanter, driven by hip ADDUCTION: standing in hip-hanging posture, crossing legs, side-lying without a pillow, and Trendelenburg gait from abductor weakness. Compression - not friction - is the mechanism, which is why the bursitis label misleads
A15: DESIRED ACTIVITY GOAL | B15: =IFERROR(INDEX('Master Matrix'!K$4:K$41,MATCH($B$4,'Master Matrix'!$G$4:$G$41,0)),"") -> Sleep on the affected side, climb stairs and stand on one leg without lateral hip pain
A16: PHYSIOTHERAPY SPECIFIC EXERCISE | B16: =IFERROR(INDEX('Master Matrix'!L$4:L$41,MATCH($B$4,'Master Matrix'!$G$4:$G$41,0)),"") -> ISOMETRIC abductor holds (supine isometric abduction) 5 x 30-45 s for analgesia; progressive abductor loading in NEUTRAL, avoiding adduction (supine isometric abduction, side-lying abduction to neutral only, standing hip hitch, offset squat, single-leg bridge) 3-4 sets 8-12 RM 3x/week; gluteus maximus loading; gait and standing posture retraining; sleeping position with a pillow between the knees
A17: Pain mechanism | B17: =IFERROR(INDEX('Master Matrix'!M$4:M$41,MATCH($B$4,'Master Matrix'!$G$4:$G$41,0)),"") -> Nociceptive - compressive plus tensile tendon load
A18: Classification / cluster | B18: =IFERROR(INDEX('Master Matrix'!N$4:N$41,MATCH($B$4,'Master Matrix'!$G$4:$G$41,0)),"") -> Cluster - GTPS / gluteal tendinopathy. The term 'trochanteric bursitis' is misleading; bursal change is secondary. Stage on the tendinopathy continuum
A19: RED FLAG STATUS | B19: =IFERROR(INDEX('Master Matrix'!O$4:O$41,MATCH($B$4,'Master Matrix'!$G$4:$G$41,0)),"") -> No
A20: MANAGEMENT EMPHASIS | B20: =IFERROR(INDEX('Master Matrix'!P$4:P$41,MATCH($B$4,'Master Matrix'!$G$4:$G$41,0)),"") -> EDUCATION PLUS PROGRESSIVE ABDUCTOR LOADING with strict avoidance of hip ADDUCTION positions. The LEAP trial showed education plus exercise outperformed corticosteroid injection and wait-and-see at 8 weeks AND at 12 months. Injection gives short-term relief only
A21: Loading stage & entry dose | B21: =IFERROR(INDEX('Master Matrix'!Q$4:Q$41,MATCH($B$4,'Master Matrix'!$G$4:$G$41,0)),"") -> Stage 1-2. Isometric abductor holds for analgesia; progressive abductor loading IN NEUTRAL 3-4 sets 8-12 RM 3x/week; avoid adduction-loaded exercises such as clamshells in adduction and crossed-leg stretching
A22: BIOMECHANICAL CORRECTIONS & KINETIC CHAIN | B22: =IFERROR(INDEX('Master Matrix'!R$4:R$41,MATCH($B$4,'Master Matrix'!$G$4:$G$41,0)),"") -> REMOVE THE COMPRESSION, then load: stop standing in hip-hanging posture and crossing the legs, use a pillow between the knees at night, avoid ITB stretching and foam rolling over the trochanter, correct Trendelenburg gait and pelvic drop with abductor strengthening, address step width and stair strategy
A23: Manual therapy, positional & adjuncts | B23: =IFERROR(INDEX('Master Matrix'!S$4:S$41,MATCH($B$4,'Master Matrix'!$G$4:$G$41,0)),"") -> Sleeping position advice and a pillow between the knees are among the highest-yield interventions; AVOID ITB stretching and rolling over the trochanter; taping is of limited value
A24: Advanced / surgical options | B24: =IFERROR(INDEX('Master Matrix'!T$4:T$41,MATCH($B$4,'Master Matrix'!$G$4:$G$41,0)),"") -> Guided corticosteroid injection gives short-term relief only and is inferior to education plus exercise at 12 months; ESWT as an adjunct in refractory cases; surgical gluteal tendon repair for a confirmed full-thickness tear
A25: Outcome measures | B25: =IFERROR(INDEX('Master Matrix'!U$4:U$41,MATCH($B$4,'Master Matrix'!$G$4:$G$41,0)),"") -> VISA-G; HOOS; Oxford Hip Score; NPRS on side-lying and stairs
A26: Re-testable markers | B26: =IFERROR(INDEX('Master Matrix'!V$4:V$41,MATCH($B$4,'Master Matrix'!$G$4:$G$41,0)),"") -> Side-lying tolerance; single-leg stance time to pain; stair pain; abductor strength LSI; trochanteric tenderness
A27: Expected timeline | B27: =IFERROR(INDEX('Master Matrix'!W$4:W$41,MATCH($B$4,'Master Matrix'!$G$4:$G$41,0)),"") -> 12 weeks for meaningful change; 3-6 months for full resolution
A28: Referral / surgical trigger | B28: =IFERROR(INDEX('Master Matrix'!X$4:X$41,MATCH($B$4,'Master Matrix'!$G$4:$G$41,0)),"") -> Suspected full-thickness gluteal tendon tear (marked weakness, Trendelenburg); failure after a well-delivered 12-week programme
A29: Evidence anchor | B29: =IFERROR(INDEX('Master Matrix'!Y$4:Y$41,MATCH($B$4,'Master Matrix'!$G$4:$G$41,0)),"") -> LEAP trial (Mellor BMJ 2018); Grimaldi & Fearon JOSPT 2015
A31: NOTES
A32: • Green text is pulled from the Master Matrix — edit the matrix, not this sheet.
A33: • Check RED FLAG STATUS first. A crimson entry means screen or refer before rehabilitating.
A34: • The DESIRED ACTIVITY GOAL and PHYSIOTHERAPY SPECIFIC EXERCISE rows are written to be handed straight to the patient.
A35: • Print this sheet (portrait, fit to one page wide) for the patient file.

Sheet Assessment Roadmap
A1: FIVE-GATE ASSESSMENT ROADMAP
A2: Work top to bottom. Gate 3 — pain, stiffness or instability — does most of the diagnostic work.
A3: Gate | B3: Purpose | C3: What You Assess | D3: Findings That Matter | E3: Decision Rule
A4: GATE 1 | B4: Screen for serious pathology | C4: High-risk bone stress; fracture; septic joint; malignancy; AVN; visceral referral; paediatric emergencies | D4: TENSION-side femoral neck stress fracture (groin pain now present on walking) is an emergency. Hip fracture after a fall (shortened, externally rotated leg). Hot, painful hip with fever = sepsis. Constant non-mechanical night pain with systemic features or cancer history = malignancy. Progressive rest and night pain with corticosteroid or alcohol history = AVN. ADOLESCENT WITH HIP OR KNEE PAIN AND A LIMP = SCFE until excluded | E4: If present -> investigate or refer BEFORE local treatment
A5: GATE 2 | B5: Screen the lumbar spine and pelvis | C5: Lumbar range and provocation; straight leg raise and slump; sacroiliac provocation cluster; neurological screen | D5: The lumbar spine refers to the buttock, groin and thigh constantly. Symptoms changed more by SPINE than by HIP movement, with negative hip provocation tests, points to a lumbar source. HIP-SPINE SYNDROME is common - both may be contributing and both may need treatment. Screen for inflammatory back pain features in the young adult | E5: Clear the spine and pelvis BEFORE committing to a hip diagnosis
A6: GATE 3 | B6: Anterior, lateral, posterior or medial? | C6: Localise the pain generator by region, then by structure, then by mechanism | D6: ANTERIOR/GROIN: intra-articular (FAI, labrum, OA, AVN), iliopsoas, adductor, inguinal, pubic, femoral neck. LATERAL: gluteal tendinopathy (GTPS), bursa, snapping ITB, lateral femoral cutaneous nerve. POSTERIOR: proximal hamstring, deep gluteal, ischiofemoral, sacroiliac, lumbar referral. MEDIAL/PUBIC: adductor and pubic-related. The C-SIGN (gripping the hip with a C-shaped hand) suggests an intra-articular source | E6: Map pain to region -> structure -> mechanism
A7: GATE 4 | B7: Cluster to a working diagnosis | C7: History + palpation + provocation + the Doha groin classification | D7: Cluster 1 FAI syndrome (Warwick): symptoms AND clinical signs AND imaging findings - all three. Cluster 2 Adductor-related (Doha): adductor tenderness AND pain on resisted adduction. Cluster 3 GTPS: lateral hip pain + trochanteric tenderness + pain on 30-second single-leg stance. Cluster 4 Sacroiliac: 3 or more of 5 provocation tests positive | E7: Clustering beats any single test. In groin pain, use the Doha entity classification - more than one entity commonly coexists
A8: GATE 5 | B8: Quantify impairments and capacity | C8: Range (especially internal rotation); hip abductor and adductor strength; squeeze test; single-leg control; gait | D8: Hip internal rotation range at 90 degrees flexion (lost early in FAI and OA); ADDUCTOR SQUEEZE FORCE at 0, 45 and 90 degrees; hip abductor strength and the adduction:abduction ratio; 30-second single-leg stance; Trendelenburg sign; single-leg squat and step-down quality; sitting tolerance | E8: These become the baseline re-testable markers that drive the plan and, for athletes, return-to-sport testing
A10: DIAGNOSTIC ALGORITHM — NARRATIVE FLOW
A11: • Hip or groin pain → Red flags? YES: image or refer. NO ↓
A12: • Referred from the lumbar spine? YES: treat the lumbar source (and screen for hip-spine syndrome). NO ↓
A13: • Which region?
A14: • ANTERIOR / GROIN → C-sign with deep flexion and sitting, restricted internal rotation = intra-articular (FAI, labrum, OA, AVN). Resisted adduction pain = adductor-related. Resisted hip flexion pain = iliopsoas-related. Central pubic tenderness = pubic-related. Cough or Valsalva pain = inguinal-related. Pain now on WALKING in a runner = femoral neck stress fracture.
A15: • LATERAL → unable to lie on that side with trochanteric tenderness and positive 30-second single-leg stance = GTPS. Marked weakness with Trendelenburg = gluteal tendon tear. Burning and numbness with no weakness = meralgia paraesthetica.
A16: • POSTERIOR → ischial pain worst on SITTING = proximal hamstring tendinopathy. Deep buttock pain with leg symptoms and negative lumbar screen = deep gluteal syndrome. Pain on LONG STRIDES = ischiofemoral impingement. Three or more provocation tests positive = sacroiliac.
A17: • PAEDIATRIC → adolescent with hip or knee pain and a limp = SCFE. Child with a limp and limited abduction = Perthes. Unwell febrile child = septic arthritis. Sudden pop in an adolescent = apophyseal avulsion.
A18: • Confirm with the impairment and capacity profile → set baseline markers → enter the Phased Programme.
A20: CLINICAL PEARL
A21: • Convert every diagnosis into two or three re-testable markers BEFORE you treat — hip internal rotation range, adductor squeeze figure, 30-second single-leg stance, or sitting tolerance.
A22: • If those markers do not improve over 4-6 weeks of appropriate loading, revisit the diagnosis, re-screen the lumbar spine, and check whether a compressive position is still being loaded.

Sheet Subjective Exam
A1: SUBJECTIVE EXAMINATION TEMPLATE
A2: Yellow column is the input column. A structured history alone points to the diagnosis in most shoulder presentations.
A3: Domain | B3: What to Ask | C3: Why It Matters | D3: Findings (fill in)
A4: Onset & mechanism | B4: Insidious/overuse or traumatic? Kicking, cutting, sprinting, a fall, or no clear event? | C4: Insidious points to FAI, tendinopathy, OA or bone stress; sudden points to strain, avulsion or fracture | D4: e.g. insidious over 3 months, after increasing running from 20 to 45 km/week
A5: Age & context | B5: Age; occupation; sport and level; training volume and recent change | C5: Age transforms the differential: SCFE and Perthes in children, FAI and groin pain in young adults, OA and gluteal tendinopathy in the older adult
A6: Pain location | B6: Point with one finger. Groin / lateral / posterior / pubic. Do they grip the hip in a C-shape? | C6: The C-SIGN suggests an intra-articular source. Groin = intra-articular or muscle-related. Lateral = gluteal tendon. Posterior = hamstring, deep gluteal or lumbar
A7: Radiation | B7: Does it travel down the leg? Any numbness or pins and needles? | C7: Leg symptoms with a positive lumbar screen point to the spine, not the hip; burning over the outer thigh with no weakness suggests meralgia paraesthetica
A8: Aggravating movements | B8: Deep squatting, prolonged sitting, kicking, cutting, stairs, single-leg standing, lying on the side, long strides | C8: Sitting = FAI or proximal hamstring. Lying on the side = GTPS. Kicking = adductor or iliopsoas. Long strides = ischiofemoral
A9: SITTING TOLERANCE | B9: How long can you sit before it hurts? Hard or soft chair? Car journeys? | C9: The defining functional limitation in proximal hamstring tendinopathy, and a major one in FAI
A10: NIGHT PAIN & SIDE-LYING | B10: Can you lie on that side? Do you sleep with a pillow between the knees? | C10: Inability to lie on the side is the hallmark of GTPS; the pillow question leads straight into the highest-yield early intervention
A11: Load & training change | B11: Recent change in running volume, cutting or kicking load, gym content, or walking volume | C11: Almost every atraumatic hip and groin presentation is a load change on an unprepared hip
A12: LUMBAR SCREEN | B12: Any back pain or stiffness? Does moving your back change the hip pain? Any leg symptoms? | C12: GATE 2 — the lumbar spine refers to the buttock, groin and thigh constantly. Hip-spine syndrome is common
A13: RED FLAG SCREEN | B13: Groin pain now present on walking? Constant night pain unrelated to movement? Weight loss or cancer history? Fever or unwell? Corticosteroid or alcohol history? A fall with inability to weight-bear? Bladder or bowel change? | C13: GATE 1 — bone stress, fracture, sepsis, malignancy, AVN and cauda equina all present as hip pain
A14: PAEDIATRIC SCREEN | B14: In a child or adolescent: is there a limp? Any KNEE pain? Recent illness? Is the child systemically well? | C14: AN ADOLESCENT WITH HIP OR KNEE PAIN AND A LIMP IS SCFE UNTIL EXCLUDED. A febrile child refusing to weight-bear is septic until excluded
A15: Bone health & energy availability | B15: In athletes: menstrual history, dietary intake relative to training, previous bone stress injury, stress fracture history | C15: Low energy availability is the central driver of bone stress injury and is highly prevalent in running, dance and gymnastics
A16: Hypermobility | B16: Do your joints feel loose? Were you very flexible as a child? Any dance, gymnastics or yoga background? | C16: Hypermobility REVERSES the approach in microinstability and dysplasia — stretching makes it worse. Record a Beighton score
... A19: Goals | B19: What do you want to get back to — specifically? | C19: Feeds directly into the DESIRED ACTIVITY GOAL column of the Master Matrix
A21: HOW TO FILL THIS SHEET
A22: • Row 4 shows an example entry in grey — overwrite it.
A23: • Three questions triage most hip and groin pain fast: "Can you point to it with one finger?", "What brings it on — sitting, kicking, standing on one leg, lying on it?", and "Does moving your back change it?"
A24: • In anyone under 18 with hip OR knee pain and a limp, stop and consider SCFE and Perthes before anything else.

Sheet Objective Exam
A1: PHYSICAL EXAMINATION TEMPLATE
A2: Yellow columns are input columns. Two distinctions organise the whole examination — see the note at the foot of the sheet.
A3: Section | B3: Item | C3: How to Test / What to Look For | D3: Involved (fill in) | E3: Uninvolved (fill in) | F3: Interpretation
A4: Observation | B4: Standing posture & pelvic position | C4: Anterior pelvic tilt, pelvic obliquity, lumbar lordosis, standing on one hip | D4: e.g. anterior tilt, stands on right hip | E4: similar | F4: Standing hanging on one hip is a direct compressive driver in GTPS
A5: Observation | B5: Muscle bulk | C5: Gluteal bulk and symmetry; quadriceps and hamstring bulk | F5: Gluteal wasting is common and is the main rehabilitation target across most hip diagnoses
A6: Observation | B6: GAIT | C6: Antalgia, Trendelenburg or compensated Trendelenburg, stride length, step width, foot progression angle | F6: Trendelenburg indicates abductor deficiency; a long stride pattern provokes ischiofemoral impingement
A7: Observation | B7: Leg length | C7: Real and apparent leg length | F7: Relevant post-arthroplasty and in sacroiliac and pelvic girdle presentations
A8: Palpation | B8: Greater trochanter | C8: Focal tenderness over the gluteal tendon insertion | F8: GTPS — cluster with the 30-second single-leg stance test
A9: Palpation | B9: Adductor longus origin | C9: Focal tenderness at the enthesis | F9: Adductor-related groin pain (Doha criterion)
A10: Palpation | B10: Pubic symphysis & adjacent bone | C10: Central tenderness | F10: Pubic-related groin pain (Doha criterion)
A11: Palpation | B11: Inguinal canal | C11: Tenderness; NO palpable hernia | F11: Inguinal-related groin pain (Doha criterion)
A12: Palpation | B12: Iliopsoas | C12: Tenderness lateral to the femoral pulse | F12: Iliopsoas-related groin pain (Doha criterion)
A13: Palpation | B13: Ischial tuberosity | C13: Focal tenderness | F13: Proximal hamstring tendinopathy
A14: Palpation | B14: Sacroiliac region / PSIS | C14: Tenderness; Fortin finger test | F14: Sacroiliac joint-related pain
A15: Range (passive) | B15: Hip flexion (degrees) | C15: Supine, pelvis stabilised | F15: Compare sides
A16: Range (passive) | B16: INTERNAL ROTATION at 90 deg flexion | C16: Supine, hip and knee at 90 degrees, pelvis stabilised | D16: e.g. 15 | E16: 35 | F16: THE most important single measurement — lost earliest in FAI and hip OA
A17: Range (passive) | B17: External rotation at 90 deg flexion | C17: Supine, pelvis stabilised | F17: Excess rotation suggests capsular laxity or microinstability
A18: Range (passive) | B18: Hip extension (Thomas test) | C18: Thomas test position; note hip flexor and rectus femoris length | F18: Restricted extension drives anterior pelvic tilt and iliopsoas overload
A19: Range (passive) | B19: Abduction (degrees) | C19: Supine, pelvis stabilised | F19: THE key measure in Perthes and in paediatric DDH
A20: Strength | B20: ADDUCTOR SQUEEZE (0, 45, 90 deg) | C20: Sphygmomanometer or dynamometer between the knees — RECORD THE FIGURE | F20: Simultaneously diagnostic, the treatment target and the discharge criterion in all groin presentations
A21: Strength | B21: Hip abduction (kg) | C21: Handheld dynamometry in side-lying or supine | F21: Feeds the LSI and the adduction:abduction ratio in the Progress Tracker
A22: Strength | B22: Hip adduction (kg) | C22: Handheld dynamometry | F22: Feeds the adduction:abduction ratio — a low ratio predicts groin injury
A23: Strength | B23: Hip extension (kg) | C23: Handheld dynamometry or single-leg bridge repetitions | F23: Gluteus maximus capacity
A24: Strength | B24: Hip flexion (kg) | C24: Handheld dynamometry | F24: Iliopsoas capacity; also relevant post-psoas surgery
A25: Control | B25: 30-SECOND SINGLE-LEG STANCE | C25: Time to pain onset; observe for pelvic drop | F25: The primary GTPS test AND the primary re-test marker
A26: Control | B26: Single-leg squat / step-down quality | C26: Pelvic drop, dynamic valgus, trunk lean; grade good / fair / poor | F26: Frontal-plane control — the treatment target across most hip diagnoses
A27: Control | B27: Trendelenburg sign | C27: Pelvic drop on the contralateral side in single-leg stance | F27: Marked drop with weakness suggests a gluteal tendon tear rather than tendinopathy
A28: Special tests | B28: FADIR (anterior impingement) | C28: See Special Tests sheet | F28: Highly SENSITIVE — a negative test makes intra-articular pathology unlikely
... A40: Function | B40: Functional tasks | C40: Sit-to-stand, stair climbing, sock test, squat depth | F40: What the patient actually cares about — use as re-test markers
A42: HOW TO FILL THIS SHEET
A43: • THREE MEASUREMENTS DO MOST OF THE WORK IN THE HIP: internal rotation at 90 degrees flexion (earliest change in FAI and OA), the ADDUCTOR SQUEEZE FIGURE (all groin presentations), and the 30-SECOND SINGLE-LEG STANCE (GTPS and abductor capacity). Record all three in every hip.
A44: • Stabilise the pelvis when measuring hip rotation, or the reading includes lumbopelvic movement and is meaningless.
A45: • In every child and adolescent, perform passive hip flexion and watch for obligatory external rotation — it takes five seconds and it is how SCFE is caught.
A46: • Transfer range, squeeze and strength figures into the Progress Tracker, which calculates symmetry and the adduction:abduction ratio automatically.
A47: • Row 4 shows an example entry in grey — overwrite it.

Sheet Special Tests
A1: SPECIAL TESTS
A2: No single shoulder test is definitive. Many named "impingement" tests are sensitive but not specific — read them as symptom provocation, not structure identification.
A3: Category | B3: Test | C3: Targets | D3: Positive Finding | E3: Clinical Note
A4: Intra-articular | B4: FADIR / anterior impingement test | C4: FAI syndrome, labral tear, intra-articular | D4: Reproduction of the patient's anterior groin pain | E4: Highly SENSITIVE - a negative test makes intra-articular pathology unlikely. Poor specificity
A5: Intra-articular | B5: FABER (Patrick's) test | C5: Intra-articular, sacroiliac | D5: Groin pain (hip) or posterior pain (sacroiliac); measure knee-to-couch distance | E5: Localise WHERE the pain is felt - it differentiates hip from sacroiliac
A6: Intra-articular | B6: Hip internal rotation at 90 deg flexion | C6: FAI syndrome, hip OA | D6: Reduced range compared with the other side | E6: The EARLIEST measurable change in both FAI and hip OA - measure it in every hip
A7: Intra-articular | B7: Log roll test | C7: Intra-articular; capsular laxity | D7: Pain or excess rotation with passive femoral rotation | E7: The most specific test for an intra-articular source; excess rotation suggests microinstability
A8: Intra-articular | B8: Scour / quadrant test | C8: Intra-articular, chondral | D8: Pain or catching through the arc | E8: Uncomfortable in normal hips - interpret cautiously
A9: Intra-articular | B9: Hip apprehension (extension + external rotation) | C9: Microinstability, dysplasia | D9: Apprehension rather than pain | E9: Positive apprehension should prompt measurement of the lateral centre-edge angle
A10: Groin / Adductor | B10: Adductor squeeze test (0, 45 and 90 deg) | C10: Adductor-related groin pain | D10: Pain and reduced force; RECORD THE FIGURE in mmHg or Newtons | E10: Both a diagnostic test and the primary re-test marker - record it every time
A11: Groin / Adductor | B11: Adductor origin palpation | C11: Adductor-related groin pain | D11: Local tenderness at the adductor longus enthesis | E11: Part of the Doha diagnostic criteria
A12: Groin / Iliopsoas | B12: Resisted hip flexion / Thomas test | C12: Iliopsoas-related groin pain | D12: Pain on resistance; restricted extension on Thomas | E12: Part of the Doha criteria
A13: Groin / Pubic | B13: Pubic symphysis palpation | C13: Pubic-related groin pain | D13: Local tenderness over the symphysis and adjacent bone | E13: Part of the Doha criteria
A14: Groin / Inguinal | B14: Resisted sit-up and Valsalva | C14: Inguinal-related groin pain | D14: Inguinal pain on resistance and on cough | E14: A diagnosis of exclusion - rule out hernia and other entities first
... A34: Lumbar / Neural | B34: Lumbar range and provocation | C34: Lumbar referred pain | D34: Symptoms changed more by spine than by hip movement | E34: The key discriminator between lumbar and hip sources

Sheet Clusters & Doha
A1: DIAGNOSTIC CLUSTERS & THE DOHA CLASSIFICATION
A2: Clustering beats any single test. In athletic groin pain, use the Doha entity classification — more than one entity commonly coexists.
A3: Cluster | B3: Feature 1 | C3: Feature 2 | D3: Feature 3 | E3: Working Diagnosis
A4: CLUSTER 1 | B4: Anterior groin pain with deep flexion, pivoting and prolonged sitting; the C-sign | C4: Positive FADIR (anterior impingement) test with restricted internal rotation at 90 degrees flexion | D4: Cam or pincer morphology on radiograph (alpha angle, lateral centre-edge angle) | E4: FAI syndrome - ALL THREE required (Warwick Agreement)
A5: CLUSTER 2 | B5: Groin pain with kicking, sprinting and change of direction | C5: Tenderness at the adductor longus origin | D5: Pain on resisted adduction; reduced adductor squeeze force | E5: Adductor-related groin pain (Doha)
A6: CLUSTER 3 | B6: Lateral hip pain, unable to lie on that side at night | C6: Tenderness over the greater trochanter | D6: Pain reproduced by 30-second single-leg stance | E6: Greater trochanteric pain syndrome (gluteal tendinopathy)
A7: CLUSTER 4 | B7: Posterior pelvic pain below the PSIS, worse on single-leg loading and transitions | C7: Three or more of five provocation tests positive (distraction, thigh thrust, compression, sacral thrust, Gaenslen) | D7: Negative lumbar screen; Fortin finger test positive | E7: Sacroiliac joint-related pain (Laslett cluster)
A8: CLUSTER 5 | B8: Deep buttock pain at the ischial tuberosity, worse with sitting and hill running | C8: Tenderness at the ischial tuberosity | D8: Pain on the bent-knee stretch and long-lever bridge tests | E8: Proximal hamstring tendinopathy
A9: CLUSTER 6 | B9: Adolescent with hip, thigh OR KNEE pain and a limp | C9: OBLIGATORY external rotation on passive hip flexion | D9: Slip visible on the frog-lateral radiograph (Klein's line) | E9: Slipped capital femoral epiphysis - EMERGENCY
A11: THE ONE-LINE DIFFERENTIATORS
A12: • Anterior groin pain with deep flexion and sitting, plus the C-sign = intra-articular (FAI, labrum, OA)
A13: • Loss of hip INTERNAL ROTATION at 90 degrees flexion is the earliest sign of both FAI and hip OA
A14: • Groin pain on resisted adduction with adductor origin tenderness = adductor-related (Doha)
A15: • Central pubic tenderness with bilateral symptoms = pubic-related (osteitis pubis)
A16: • Lateral hip pain and unable to lie on that side = gluteal tendinopathy (GTPS), not 'bursitis'
A17: • Deep buttock pain worst on SITTING = proximal hamstring tendinopathy
A18: • Deep buttock pain with leg symptoms and a NEGATIVE lumbar screen = deep gluteal syndrome
A19: • Deep posterior hip pain on LONG STRIDES = ischiofemoral impingement
A20: • Groin pain now present on WALKING in a runner = femoral neck stress fracture until excluded
A21: • ADOLESCENT with hip OR KNEE pain and a limp = SCFE until excluded
A22: • Constant non-mechanical night pain with systemic features = refer, do not rehabilitate
A24: Doha Entity | B24: Defining Criteria | C24: Management Emphasis | D24: Note
A25: Adductor-related | B25: Adductor tenderness AND pain on resisted adduction | C25: Copenhagen adduction programme; restore the adduction:abduction ratio | D25: The commonest single entity in athletic groin pain
A26: Iliopsoas-related | B26: Iliopsoas tenderness, with pain on resisted hip flexion and/or on stretching the hip flexors | C26: Progressive hip flexor loading; correct anterior pelvic tilt and gluteal deficit | D26: Often coexists with adductor-related pain
A27: Inguinal-related | B27: Inguinal canal tenderness and pain, with NO palpable hernia; worse on Valsalva | C27: Abdominal and lumbopelvic loading; surgical repair for refractory cases | D27: A diagnosis of exclusion
A28: Pubic-related | B28: Local tenderness of the pubic symphysis and the immediately adjacent bone | C28: Adductor and abdominal loading to rebalance forces across the symphysis | D28: The slowest entity - set a 3-6 month expectation
A29: Hip-related | B29: Intra-articular source: FAI syndrome, labral tear, dysplasia, chondral lesion, OA | C29: Gluteal and lumbopelvic loading; surgical opinion for defined structural indications | D29: Always consider - and always establish the underlying morphology
A30: Other causes | B30: Bone stress, nerve entrapment, referred lumbar or visceral, inflammatory, paediatric | C30: Determined by the entity | D30: The Doha classification explicitly reminds you to think beyond the four muscle-related entities
A32: CLINICAL PEARL
A33: • The Doha agreement replaced a confusing vocabulary (osteitis pubis, sportsman hernia, Gilmore groin) with defined clinical ENTITIES. Name the entity, and the management follows.
A34: • MORE THAN ONE ENTITY COMMONLY COEXISTS in the same athlete — adductor-related and iliopsoas-related pain travel together, and both may need treating.
A35: • Always ask whether the source is HIP-RELATED (intra-articular) before settling on a muscle-related entity — and if it is, establish the underlying morphology.

Sheet Imaging Guide
A1: IMAGING GUIDE
A2: Most shoulder pain is a clinical diagnosis. Image to answer a specific question — not to confirm an obvious RCRSP or frozen shoulder.
A3: Modality | B3: When to Request | C3: What It Answers | D3: Interpretation Caution
A4: Clinical examination alone | B4: The majority of atraumatic hip and groin presentations | C4: GTPS, adductor-related groin pain, proximal hamstring tendinopathy, sacroiliac pain, hip OA in the over-45s (NICE) | D4: Most hip and groin pain is a clinical diagnosis. NICE permits diagnosing hip OA clinically without imaging in the over-45s
A5: Weight-bearing AP pelvis radiograph | B5: Suspected OA, FAI morphology, dysplasia, fracture, SCFE, Perthes | C5: Joint space, osteophytes, alpha angle, LATERAL CENTRE-EDGE ANGLE, physeal position | D5: MUST be weight-bearing for joint space assessment. ALWAYS measure the LCEA - missing dysplasia before arthroscopy is a serious error
A6: Dunn lateral / frog-lateral radiograph | B6: Cam morphology; SCFE | C6: Alpha angle (cam morphology); Klein's line for slip | D6: The frog-lateral is essential in suspected SCFE - a slip can be invisible on the AP view alone
A7: MRI | B7: Bone stress injury; AVN; muscle and tendon injury; occult fracture; malignancy | C7: Marrow oedema, tendon pathology, muscle injury grading, subchondral changes | D7: THE test for a suspected femoral neck stress fracture and for AVN - radiographs are insensitive early and give false reassurance
A8: MR arthrogram | B8: Labral pathology; ligamentum teres; capsular assessment | C8: Labral tear, chondrolabral junction, capsular integrity | D8: The imaging standard for the labrum - plain MRI misses tears. But labral change is common in ASYMPTOMATIC hips
A9: Ultrasound | B9: Gluteal tendons; iliopsoas snapping; bursae; guiding injection | C9: Tendon pathology, dynamic snapping, bursal distension, effusion | D9: Dynamic assessment of snapping hip is where ultrasound excels. Operator-dependent
A10: CT | B10: Bony detail; version and torsion; fracture planning; surgical planning | C10: Femoral and acetabular version, bone loss, fracture configuration | D10: Femoral and acetabular VERSION are increasingly recognised drivers in hip pain and are not visible on plain films
A11: Ultrasound-guided aspiration | B11: Suspected septic arthritis of the hip | C11: Cell count, Gram stain, culture | D11: URGENT where sepsis is suspected - the hip is deep and clinical signs are less obvious than in superficial joints
A12: DXA | B12: Recurrent bone stress injury; fragility fracture; RED-S features | C12: Bone mineral density Z or T score | D12: Mandatory after a fragility fracture and in recurrent bone stress injury
A14: WHEN TO IMAGE
A15: • Trauma with suspected fracture, dislocation or acute cuff tear
A16: • Suspected surgical pathology (significant cuff tear, structural instability, advanced OA)
A17: • Red flags for malignancy, infection or an atypical presentation
A18: • Failure to respond to appropriate loaded rehabilitation
A20: RED FLAG — IMAGING INTERPRETATION
A21: • Structural findings are extremely common in PAIN-FREE shoulders — cuff tears (especially degenerative), labral change and acromial variants appear on imaging in many asymptomatic people, rising steeply with age.
A22: • Acromiohumeral distance and "impingement" morphology correlate POORLY with pain.
A23: • A scan finding does not by itself explain the patient's pain — treat the patient, not the scan.
A24: • Reframing imaging findings for the patient is itself a high-value intervention.

Sheet Phased Programme
A1: PHASED MANAGEMENT PROGRAMME
A2: Progress by capacity, not calendar — and match intensity to irritability.
A3: Phase | B3: Name | C3: Typical Timing | D3: Goal | E3: Content | F3: Markers Tracked | G3: Exit Criteria
A4: Phase 0 | B4: Screen & Settle | C4: 0 - as required | D4: Exclude serious pathology; clear the lumbar spine; settle irritability; protect where bone stress or structural pathology exists | E4: Red flag and lumbar screen; grade irritability; pain control; protected or non-weight bearing where indicated; low-load isometric gluteal and adductor work for analgesia; maintain general conditioning; EDUCATION on the load-capacity model and realistic timelines | F4: Weight-bearing status; pain at rest and night; available pain-free range; irritability grade | G4: Serious pathology excluded; irritability settling; the patient understands the diagnosis, the plan and the timeline
A5: Phase 1 | B5: Restore Motion & Activate | C5: Weeks 0-4 | D5: Restore range appropriate to the diagnosis; activate the gluteals; establish lumbopelvic control | E5: Range work matched to the diagnosis (NOT end-range in dysplasia or microinstability); isometric gluteal and adductor holds 5 x 30-45 s for analgesia; lumbopelvic control (dead bug, bird-dog, side plank); low-load isotonic gluteal and adductor work; gait quality work | F5: Hip internal rotation range; adductor squeeze figure; single-leg stance tolerance; gluteal activation | G5: Pain-free or acceptable-pain loading established; lumbopelvic control demonstrated; gait quality improving
A6: Phase 2 | B6: Build Capacity | C6: Weeks 4-12 | D6: Build gluteal, adductor and lumbopelvic strength through functional range | E6: Progressive gluteal loading (hip thrust, split squat, step-up, side-lying abduction, banded lateral walk) 3-4 sets 8-12 RM 2-3x/week; COPENHAGEN ADDUCTION for adductor and pubic-related presentations; heavy slow resistance for tendinopathies; deep rotator control; endurance as well as peak strength | F6: Hip abductor and adductor strength LSI; adduction:abduction ratio; adductor squeeze figure; single-leg squat control | G6: Strength LSI >=80%; adduction:abduction ratio restored; controlled single-leg loading without pelvic drop
A7: Phase 3 | B7: Power, Impact & Change of Direction | C7: Weeks 8-20 | D7: Restore impact tolerance, deceleration capacity and rate of force development | E7: Progressive running or walking volume via a graded programme; hopping, bounding and landing drills; deceleration and change-of-direction preparation; continued heavy strength work 2x/week; sport-specific movement patterns at sub-maximal intensity | F7: Running or walking volume tolerance; hop symmetry; landing and change-of-direction quality | G7: Impact and running progression completed without symptom escalation; no pelvic drop or dynamic valgus on landing
A8: Phase 4 | B8: Sport / Function-Specific & Discharge | C8: Weeks 12+ (6-12 months post surgery) | D8: Replicate sport, work and life demands and prove readiness | E8: Sport-specific drills: cutting, kicking, sprinting, contact progression; occupational task simulation; graded return with load monitoring (acute:chronic workload, kicking and sprint volume); prevention programme embedded | F8: Full return-to-sport battery; adductor squeeze figure; sport-specific volume tolerance | G8: Strength LSI >=90%; adductor squeeze symmetrical; sport or work progression completed; confidence restored
A10: MASTER TREATMENT ALGORITHM
A11: • CONFIRM the diagnosis and set re-testable markers (internal rotation range, adductor squeeze figure, single-leg stance tolerance, walking tolerance)
A12: • EDUCATE: load-capacity model, imaging reframing, realistic timelines, positional and activity modification
A13: • CORE CARE (0-12 weeks): progressive gluteal and lumbopelvic loading, entity-specific loading (Copenhagen for adductors, neutral-range abduction for GTPS), gait retraining
A14: • REASSESS at 4-6 weeks against baseline markers. Improving -> progress toward impact and sport-specific loading. Not improving -> audit adherence, dosage, positional compression and the diagnosis
A15: • STALLED (>8-12 weeks): consider ESWT for recalcitrant tendinopathy, a guided injection to enable loading, or a diagnostic block; RE-SCREEN red flags, the lumbar spine and bone health
A16: • SURGICAL INDICATION: refer for defined indications (dysplasia, failed FAI rehabilitation, full-thickness gluteal tear, end-stage OA, AVN, any high-risk bone stress lesion)
A17: • TIME-SENSITIVE EXCEPTIONS that bypass this sequence entirely: tension-side femoral neck stress fracture, SCFE, septic arthritis, hip fracture, and symptomatic dysplasia in a young adult
A19: PRINCIPLES OF LOAD MANAGEMENT
A20: • Relative, not complete, rest — de-loaded tissue and muscle lose capacity quickly.
A21: • MATCH INTENSITY TO IRRITABILITY. Highly irritable shoulders (including the painful stage of frozen shoulder) need gentler, pain-guided input; low-irritability shoulders tolerate progressive loading.
A22: • For RCRSP, loading INTO ACCEPTABLE PAIN (<=5/10 settling within 24 h) is safe and effective — pain-free is NOT required, and waiting for pain-free movement delays progress.
... A24: • Progress by capacity, not calendar; treat the scapula and kinetic chain, not just the glenohumeral joint.

Sheet Exercise & Dosage
A1: EXERCISE PRESCRIPTION & DOSAGE LIBRARY
A2: Match the diagnosis to a loading strategy and a stage. Adjust volume to irritability.
A3: Loading Category | B3: Purpose | C3: Example Exercises | D3: Dosage | E3: Best Suited To
A4: Isometric / low-load | B4: Analgesia; irritable stage; early activation | C4: Isometric gluteal abduction holds; adductor squeeze holds; long-lever bridge holds | D4: 5 x 30-45 s holds, 1-2x/day | E4: Irritable GTPS, adductor-related pain, proximal hamstring tendinopathy, post-injury inhibition
A5: Gluteal strengthening (posterolateral) | B5: The single highest-yield hip intervention across almost every diagnosis | C5: Side-lying abduction, banded lateral walk, hip hitch, bridge, hip thrust, split squat, step-up, single-leg deadlift | D5: 3-4 sets, 8-12 RM, 2-3x/week | E5: GTPS, hip OA, FAI, dysplasia, sacroiliac pain, post-arthroplasty, deep gluteal syndrome - almost everything
A6: Copenhagen adduction | B6: Adductor capacity and injury prevention - the best-evidenced groin exercise | C6: Side-lying hip adduction, short lever progressing to long lever | D6: 3 sets, progressing volume, building to 3x/week | E6: Adductor-related and pubic-related groin pain; prevention in kicking and cutting sport
A7: Heavy slow resistance | B7: Build tendon capacity in hip tendinopathies | C7: Loaded hip abduction, Romanian deadlift, hip thrust, split squat | D7: 3-4 sets, 6-12 RM, 3 s up / 3 s down, 2-3x/week | E7: Gluteal tendinopathy, proximal hamstring tendinopathy, iliopsoas-related pain
A8: Eccentric hamstring | B8: Eccentric capacity and fascicle length - the best-evidenced hamstring intervention | C8: Nordic hamstring curl, Romanian deadlift, slider curl, Askling L-protocol | D8: 2-3 sets, 2-3x/week | E8: Acute hamstring strain, proximal hamstring tendinopathy, prevention in sprint sport
A9: Lumbopelvic control | B9: Control the pelvis so the hip is not compensating | C9: Dead bug, bird-dog, Pallof press, side plank, cable chop, hip hinge patterning | D9: 3-4 sets, 3x/week | E9: FAI, pubic-related and inguinal-related groin pain, sacroiliac pain, pelvic girdle pain
A10: Hip mobility (selective) | B10: Restore range where it is genuinely restricted | C10: Hip flexor and quadriceps lengthening, 90/90 rotation work, hip extension mobility | D10: 3-5 x 30 s, daily | E10: FAI with restricted rotation, hip OA, iliopsoas-related pain. NOT in dysplasia, microinstability or hypermobility
A11: Impact and plyometric | B11: Restore landing, deceleration and change-of-direction capacity | C11: Hopping, bounding, drop landings, deceleration drills, change-of-direction ladders | D11: 2-3x/week with 48 h between sessions | E11: All athletic hips before return to cutting or running sport
A12: Graded walking / running | B12: Rebuild impact volume after bone stress or a long lay-off | C12: Walk-run intervals progressing to continuous running, then speed and hills | D12: Alternate days; 10-15% weekly increments; ACWR 0.8-1.3 | E12: Bone stress injury, hip OA, post-arthroplasty, deconditioning
A13: Aerobic and general conditioning | B13: Guideline first-line for OA; maintain fitness during protection | C13: Cycling, pool work, cross-trainer, walking programme | D13: 150 min/week moderate intensity, or as tolerated | E13: Hip OA, axial spondyloarthritis, all protected-loading phases
A14: Aquatic exercise | B14: Load-reduced range and strength work | C14: Pool walking, aquatic range and strengthening, deep-water running | D14: 2-3x/week | E14: Irritable hip, Perthes, hip OA, axial spondyloarthritis, post-operative early phase
A15: Gait retraining | B15: Change the load pattern, not just the capacity | C15: Step rate increase, step width, stride length reduction, pelvic drop correction, walking aid technique | D15: Integrated into every session | E15: GTPS, ischiofemoral impingement, hip OA, bone stress injury, post-arthroplasty
A17: THE GENERIC LOADING PROGRESSION (Appendix B)
A18: • Stage 1 — Isometric / low-load cuff activation for pain and early capacity.
A19: • Stage 2 — Heavy slow resistance / isotonic cuff and scapular strengthening.
A20: • Stage 3 — Functional and overhead loading; kinetic-chain integration.
A21: • Stage 4 — Sport or occupation-specific loading (throwing, overhead work).
A22: • Thoracic mobility runs through all four stages — a near-universal contributor that costs nothing to include.
A23: • Motor-control retraining is the TREATMENT for Stanmore Polar III, not an adjunct — strengthening alone without control retraining does not work.

Sheet Adjuncts & Advanced
A1: ADJUNCTS, ADVANCED THERAPEUTICS & REFERRAL OPTIONS
A2: These open a comfort window for loading. On their own they build no capacity — with one exception: education.
A3: Tier | B3: Intervention | C3: Role | D3: Evidence Position | E3: Practical Note
A4: Adjunct | B4: Education & load management | C4: Foundational across every hip diagnosis | D4: A high-value intervention in its own right, particularly in GTPS | E4: In GTPS the education about removing ADDUCTION compression is as important as the exercise
A5: Adjunct | B5: Positional and sleeping modification | C5: Remove the compressive position | D5: Highly effective and often the fastest early win | E5: Pillow between the knees for GTPS; cushion and sitting modification for proximal hamstring tendinopathy
A6: Adjunct | B6: Activity and ergonomic modification | C6: Reduce provocative loading | D6: Central to FAI (deep sitting, squat depth) and groin pain (cutting and kicking volume) | E6: Modify rather than eliminate - relative, not complete, rest
A7: Adjunct | B7: Manual therapy | C7: Short-term pain and range gain to enable loading | D7: Adjunct only; combine with exercise | E7: AVOID ITB rolling and adduction stretching in GTPS - they compress the tendon
A8: Adjunct | B8: Walking aid | C8: Offloading in hip OA, bone stress and post-fracture | D8: Recommended in OA guidelines for selected cases | E8: Hold it in the CONTRALATERAL hand to reduce the hip joint reaction force
A9: Adjunct | B9: Pelvic belt | C9: Short-term support in pelvic girdle pain | D9: Selected cases, particularly post-partum | E9: Scaffolding during loading, not a substitute for capacity
A10: Adjunct | B10: Aquatic therapy | C10: Load-reduced exercise | D10: Valuable in irritable hips, OA, Perthes and axSpA | E10: Particularly useful where weight bearing is restricted
A11: Advanced | B11: Guided intra-articular corticosteroid injection | C11: Diagnostic and short-term therapeutic in intra-articular pain | D11: Short-term relief; also confirms an intra-articular source | E11: The diagnostic value is often greater than the therapeutic value
A12: Advanced | B12: Guided peritendinous or bursal injection | C12: GTPS, iliopsoas, ischiogluteal bursa | D12: INFERIOR to education plus exercise at 12 months in GTPS (LEAP) | E12: Use sparingly and only to open a window for loading
A13: Advanced | B13: ESWT | C13: Recalcitrant gluteal and proximal hamstring tendinopathy | D13: Supportive as an add-on when loading alone stalls | E13: Continue loading throughout - never a replacement
A14: Advanced | B14: Diagnostic nerve block | C14: Suspected obturator, ilioinguinal or lateral femoral cutaneous entrapment | D14: Confirms the source before considering surgery | E14: Often the only way to confirm a neural entrapment
... A20: Referral | B20: Core decompression | C20: Pre-collapse femoral head AVN | D20: May preserve the head in early-stage disease | E20: Stage determines everything - pre-collapse versus post-collapse
A22: SEQUENCING ADVANCED CARE
A23: • Optimise loading + education + adjuncts for 8-12 weeks (stage-based for frozen shoulder).
A24: • If stalled: calcific disease → ESWT or barbotage; add NMES where activation is poor — CONTINUE loading throughout.
A25: • Consider corticosteroid or hydrodilatation to enable rehabilitation in appropriate cases; PEMF, laser and TENS as low-risk adjuncts.
A26: • Refer for surgical opinion for DEFINED indications (acute cuff tear, recurrent structural instability, refractory frozen shoulder, end-stage OA) — not routine decompression.
A27: • The commonest reason advanced modalities disappoint is that they are used INSTEAD of loading rather than WITH it — and for RCRSP the evidence is clear that decompression adds nothing over placebo.
A28: • EDUCATION is the exception: for the shoulder it is a high-value intervention in its own right.

Sheet Post-Surgical Guide
A1: HIP SURGERY — PROTECTION & RETURN-TO-SPORT GUIDE
A2: 24 procedures across 9 categories. Timelines are general guidelines — ALWAYS follow the specific protocol provided by the operating surgeon, and CONFIRM THE APPROACH for arthroplasty.
A3: # | B3: Procedure Category | C3: Procedure | D3: Indication | E3: MOVEMENTS TO AVOID | F3: WEIGHT BEARING / PROTECTION | G3: Full Range | H3: Gym / Strength | I3: Running / Impact | J3: Return to Sport
A4: 1 | B4: Arthroscopic FAI Correction | C4: Femoroplasty (cam osteochondroplasty) | D4: Cam morphology in FAI syndrome | E4: Forced deep flexion; end-range internal rotation; impact loading | F4: Protected WB 2-4 weeks | G4: 6-8 weeks | H4: 12 weeks | I4: 4-6 months | J4: 6-9 months
A5: 1 | B5: Arthroscopic FAI Correction | C5: Acetabuloplasty (pincer rim trimming) | D5: Pincer morphology; focal or global over-coverage | E5: Forced deep flexion; end-range rotation | F5: Protected WB 2-4 weeks | G5: 6-8 weeks | H5: 12 weeks | I5: 4-6 months | J5: 6-9 months
A6: 2 | B6: Labral Surgery | C6: Labral repair | D6: Repairable labral tear with underlying FAI | E6: End-range rotation; deep flexion; forced extension with external rotation | F6: Protected WB 2-4 weeks | G6: 6-8 weeks | H6: 12 weeks | I6: 4-6 months | J6: 6-9 months
A7: 2 | B7: Labral Surgery | C7: Labral reconstruction (graft) | D7: Irreparable or deficient labrum | E7: End-range rotation; deep flexion; aggressive stretching | F7: Protected WB 4-6 weeks | G7: 8-10 weeks | H7: 12-16 weeks | I7: 6 months | J7: 9-12 months
A8: 2 | B8: Labral Surgery | C8: Labral debridement | D8: Degenerate or unstable flap not amenable to repair | E8: Impact loading initially | F8: WB as tolerated | G8: 4 weeks | H8: 8 weeks | I8: 3 months | J8: 3-4 months
A9: 3 | B9: Capsular Procedures | C9: Capsular plication / capsulorrhaphy | D9: Hip microinstability; capsular laxity | E9: END-RANGE EXTENSION AND EXTERNAL ROTATION; aggressive stretching | F9: Protected WB 4 weeks with a brace limiting extension and ER | G9: 8-10 weeks | H9: 12-16 weeks | I9: 6 months | J9: 9 months
A10: 3 | B10: Capsular Procedures | C10: Capsular closure / repair | D10: Routine closure after arthroscopy | E10: End-range extension and external rotation early | F10: Protected WB 2-4 weeks | G10: 6-8 weeks | H10: 12 weeks | I10: 4-6 months | J10: 6-9 months
A11: 4 | B11: Bone Realignment | C11: Periacetabular osteotomy (PAO) | D11: Symptomatic acetabular dysplasia with preserved cartilage | E11: Weight bearing until union; impact loading; hip flexor loading early | F11: PROTECTED / partial WB 6-8 weeks | G11: 10-12 weeks | H11: 16-20 weeks | I11: 6-9 months | J11: 9-12 months
A12: 4 | B12: Bone Realignment | C12: Femoral derotation osteotomy | D12: Femoral version abnormality driving symptoms | E12: Weight bearing until union; rotational loading | F12: Protected WB 6-8 weeks | G12: 10-12 weeks | H12: 16 weeks | I12: 6-9 months | J12: 9-12 months
A13: 5 | B13: Cartilage & Bone | C13: Microfracture / chondroplasty | D13: Focal chondral defect | E13: Impact loading; weight bearing per lesion location | F13: Protected / non-WB 6-8 weeks | G13: 10-12 weeks | H13: 16 weeks | I13: 6-9 months | J13: 9-12 months
A14: 5 | B14: Cartilage & Bone | C14: Core decompression | D14: Pre-collapse femoral head AVN | E14: Weight bearing; impact loading | F14: Protected / non-WB 6 weeks | G14: 12 weeks | H14: 16 weeks | I14: 6 months | J14: 9-12 months
A15: 6 | B15: Tendon & Soft Tissue | C15: Gluteal tendon repair (open or endoscopic) | D15: Full-thickness gluteus medius or minimus tear | E15: ACTIVE ABDUCTION; adduction past neutral; side-lying on the operated side | F15: Protected WB 6 weeks with an ABDUCTION BRACE | G15: 12 weeks | H15: 16-20 weeks | I15: 6 months | J15: 6-9 months
... A27: 9 | B27: Fracture Fixation | C27: In-situ screw fixation (SCFE) | D27: Slipped capital femoral epiphysis | E27: Weight bearing per surgeon; impact loading | F27: Protected WB 4-6 weeks | G27: 12 weeks | H27: 12-16 weeks | I27: 3-6 months | J27: 6 months
A29: Restriction | B29: What It Means | C29: Applies To
A30: Weight bearing restriction | B30: Protected or non-weight bearing to allow bone or cartilage healing | C30: PAO, femoral osteotomy, microfracture, core decompression, cannulated screw fixation, high-risk bone stress injury
A31: END-RANGE EXTENSION AND EXTERNAL ROTATION | B31: Avoid the position that stresses an anterior capsular repair | C31: Capsular plication, capsular closure, hip microinstability procedures
A32: Deep flexion and end-range rotation | B32: Avoid forcing the femoral neck back toward the rim while it heals | C32: Femoroplasty, acetabuloplasty, labral repair and reconstruction
A33: ACTIVE ABDUCTION | B33: No active abduction - the repaired gluteal tendon cannot yet take the load | C33: Gluteal tendon repair - protected with an ABDUCTION BRACE
A34: HIP FLEXION WITH KNEE EXTENSION | B34: Avoid lengthening the repaired hamstring across both joints at once | C34: Proximal hamstring repair - protected with a brace limiting hip flexion
A35: Arthroplasty dislocation positions | B35: Approach-dependent: posterior approach avoids combined flexion, adduction and internal rotation | C35: Total hip arthroplasty, hemiarthroplasty - confirm the approach with the surgeon
A36: EARLY MOBILISATION IS THE TREATMENT | B36: Weight bearing and walking from day one improves outcomes - immobility is the risk | C36: Total hip arthroplasty, hemiarthroplasty, most extracapsular fracture fixation
A38: GENERAL REHABILITATION PRINCIPLES
A39: • Protect the repair, the graft or the healing bone - but only where protection is actually indicated
A40: • After arthroplasty and most fracture fixation the opposite applies: early mobilisation from day one improves outcomes
A41: • Restore range within the surgical constraints before loading through it
A42: • Rebuild gluteal capacity - it is routinely under-rehabilitated after every hip operation
A43: • Restore gait quality and correct Trendelenburg before increasing walking volume
A44: • Progress on clinical criteria, not just time
A45: • Return to sport on capacity and control, not on comfort
A47: IMPORTANT
A48: • Timelines are general guidelines and vary with tissue quality, fixation, patient factors and surgeon preference
A49: • ALWAYS follow the specific post-operative protocol provided by the operating surgeon - it overrides everything on this sheet
A50: • For arthroplasty, CONFIRM THE SURGICAL APPROACH - the dislocation precautions differ between posterior, lateral and anterior approaches
A51: • Hip protocols vary substantially between surgeons for the same operation - confirm, do not assume

Sheet Sport Profiles
A1: ATHLETIC HIP — SPORT-SPECIFIC DEMANDS & INJURY RISK
A2: Twenty sports and populations: what the hip is asked to do, what breaks, and what to manage on the way back.
A3: Sport / Population | B3: Primary Hip Demands | C3: Injury Risks | D3: RETURN & LOAD CONSIDERATIONS
A4: Football (soccer) | B4: Kicking, cutting, sprinting, deceleration | C4: Adductor-related and pubic-related groin pain, FAI syndrome, hamstring strain, hip flexor strain | D4: Copenhagen adduction as both prevention and rehabilitation; monitor adductor squeeze through the season; graded return to kicking LAST
A5: Ice hockey | B5: Deep skating position, explosive adduction, cutting | C5: Adductor-related groin pain, FAI syndrome (very high cam prevalence), labral tear, sports hernia | D5: The skating position is sustained hip flexion and abduction - screen for FAI early; Copenhagen adduction; monitor groin squeeze
A6: Australian Rules / Gaelic football | B6: Kicking volume, sprinting, cutting | C6: Osteitis pubis, adductor-related groin pain, hamstring strain | D6: Kicking volume is the key load metric; pubic-related pain is slow - set a 3-6 month expectation
A7: Rugby | B7: Collision, scrummaging, cutting, sprinting | C7: Adductor-related groin pain, hip flexor strain, hamstring strain, AC and contact injury | D7: Contact and scrummaging load the hip in end range; build gluteal and adductor capacity before contact return
A8: Distance running | B8: High-volume repetitive impact and single-leg loading | C8: GTPS, femoral neck and pubic ramus stress fracture, proximal hamstring tendinopathy, ITB-related pain | D8: Screen energy availability in every female runner with hip pain; step rate +5-10%; graded volume with ACWR 0.8-1.3
A9: Sprinting & hurdling | B9: Explosive eccentric hamstring and hip flexor demand | C9: Hamstring strain, proximal hamstring tendinopathy, rectus femoris strain, apophyseal avulsion in adolescents | D9: Nordic hamstring programme; regular high-speed running exposure; criteria-based return, never time-based
A10: Dance & ballet | B10: Extreme range, turnout, repetitive end-range loading | C10: FAI syndrome, labral tear, hip microinstability, snapping hip, proximal hamstring tendinopathy | D10: Screen for hypermobility and dysplasia - do NOT prescribe more stretching to a hypermobile dancer; build dynamic control instead
A11: Gymnastics | B11: Extreme range, impact landing, weight-bearing through the hip | C11: FAI syndrome, labral tear, apophyseal avulsion, hip microinstability | D11: Skeletally immature athletes need apophyseal injury on the differential; cap skill repetition volume
A12: Martial arts | B12: High kicks, deep stances, rotational loading | C12: Adductor-related groin pain, FAI syndrome, hip flexor strain | D12: Kicking height and volume are the load metrics; adductor and hip flexor capacity before high-kick return
A13: Weightlifting & CrossFit | B13: Deep squat, hip hinge, explosive triple extension | C13: FAI syndrome, proximal hamstring tendinopathy, adductor strain, hip flexor pain | D13: Squat depth and hip hinge technique review; cap deep-flexion volume in FAI; posterior chain loading
A14: Cycling | B14: Sustained hip flexion, repetitive low-load pedalling | C14: Iliopsoas-related pain, gluteal deconditioning, obturator or pudendal nerve symptoms, ITB-related pain | D14: Bike fit: saddle height, fore-aft, saddle type and tilt; cyclists are commonly gluteally deconditioned - load them
... A23: Older adult & general population | B23: Walking, stairs, sit-to-stand, gardening | C23: Hip OA, GTPS, gluteal tendon tear, hip fracture, sacroiliac pain | D23: Gluteal strengthening plus aerobic exercise is guideline first-line; falls prevention and bone health run alongside
A25: ACTIVITY- & SPORT-SPECIFIC CONSIDERATIONS
A26: • KICKING AND CUTTING SPORT: the Copenhagen adduction exercise is both the treatment and the prevention; monitor the adductor squeeze figure through the season; return to KICKING last.
A27: • RUNNING AND ENDURANCE SPORT: screen energy availability in every athlete with hip or groin pain; step rate and volume progression are the levers; ACWR 0.8-1.3 on return.
A28: • DANCE, GYMNASTICS AND YOGA: screen for hypermobility and dysplasia FIRST — prescribing more stretching to a hypermobile or dysplastic hip actively worsens it.
A29: • OLDER ADULTS AND THE GENERAL POPULATION: gluteal strengthening plus aerobic exercise is guideline first-line for hip OA; falls prevention and bone health run alongside.

Sheet Return to Sport
A1: RETURN-TO-SPORT CRITERIA
A2: Discharge on capacity and control, not on comfort.
A3: Criterion | B3: Target | C3: How to Measure
A4: Pain | B4: No pain at rest, at night, or with daily activity | C4: NPRS; night pain score
A5: Range of motion | B5: Symmetrical hip range, particularly internal rotation at 90 deg flexion | C5: Goniometry
A6: Adductor squeeze | B6: Symmetrical squeeze force; the key marker in all groin presentations | C6: Sphygmomanometer or dynamometer at 0, 45 and 90 deg
A7: Hip abductor strength LSI | B7: >=90% of the uninvolved side | C7: Handheld dynamometry
A8: Adduction:abduction ratio | B8: Restored toward 1.0; a low ratio predicts groin injury | C8: Handheld dynamometry
A9: Single-leg stance | B9: 30 seconds without pain or pelvic drop | C9: Timed single-leg stance with Trendelenburg observation
A10: Single-leg control | B10: No pelvic drop or dynamic valgus on single-leg squat and step-down | C10: Observation under load and at fatigue
A11: Hop symmetry | B11: >=90% on single, triple and crossover hop where impact sport is the goal | C11: Hop battery, best of three per limb
A12: Sport-specific progression | B12: Running, then cutting, then kicking or contact - each completed without symptom escalation | C12: Documented graded progression
A13: Load monitoring | B13: Graded return with acute:chronic workload monitoring | C13: Weekly load tracking
A15: CLINICAL PEARL
A16: • A throwing athlete whose shoulder feels better but still has an ER/IR strength deficit, poor scapular control at speed, or residual apprehension is primed to relapse.
A17: • Prove strength, control and (for instability) CONFIDENCE in sport positions before releasing the load ceiling.
A18: • Use the Progress Tracker to calculate symmetry, the ER:IR ratio, GIRD and total arc, and to generate an automatic pass/fail against these criteria.
A19: • Cross-reference the Sport Profiles sheet for what the athlete's specific sport will ask of the shoulder on return.

Sheet Progress Tracker
A1: PROGRESS TRACKER & READINESS CALCULATOR
A2: Enter values in the yellow cells only. Range deficits, adductor squeeze symmetry, limb symmetry and the adduction:abduction ratio calculate automatically.
A4: PATIENT & CASE DETAILS
A5: Patient ID / initials | B5: e.g. PR-041 | F5: Desired activity goal for this condition:
A6: Condition (as listed in Master Matrix) | B6: Greater Trochanteric Pain Syndrome (Gluteal Tendinopathy) | F6: =IFERROR(INDEX('Master Matrix'!L$4:L$41,MATCH($B$6,'Master Matrix'!$H$4:$H$41,0)),"Enter a condition exactly as listed in the Master Matrix") -> Enter a condition exactly as listed in the Master Matrix
A7: Involved side | B7: Right
A8: Assessment date
A10: RANGE OF MOTION (degrees) — target: symmetrical
A11: Movement | B11: Involved | C11: Uninvolved | D11: Unit | E11: Deficit | F11: Status | G11: Note
A12: INTERNAL ROTATION at 90 deg flexion | B12: 15 | C12: 35 | D12: deg | E12: =IF(OR(B12="",C12=""),"",C12-B12) -> 20 | F12: =IF(E12="","",IF(E12<=5,"SYMMETRICAL",IF(E12<=15,"MILD DEFICIT","RESTRICTED"))) -> RESTRICTED | G12: THE earliest measurable change in FAI syndrome and hip OA
A13: External rotation at 90 deg flexion | D13: deg | E13: =IF(OR(B13="",C13=""),"",C13-B13) | F13: =IF(E13="","",IF(E13<=5,"SYMMETRICAL",IF(E13<=15,"MILD DEFICIT","RESTRICTED")))
A14: Hip flexion | D14: deg | E14: =IF(OR(B14="",C14=""),"",C14-B14) | F14: =IF(E14="","",IF(E14<=5,"SYMMETRICAL",IF(E14<=15,"MILD DEFICIT","RESTRICTED")))
A15: Hip extension (Thomas) | D15: deg | E15: =IF(OR(B15="",C15=""),"",C15-B15) | F15: =IF(E15="","",IF(E15<=5,"SYMMETRICAL",IF(E15<=15,"MILD DEFICIT","RESTRICTED")))
A16: Hip abduction | D16: deg | E16: =IF(OR(B16="",C16=""),"",C16-B16) | F16: =IF(E16="","",IF(E16<=5,"SYMMETRICAL",IF(E16<=15,"MILD DEFICIT","RESTRICTED")))
A18: ADDUCTOR SQUEEZE — THE KEY GROIN MARKER
A19: Position | B19: Involved side | C19: Uninvolved / previous | D19: Unit | E19: Change | F19: Status | G19: Note
A20: Squeeze at 0 deg | B20: 180 | C20: 240 | D20: mmHg / N | E20: =IF(N(C20)=0,"",B20/C20) -> 0.75 | F20: =IF(E20="","",IF(E20>=0.9,"PASS","NOT YET")) -> NOT YET | G20: Record the figure every session — diagnostic test, treatment target AND discharge criterion
A21: Squeeze at 45 deg | D21: mmHg / N | E21: =IF(N(C21)=0,"",B21/C21) | F21: =IF(E21="","",IF(E21>=0.9,"PASS","NOT YET"))
A22: Squeeze at 90 deg | D22: mmHg / N | E22: =IF(N(C22)=0,"",B22/C22) | F22: =IF(E22="","",IF(E22>=0.9,"PASS","NOT YET"))
A24: HIP STRENGTH — LIMB SYMMETRY INDEX
A25: Measure | B25: Involved | C25: Uninvolved | D25: Unit | E25: LSI | F25: Status | G25: Note
A26: Hip abduction | B26: 14 | C26: 20 | D26: kg | E26: =IF(N(C26)=0,"",B26/C26) -> 0.7 | F26: =IF(E26="","",IF(E26>=$B$42,"PASS","NOT YET")) -> NOT YET
A27: Hip adduction | D27: kg | E27: =IF(N(C27)=0,"",B27/C27) | F27: =IF(E27="","",IF(E27>=$B$42,"PASS","NOT YET"))
A28: Hip extension | D28: kg | E28: =IF(N(C28)=0,"",B28/C28) | F28: =IF(E28="","",IF(E28>=$B$42,"PASS","NOT YET"))
A29: Hip flexion | D29: kg | E29: =IF(N(C29)=0,"",B29/C29) | F29: =IF(E29="","",IF(E29>=$B$42,"PASS","NOT YET"))
A30: ADDUCTION:ABDUCTION RATIO — involved | B30: =IF(OR(N(B26)=0,B27=""),"",B27/B26) | C30: Uninvolved | D30: =IF(OR(N(C26)=0,C27=""),"",C27/C26) | E30: =IF(B30="","",IF(B30>=0.9,"Ratio acceptable (target approaching 1.0)","LOW RATIO — adductor deficit; a known predictor of groin injury"))
A32: RE-TESTABLE MARKERS — BASELINE vs CURRENT
A33: Marker | B33: Baseline | C33: Current | D33: Unit | E33: Change | F33: % Change | G33: Direction of improvement
A34: 30-second single-leg stance (time to pain) | B34: 8 | C34: 25 | D34: sec | E34: =IF(OR(B34="",C34=""),"",C34-B34) -> 17 | F34: =IF(OR(N(B34)=0,C34=""),"",(C34-B34)/B34) -> 2.125 | G34: Higher is better
A35: Sitting tolerance | D35: min | E35: =IF(OR(B35="",C35=""),"",C35-B35) | F35: =IF(OR(N(B35)=0,C35=""),"",(C35-B35)/B35) | G35: Higher is better
A36: Walking / running tolerance | D36: min or km | E36: =IF(OR(B36="",C36=""),"",C36-B36) | F36: =IF(OR(N(B36)=0,C36=""),"",(C36-B36)/B36) | G36: Higher is better
A37: Primary task pain (NRS 0-10) | D37: /10 | E37: =IF(OR(B37="",C37=""),"",C37-B37) | F37: =IF(OR(N(B37)=0,C37=""),"",(C37-B37)/B37) | G37: Lower is better
A38: Night pain / side-lying tolerance (0-3) | D38: grade | E38: =IF(OR(B38="",C38=""),"",C38-B38) | F38: =IF(OR(N(B38)=0,C38=""),"",(C38-B38)/B38) | G38: Lower is better
A39: PROM score (HOOS / iHOT-33 / HAGOS / VISA-G) | D39: points | E39: =IF(OR(B39="",C39=""),"",C39-B39) | F39: =IF(OR(N(B39)=0,C39=""),"",(C39-B39)/B39) | G39: Higher is better
A41: RETURN-TO-SPORT / FUNCTION READINESS
A42: LSI target threshold (editable) | B42: 0.9
A43: Strength tests entered | B43: =COUNT(E26:E29) -> 1
A44: Strength tests passed | B44: =COUNTIF(F26:F29,"PASS") -> 0
A45: Squeeze positions passed | B45: =COUNTIF(F20:F22,"PASS") -> 0
A46: Range measures symmetrical or mild | B46: =COUNTIF(F12:F16,"SYMMETRICAL")+COUNTIF(F12:F16,"MILD DEFICIT") -> 0
A47: No pelvic drop or dynamic valgus on single-leg squat and landing | B47: NO
A48: Sport-specific progression completed (running → cutting → kicking or contact) | B48: NO
A49: The load error that caused this has been identified and corrected | B49: NO
A50: Bone-health / energy-availability review completed where indicated | B50: NO
A52: OVERALL READINESS STATUS → | C52: =IF(COUNT(E26:E29)=0,"Enter test data to calculate",IF(AND(COUNT(E26:E29)>=3,COUNTIF(F26:F29,"NOT YET")=0,COUNTIF(F20:F22,"NOT YET")=0,COUNTIF(F12:F16,"RESTRICTED")=0,COUNTIF(B47:B50,"YES")=4),"READY — all criteria met","NOT YET — criteria outstanding: continue loading and re-test")) -> NOT YET — criteria outstanding: continue loading and re-test
A54: HOW TO USE THIS SHEET
A55: • Yellow cells are inputs. Every other cell is a formula — do not overwrite them.
A56: • INTERNAL ROTATION AT 90 DEGREES FLEXION is the earliest measurable change in both FAI syndrome and hip osteoarthritis. Stabilise the pelvis when you measure it.
A57: • THE ADDUCTOR SQUEEZE FIGURE is the single most useful objective marker in athletic groin pain — record it at every session, in the same position, with the same device.
A58: • A low ADDUCTION:ABDUCTION RATIO is an independent predictor of groin injury. Chase the adductors, not just overall hip strength.
A59: • Discharge criteria include correcting the load error that caused the injury. Returning an athlete to the same kicking or running pattern that broke them is why groin pain recurs.
A60: • Example values are pre-filled in the first row of each block — overwrite them.

Sheet Outcome Measures
A1: OUTCOME MEASURES
A2: One patient-reported measure plus two or three objective markers is the minimum baseline dataset.
A3: Measure | B3: Full Name | C3: What It Captures | D3: Scoring | E3: Best Suited To
A4: HOOS | B4: Hip disability and Osteoarthritis Outcome Score | C4: Pain, symptoms, function, sport and quality of life | D4: 0-100 (higher = better) | E4: Hip OA, general hip pain, post-arthroplasty
A5: iHOT-33 / iHOT-12 | B5: International Hip Outcome Tool | C5: Young active adult hip function and quality of life | D5: 0-100 (higher = better) | E5: FAI, labral tear, dysplasia, young athletic hips - the standard in this group
A6: HAGOS | B6: Copenhagen Hip and Groin Outcome Score | C6: Hip and GROIN specific function and quality of life | D6: 0-100 (higher = better) | E6: Athletic groin pain - the groin-specific standard
A7: Oxford Hip Score | B7: Oxford Hip Score | C7: Pain and function | D7: 0-48 (higher = better) | E7: Hip OA and arthroplasty
A8: Harris Hip Score | B8: Harris Hip Score | C8: Pain, function, deformity, range | D8: 0-100 (higher = better) | E8: Arthroplasty and surgical outcome reporting
A9: VISA-G | B9: Victorian Institute of Sport Assessment - Gluteal | C9: Gluteal tendinopathy severity | D9: 0-100 (higher = better) | E9: GTPS / gluteal tendinopathy
A10: VISA-H | B10: Victorian Institute of Sport Assessment - Hamstring | C10: Proximal hamstring tendinopathy severity | D10: 0-100 (higher = better) | E10: Proximal hamstring tendinopathy
A11: Pelvic Girdle Questionnaire | B11: PGQ | C11: Pelvic girdle pain activity and symptoms | D11: 0-100 (lower = better) | E11: Pregnancy-related and post-partum pelvic girdle pain
A12: BASDAI / BASFI | B12: Bath Ankylosing Spondylitis indices | C12: Disease activity and function in axSpA | D12: 0-10 | E12: Axial spondyloarthritis
A13: Adductor squeeze force | B13: Objective capacity marker | C13: Adductor strength and symptom provocation | D13: mmHg or Newtons at 0, 45, 90 deg | E13: ALL groin presentations - the single most useful objective marker
A14: Hip internal rotation at 90 deg | B14: Objective capacity marker | C14: The earliest measurable change in FAI and hip OA | D14: Degrees | E14: FAI, hip OA - measure in every hip
... A18: Hop battery / limb symmetry index | B18: Objective capacity marker | C18: Impact and single-leg capacity | D18: Percentage symmetry | E18: Athletic hips before return to sport
A20: NOTES
A21: • Scoring DIRECTION differs between measures — SPADI, QuickDASH, WOSI and WORC improve as they FALL; ASES, Constant, Oxford and KJOC improve as they RISE.
A22: • The night-pain score is often the change that matters most to the patient, and it moves earlier than range or strength.
A23: • Record a Beighton score in any atraumatic instability presentation — it changes management entirely.

Sheet Whole-Person Screen
A1: WHOLE-PERSON & METABOLIC SCREEN
A2: A refractory shoulder is a cue to widen the lens — the shoulder is often the messenger, not the whole message.
A3: Factor | B3: Relevance to Shoulder Pain | C3: What to Screen | D3: Clinical Action | E3: Findings (fill in)
A4: Lumbar spine and pelvis | B4: The spine refers to the buttock, groin and thigh constantly; HIP-SPINE SYNDROME means both may contribute | C4: Screen the lumbar spine in EVERY hip presentation, and the hip in every lumbar presentation | D4: Treat both where both are contributing; do not chase one and ignore the other
A5: Energy availability and bone health | B5: Low energy availability is the central driver of bone stress injury and is highly prevalent in running, dance and gymnastics | C5: Screen in every bone stress injury, and in every female athlete with hip or groin pain | D5: Refer to a sports dietitian and physician; DXA where recurrent. Do not prescribe intake yourself
A6: Menstrual status | B6: Menstrual dysfunction signals endocrine disruption and low bone mineral density risk | C6: Ask in every female athlete with a bone stress injury or recurrent hip pain | D6: Refer for endocrine and gynaecological review
A7: Obesity and metabolic health | B7: Increases hip joint load, is associated with hip OA progression, and is a major risk factor for SCFE in adolescents | C7: Screen in hip OA and in every adolescent with hip pain | D7: Weight management is guideline first-line for OA; refer for dietetic co-management
A8: Generalised hypermobility | B8: CHANGES THE ENTIRE APPROACH in hip microinstability and dysplasia - stretching makes it worse | C8: Beighton score in any hip presenting with instability, clicking or excess range | D8: Build dynamic control; AVOID end-range stretching, extreme yoga positions and passive mobilisation
A9: Bone mineral density and falls risk | B9: A hip fragility fracture strongly predicts the next fracture; falls risk is the upstream driver | C9: Screen in every older adult with a low-energy fracture | D9: Refer for osteoporosis assessment; deliver balance and resistance training as falls prevention
A10: Psychosocial factors and beliefs | B10: Fear-avoidance, low self-efficacy and catastrophising predict poorer outcomes and persistence | C10: Ask what they think is wrong and what they are afraid of | D10: Address beliefs directly; reframe imaging findings; graded exposure for persistent pain
A11: Sleep and night pain | B11: Night pain is the defining functional limitation in GTPS and a major driver of distress | C11: Ask specifically which side they lie on and how often they wake | D11: Positional advice with a pillow between the knees is often the fastest early win in GTPS
A12: Occupational and sitting load | B12: Prolonged deep sitting provokes FAI; hard-edged sitting provokes proximal hamstring tendinopathy; standing on one hip provokes GTPS | C12: Assess seat height, seat surface, sitting duration and standing habits | D12: Modify seating, add a cushion, introduce sit-stand breaks, and stop hanging on one hip in standing
A13: Expectations and timelines | B13: Pubic-related groin pain, proximal hamstring tendinopathy and GTPS all recover over MONTHS | C13: Ask what timeline they expect | D13: Set realistic timelines from day one - mismatched expectation is a major cause of disengagement
A15: CLINICAL ACTIONS (Module 14.2)
A16: • A FROZEN SHOULDER IS A PROMPT TO CHECK METABOLIC HEALTH — undiagnosed or poorly controlled diabetes and thyroid disease are common, change the prognosis, and are worth flagging.
A17: • Address beliefs and fears directly — reassure about the safety of loading and the poor pain-correlation of imaging findings; use graded exposure for persistent pain.
A18: • Manage sleep and night pain ACTIVELY — they are major drivers of distress and disability in shoulder conditions.
A19: • Set realistic timelines: RCRSP and frozen shoulder recover over months, and frozen shoulder in particular is often NOT quickly self-limiting.

Sheet Red Flags
A1: RED FLAGS & TIME-SENSITIVE PRESENTATIONS
A2: Twelve presentations where a rehabilitation trial is the wrong first move.
A3: Presentation | B3: Features | C3: Action Required | D3: Why It Cannot Wait
A4: Tension-side femoral neck stress fracture | B4: Groin pain in a runner or recruit now present on WALKING, at rest or at night | C4: EMERGENCY - non-weight-bearing on crutches and same-day orthopaedic referral | D4: Displacement causes avascular necrosis and can be career- or life-altering, and it is avoidable
A5: Slipped capital femoral epiphysis (SCFE) | B5: Adolescent with hip, thigh OR KNEE pain and a limp; obligatory external rotation on hip flexion | C5: EMERGENCY - non-weight-bearing and same-day orthopaedic referral | D5: KNEE PAIN IS A CLASSIC PRESENTATION OF HIP PATHOLOGY IN CHILDREN and the commonest cause of delayed diagnosis
A6: Septic arthritis of the hip | B6: Acutely painful hip, unable to weight-bear, febrile and systemically unwell | C6: EMERGENCY - urgent aspiration and intravenous antibiotics | D6: The hip is deep and signs are less obvious; cartilage destruction begins within days
A7: Hip fracture | B7: Older adult after a fall with a shortened, externally rotated leg and inability to weight-bear | C7: EMERGENCY - urgent orthopaedic referral | D7: Surgery within 36 hours improves outcomes; always trigger bone health and falls assessment
A8: Avascular necrosis of the femoral head | B8: Progressive deep groin pain at rest and at night, with corticosteroid, alcohol or haemoglobinopathy history | C8: Urgent MRI and orthopaedic referral | D8: Radiographs are NORMAL in early disease - a normal film gives false reassurance
A9: Malignancy or metastasis | B9: Constant non-mechanical pain unrelated to movement; night pain; weight loss; cancer history | C9: Urgent imaging and medical referral; restrict weight bearing if a lytic lesion is suspected | D9: Pain not reproducible on mechanical testing IS the finding
A10: Perthes disease | B10: Child with a limp and restricted hip abduction and internal rotation | C10: Paediatric orthopaedic referral and imaging | D10: A limping child needs a diagnosis, not reassurance
A11: Developmental dysplasia of the hip | B11: Infant with limited or asymmetric hip abduction, uneven creases, or leg length difference | C11: Urgent paediatric orthopaedic referral and ultrasound | D11: Late diagnosis is the single biggest determinant of a poor lifelong outcome
A12: Acetabular dysplasia in the young adult | B12: Hip pain with instability, excess range, and a lateral centre-edge angle under 20-25 degrees | C12: Joint-preservation referral BEFORE any arthroscopy is considered | D12: Isolated arthroscopic labral surgery in a dysplastic hip can accelerate instability and degeneration
A13: Axial spondyloarthritis | B13: Young adult with alternating buttock pain, morning stiffness over 30 minutes, better with exercise and worse with rest | C13: Rheumatology referral | D13: Average diagnostic delay is measured in years; early treatment changes the long-term outcome
A14: Cauda equina syndrome | B14: Bilateral leg symptoms, saddle anaesthesia, bladder or bowel change | C14: EMERGENCY - same-day neurosurgical referral | D14: Delay causes permanent deficit
A15: Atypical femoral fracture | B15: Prodromal thigh or groin pain in a patient on long-term bisphosphonates | C15: Urgent imaging of BOTH femurs | D15: Bilateral involvement is common; prophylactic fixation may be indicated
A17: SCREENING RULES
A18: • THE OVERRIDING RULE: if nothing in the physical examination reproduces the pain the patient came in with, that mismatch IS the finding. Refer for medical assessment.
A19: • Always test axillary nerve function BEFORE AND AFTER any shoulder reduction, and in every proximal humeral fracture.
A20: • Always obtain an AXILLARY view in suspected dislocation — posterior dislocation is missed on AP films and presents as a shoulder fixed in internal rotation.
A21: • In the over-40s, a shoulder dislocation tears the CUFF more often than the labrum — re-examine for weakness once the acute pain settles.

Sheet Case-Based Learning
A1: CASE-BASED LEARNING
A2: Four worked cases integrating reasoning from presentation to return.
A3: Case | B3: Presentation | C3: Reasoning | D3: Plan
A4: Case 1 - The footballer with groin pain | B4: 24-year-old semi-professional footballer, six weeks of medial groin pain building through pre-season. Worse with cutting, kicking and sprinting. Tender at the adductor longus origin; adductor squeeze reproduces the pain and is 30% weaker than the other side. Hip range full and pain-free; FADIR negative; pubic symphysis non-tender. | C4: Adductor tenderness plus pain on resisted adduction, with a negative hip joint examination and a non-tender symphysis, places this squarely in the ADDUCTOR-RELATED entity of the Doha Agreement. A clear pre-season load spike is the driver. | D4: Copenhagen adduction programme as the core intervention, progressed over 8-12 weeks; isometric squeeze holds early for analgesia; hip abductor and lumbopelvic work to correct the adductor:abductor ratio; graded cutting and kicking reintroduction with volume logged. Re-test adductor squeeze strength at 3 and 6 weeks. Target an adductor:abductor ratio above 0.9 before full return.
A5: Case 2 - The dancer with deep groin pain and catching | B5: 22-year-old ballet dancer, deep anterior groin pain for four months with clicking and a sense of the hip slipping in end-range positions. Hypermobile (Beighton 7/9). FADIR mildly positive; anterior apprehension positive. Radiograph shows a lateral centre-edge angle of 21 degrees. | C5: The LCEA of 21 degrees is the finding that changes everything - this is BORDERLINE DYSPLASIA with microinstability, not FAI. The hip is UNDERCOVERED. Labral symptoms here are a consequence of instability, not impingement. | D5: Do NOT refer for arthroscopic capsular release or labral debridement - that risks precipitating frank instability. Long-horizon rehabilitation: deep hip external rotator and gluteus medius control, progressive closed-chain and single-leg loading, lumbopelvic control, and STOPPING aggressive end-range passive stretching. If symptoms persist with preserved cartilage, refer for a PAO opinion, not arthroscopy.
A6: Case 3 - The woman who cannot lie on her side | B6: 54-year-old, 12 months of lateral hip pain. Cannot lie on that side at night; painful on stairs and standing on one leg. Focal trochanteric tenderness; single-leg stance reproduces the pain within 30 seconds. She has had two corticosteroid injections with short-lived relief, and has been diligently stretching her ITB. | C6: Gluteal tendinopathy (GTPS). Two things are perpetuating it: the ITB stretching is COMPRESSING the tendon against the trochanter, and the injections have been substituting for loading. | D6: Education first and it is half the treatment: stop ITB and deep adduction stretching, stop crossing the legs, stop hanging on one hip in standing, and sleep with a pillow between the knees. Then progressive hip abductor loading in NEUTRAL, starting isometric. LEAP trial data show education plus exercise beats both corticosteroid and wait-and-see at 8 weeks AND at 52 weeks - set that expectation explicitly.
A7: Case 4 - The adolescent with knee pain | B7: 13-year-old, overweight, four weeks of vague left KNEE pain and a limp. Knee examination is entirely normal. On hip examination, passive hip flexion produces obligatory external rotation and internal rotation is markedly restricted. | C7: Obligatory external rotation on hip flexion is pathognomonic for SLIPPED CAPITAL FEMORAL EPIPHYSIS. Knee pain is the classic referred presentation and the classic missed one - the diagnosis is delayed when the knee is examined and the hip is not. | D7: Non-weight-bearing on crutches immediately and same-day orthopaedic referral. AP and frog-lateral radiographs of BOTH hips - the AP alone misses it and the contralateral side is often involved. This is a surgical emergency; an unstable slip carries a very high risk of avascular necrosis. Endocrine screen if atypically young or thin.
A8: Case 5 - The runner whose groin pain stopped behaving mechanically | B8: 31-year-old distance runner, groin pain that began with a mileage increase eight weeks ago. Initially only with running; now present when walking, and waking her at night. Pain at end-range hip internal rotation; antalgic gait. She has amenorrhoea and has recently lost weight. | C8: Progression from load-related to rest and night pain is the pattern that must not be rationalised. This is a FEMORAL NECK STRESS FRACTURE until MRI proves otherwise, and the amenorrhoea and weight loss point to low energy availability underneath it. | D8: Urgent MRI - a radiograph is insensitive and a normal film does not exclude it. Non-weight-bearing on crutches pending the result, because a tension-side lesion can displace catastrophically. Orthopaedic referral to grade and side the lesion. Simultaneously refer for bone health and energy availability assessment - the local injury is a symptom of a systemic problem that will otherwise recur.
A10: WHAT THE CASES TEACH
A11: • The history and a competent hip examination make most of these diagnoses - imaging confirms, it does not diagnose
A12: • MEASURE THE LATERAL CENTRE-EDGE ANGLE in every young adult with hip pain; dysplasia is routinely mislabelled as FAI, and the treatments are opposites
A13: • In lateral hip pain, REMOVING THE COMPRESSION is as powerful as the exercise - stretching the ITB makes gluteal tendinopathy worse
A14: • KNEE PAIN IN AN ADOLESCENT ALWAYS REQUIRES A HIP EXAMINATION - SCFE and Perthes both present this way
A15: • When groin pain stops behaving mechanically and starts appearing at rest and at night, stop rehabilitating and start investigating
A16: • A local injury in an athlete with low energy availability is a systemic problem wearing a local disguise

Sheet References
A1: KEY REFERENCES & FURTHER READING
A2: Guidelines evolve and terminology continues to shift — verify currency for high-stakes decisions.
A4: 1 | B4: Griffin DR, Dickenson EJ, O'Donnell J, et al. The Warwick Agreement on femoroacetabular impingement syndrome (FAI syndrome): an international consensus statement. Br J Sports Med. 2016;50(19):1169-1176
A5: 2 | B5: Griffin DR, Dickenson EJ, Wall PDH, et al. Hip arthroscopy versus best conservative care for the treatment of femoroacetabular impingement syndrome (UK FASHIoN): a multicentre randomised controlled trial. Lancet. 2018;391(10136):2225-2235
A6: 3 | B6: Weir A, Brukner P, Delahunt E, et al. Doha agreement meeting on terminology and definitions in groin pain in athletes. Br J Sports Med. 2015;49(12):768-774
A7: 4 | B7: Harøy J, Clarsen B, Wiger EG, et al. The Adductor Strengthening Programme prevents groin problems among male football players: a cluster-randomised controlled trial. Br J Sports Med. 2019;53(3):150-157
A8: 5 | B8: Mellor R, Bennell K, Grimaldi A, et al. Education plus exercise versus corticosteroid injection use versus a wait and see approach on global outcome and pain from gluteal tendinopathy (LEAP): prospective, single blinded, randomised clinical trial. BMJ. 2018;361:k1662
A9: 6 | B9: Grimaldi A, Fearon A. Gluteal tendinopathy: integrating pathomechanics and clinical features in its management. J Orthop Sports Phys Ther. 2015;45(11):910-922
A10: 7 | B10: Cook JL, Purdam C. Is compressive load a factor in the development of tendinopathy? Br J Sports Med. 2012;46(3):163-168
A11: 8 | B11: Bannuru RR, Osani MC, Vaysbrot EE, et al. OARSI guidelines for the non-surgical management of knee, hip, and polyarticular osteoarthritis. Osteoarthritis Cartilage. 2019;27(11):1578-1589
A12: 9 | B12: National Institute for Health and Care Excellence. Osteoarthritis in over 16s: diagnosis and management. NICE guideline NG226. 2022
A13: 10 | B13: Skou ST, Roos EM. Good Life with osteoArthritis in Denmark (GLA:D): evidence-based education and supervised neuromuscular exercise. BMC Musculoskelet Disord. 2017;18(1):72
A14: 11 | B14: Laslett M, Aprill CN, McDonald B, Young SB. Diagnosis of sacroiliac joint pain: validity of individual provocation tests and composites of tests. Man Ther. 2005;10(3):207-218
A15: 12 | B15: Kaeding CC, Miller T. The comprehensive description of stress fractures: a new classification system. J Bone Joint Surg Am. 2013;95(13):1214-1220
... A19: 16 | B19: Kocher MS, Zurakowski D, Kasser JR. Differentiating between septic arthritis and transient synovitis of the hip in children: an evidence-based clinical prediction algorithm. J Bone Joint Surg Am. 1999;81(12):1662-1670
A21: SOURCES USED TO BUILD THIS WORKBOOK
A22: • Source 1 — Shoulder diagnostics algorithm (your 27-condition reasoning matrix), which forms columns B–M of the Master Matrix.
A23: • Source 2 — Diagnosis & Management of Shoulder Pain Conditions: Advanced Clinical Programme Course Manual (Modules 1-16, Appendices A-C).
A24: • Source 3 — Athletic Shoulder: Sport-Specific Demands and Injury Risk Comparison (20 sports).
A25: • Source 4 — Arthroscopic Shoulder Surgeries: Categories, Indications & Rehabilitation Protection Guide (infographic, 9 categories).
A26: • This workbook is a companion to the Knee Assessment & Management Programme and the Bone Stress, Cartilage & Meniscal Injury algorithm, and follows the same structure and conventions.
A27: • It is an educational and clinical-reasoning companion. It does not replace individualised assessment, local protocols, or the operating surgeon's protocol.
