Workbook

Sheet Read Me
A1: FOOT & ANKLE ASSESSMENT AND MANAGEMENT PROGRAMME
A2: Screen (Ottawa) → clear the spine, nerves and circulation → localise the region → identify the tissue → load → discharge on dorsiflexion, heel raise and balance.
A4: SHEET | B4: WHAT IT DOES | C4: WHEN TO USE IT | D4: FOCUS
A5: Master Matrix | B5: 41 foot and ankle conditions on the established column structure: Region → Activity Level → Common Symptoms → Age → Onset → Predominance → Condition → High-Yield Question → Special Test + Imaging → Biomechanical Cause → Desired Activity Goal → Physiotherapy Specific Exercise, then pain mechanism, classification, red-flag status, management emphasis, loading dose, biomechanical corrections, adjuncts, advanced options, outcomes, markers, timeline and referral triggers. | C5: The core reference. Filter column A by region or column O by red-flag status. | D5: All foot and ankle pathology
A6: Rx Generator | B6: Pick a condition from the dropdown and the full prescription is pulled live from the Master Matrix. | C6: In clinic, or to print a plan into the patient file. | D6: Live INDEX/MATCH
A7: Assessment Roadmap | B7: The five-gate sequence, built around the Ottawa Rules at Gate 1 and the region-then-tissue branch at Gate 4. | C7: Every new patient, in order. | D7: Clinical reasoning
A8: Subjective Exam | B8: Fillable history template with the footwear, diabetic and paediatric screening questions built in. | C8: First consultation. | D8: Fillable
A9: Objective Exam | B9: Fillable examination template: observation, foot posture, palpation map by region, range, capacity, balance, special tests, vascular and neurological screen, FOOTWEAR. | C9: First consultation and every re-assessment. | D9: Fillable
A10: Special Tests | B10: 30 tests grouped by region and tissue, with what a positive means and how much weight to give it. | C10: During the physical examination. | D10: Reference
A11: Clusters & Classification | B11: Seven diagnostic clusters, fifteen one-line differentiators, and the tendinopathy continuum, tensile-versus-compressive rule, Ottawa Rules, bone stress risk stratification and foot posture frameworks. | C11: When the picture is not yet clear, and when choosing a pathway. | D11: Reference
A12: Imaging Guide | B12: When to image, which modality answers which question, and the traps — including why CT beats MRI for the navicular. | C12: Before requesting or when reading a report. | D12: Reference
A13: Phased Programme | B13: Phase 0-4 with goals, content, markers and exit criteria, plus the master treatment sequence. | C13: Building and progressing every plan. | D13: Reference
A14: Exercise & Dosage | B14: Loading library with dose and indication, including heavy slow resistance, the Rathleff high-load protocol, tibialis posterior adduction loading and balance training. | C14: Writing the actual programme. | D14: Reference
A15: Adjuncts & Advanced | B15: Footwear, orthoses, taping, external ankle support, offloading, ESWT, injection and surgery, with the sequencing rule. | C15: When loading alone is not enough — and in the foot, it often is not. | D15: Reference
... A24: References | B24: Guideline and trial sources. | C24: Verifying or citing. | D24: —
A26: CRITICAL POINTS FOR THE FOOT & ANKLE
A27: • THE FOOT'S DEFINING TRAP IS THE DIABETIC ONE: a HOT, SWOLLEN, RED FOOT WITH INTACT SKIN in a neuropathic patient is CHARCOT NEUROARTHROPATHY until proven otherwise. Immobilise, stop weight bearing and refer the same day. It is routinely misdiagnosed as cellulitis, gout or a sprain, and every day of walking destroys more bone.
A28: • THE SECOND TRAP IS THE ACHILLES DISTINCTION: MIDPORTION tendinopathy tolerates loading through dorsiflexion; INSERTIONAL does not. Eccentric drops off a step and calf stretching COMPRESS the insertion and make insertional disease worse. Locate the pain precisely before prescribing.
A29: • THE THIRD TRAP IS THE NAVICULAR: a vague dorsal midfoot ache in a sprinting athlete is a navicular stress fracture until CT says otherwise. A normal radiograph means nothing, and partial weight bearing fails — the conservative protocol is STRICT non-weight-bearing for 6 weeks.
A30: • APPLY THE OTTAWA ANKLE AND FOOT RULES to every acute injury. They are highly sensitive and exist to help you avoid unnecessary imaging, not to replace examination.
A31: • MEASURE ANKLE DORSIFLEXION (weight-bearing lunge) IN EVERY PATIENT. It is the single most modifiable risk factor across the entire region — implicated in plantar heel pain, Achilles tendinopathy, ankle sprain recurrence, anterior impingement and bone stress.
A32: • MEASURE THE SINGLE-LEG HEEL RAISE and record BOTH the repetitions and whether the heel inverts. It is two tests in one — calf endurance and tibialis posterior function — and it is the functional benchmark for the whole region.
A33: • BALANCE TRAINING IS NOT OPTIONAL after an ankle sprain. Resting a sprain is not rehabilitating it, and up to 40% go on to chronic instability. External support for 6-12 months on return is one of the best-evidenced prevention measures in sports medicine.
A34: • ALWAYS EXAMINE THE FOOTWEAR. In forefoot and heel presentations a shoe change frequently outperforms any exercise you can prescribe, and it is the thing most often never looked at.
A35: • Yellow cells are inputs. Green text is pulled from another sheet. Do not overwrite formula cells.

Sheet Master Matrix
A1: MASTER DIAGNOSTIC & MANAGEMENT MATRIX — 41 FOOT & ANKLE CONDITIONS
A2: Columns A–L follow the established diagnostics-algorithm structure. Columns M–Y add the management programme. Crimson in column O marks a red-flag or time-sensitive presentation.
A3: Region | B3: Activity Level | C3: Common Symptoms | D3: Age Group | E3: Onset | F3: Predominance | G3: Condition | H3: High-Yield Diagnostic Question | I3: Special Test + Imaging | J3: Underlying Biomechanical Cause | K3: DESIRED ACTIVITY GOAL | L3: PHYSIOTHERAPY SPECIFIC EXERCISE | M3: Pain Mechanism | N3: Classification / Cluster | O3: Red Flag Status | P3: MANAGEMENT EMPHASIS | Q3: Loading Stage & Entry Dose | R3: BIOMECHANICAL CORRECTIONS & KINETIC CHAIN | S3: Footwear, Orthoses & Adjuncts | T3: Advanced / Surgical Options | U3: Outcome Measures | V3: Re-testable Markers | W3: Expected Timeline | X3: Referral / Surgical Trigger | Y3: Evidence Anchor
A4: Lateral | B4: Court and field sport, trail running, any uneven surface; the commonest musculoskeletal injury in sport | C4: Sudden lateral ankle pain after an inversion roll, with swelling and difficulty weight-bearing | D4: 15-45 | E4: Sudden | F4: Equal | G4: Acute Lateral Ankle Sprain (ATFL / CFL) | H4: Did the ankle roll inwards, and can you take four steps on it? | I4: APPLY THE OTTAWA ANKLE RULES FIRST; anterior drawer and anterolateral drawer at 10-15 degrees plantarflexion; talar tilt; ATFL and CFL tenderness. Delayed physical examination at 4-5 days is far more accurate than examining a swollen acute ankle | J4: Inversion and internal rotation on a plantarflexed foot exceeding lateral ligament capacity; ATFL fails first, then CFL. Deficits that predispose: reduced ankle dorsiflexion, poor peroneal reaction time, impaired postural control, hip abductor weakness, and a prior sprain (the single strongest risk factor) | K4: Return to full sport and uneven terrain with confident, stable weight bearing and no giving way | L4: EARLY PROTECTED WEIGHT BEARING and mobilisation beat immobilisation. Ankle dorsiflexion mobility (weight-bearing lunge) from day 2-3; peroneal and calf loading (heel raises, banded eversion) 3-4 sets 3x/week; BALANCE AND PROPRIOCEPTIVE TRAINING (single-leg stance progressing to unstable surface and dynamic tasks) daily - this is the intervention that reduces re-injury; hop and landing progression; then change-of-direction and sport-specific | M4: Nociceptive - acute ligamentous | N4: Cluster 1 - Lateral ankle sprain. Grade I-III by laxity and function. UP TO 40% DEVELOP CHRONIC ANKLE INSTABILITY - the acute management determines that | O4: Screen: apply the OTTAWA ANKLE RULES to exclude fracture. Also exclude syndesmotic injury, fifth metatarsal base fracture, osteochondral lesion and peroneal tendon injury | P4: Early functional rehabilitation with PROTECTED WEIGHT BEARING, not immobilisation. EXERCISE AND BALANCE TRAINING IS THE CORE INTERVENTION and is what prevents recurrence. Bracing or taping for the first 6-12 months of return reduces re-injury substantially | Q4: Stage 1-4. Days 0-3: protected weight bearing, compression, early range. Week 1-2: dorsiflexion mobility and peroneal/calf loading. Week 2-6: progressive balance and strength. Week 4-12: hop, landing, change of direction, sport-specific | R4: Correct the deficits that caused it and that predict recurrence: restore ankle DORSIFLEXION range (a known re-injury risk), build peroneal and calf capacity, retrain postural control and landing mechanics, address hip abductor weakness and frontal-plane control, and review footwear and playing surface | S4: External support (brace or tape) for 6-12 months on return to sport - one of the best-evidenced re-injury prevention measures; compression and elevation acutely; a walking boot only for a severe grade III for a short period | T4: If persistent instability beyond 3-6 months of correct rehabilitation: imaging for osteochondral lesion and peroneal pathology; surgical stabilisation (Brostrom-Gould) for confirmed mechanical instability | U4: FAAM and FAAM-Sport; CAIT (Cumberland Ankle Instability Tool); NRS; weight-bearing lunge test in cm | V4: Weight-bearing lunge test (cm); single-leg balance time; hop test symmetry; giving-way episodes; swelling | W4: Grade I 1-3 weeks; grade II 3-6 weeks; grade III 6-12 weeks to sport | X4: Ottawa positive; persistent instability after 3-6 months; suspected osteochondral or peroneal injury | Y4: Ottawa Ankle Rules (Stiell); Vuurberg et al. BJSM 2018 ankle sprain guideline; Doherty CAI incidence
A5: Lateral | B5: Court and field sport, trail running; anyone with repeated sprains | C5: Repeated giving way and a sense of the ankle being unreliable on uneven ground | D5: 18-45 | E5: Slow after repeated sprains | F5: Equal | G5: Chronic Ankle Instability | H5: Does the ankle keep giving way, or feel like it might, on uneven ground? | I5: Anterior drawer and talar tilt for MECHANICAL laxity; CAIT score under 24 supports FUNCTIONAL instability; deficits on single-leg balance, Star Excursion Balance Test and hop testing; MRI where an osteochondral lesion or peroneal tear is suspected | J5: A combination of MECHANICAL laxity (attenuated ATFL and CFL) and FUNCTIONAL deficits - impaired proprioception and postural control, delayed peroneal reaction time, reduced dorsiflexion range with anterior talar positioning, and altered landing and gait strategy. Most patients have more functional than mechanical deficit | K5: Return to sport and uneven terrain without giving way, and stop the cycle of recurrent sprains | L5: BALANCE AND NEUROMUSCULAR TRAINING IS THE PRIMARY INTERVENTION - single-leg stance progressing to unstable surface, eyes closed, and dynamic perturbation, 4-6 weeks minimum, daily; peroneal and calf strengthening 3-4 sets 8-12 RM 3x/week; ankle dorsiflexion mobilisation (Mulligan mobilisation with movement has good support); hop, landing and change-of-direction progression; hip abductor and frontal-plane control | M5: Nociceptive with a strong functional and confidence component | N5: Lateral group; distinguish MECHANICAL from FUNCTIONAL instability - they need different weighting, and most cases are predominantly functional | O5: Screen: recurrent instability warrants imaging for OSTEOCHONDRAL LESION of the talus and peroneal tendon tears, both of which are commonly missed and perpetuate symptoms | P5: Exercise-based rehabilitation with a heavy emphasis on BALANCE AND NEUROMUSCULAR TRAINING is first-line and effective. Bracing or taping during sport. Surgical stabilisation (Brostrom-Gould) for confirmed mechanical instability that has failed a genuine programme | Q5: Stage 2-4. Progressive balance and neuromuscular loading daily for 4-6 weeks minimum; peroneal and calf strengthening 3x/week; then hop, landing and change-of-direction progression; then sport-specific with external support | R5: Address the whole chain and the mechanics: restore ankle dorsiflexion and correct anterior talar positioning, build peroneal reaction and calf capacity, retrain landing and cutting mechanics, build hip abductor and frontal-plane control, review footwear and surface, and use external support during sport | S5: Brace or tape during sport - well evidenced for re-injury prevention; Mulligan mobilisation with movement for dorsiflexion restriction | T5: Imaging for osteochondral lesion and peroneal tears; Brostrom-Gould lateral ligament repair for confirmed mechanical instability (see Post-Surgical Guide, category 1) | U5: CAIT; FAAM and FAAM-Sport; Star Excursion Balance Test; giving-way episode count | V5: CAIT score; single-leg balance time (eyes open and closed); Star Excursion reach; hop symmetry; giving-way frequency | W5: 12 weeks minimum for a genuine neuromuscular programme; 6-9 months post stabilisation | X5: Confirmed mechanical instability after a genuine programme; suspected osteochondral lesion or peroneal tear | Y5: Delahunt/Gribble CAI consensus; balance training evidence in CAI
A6: Lateral | B6: Runner, dancer, court athlete; also anyone with a cavovarus foot or after ankle sprain | C6: Pain and swelling behind and below the lateral malleolus, worse with push-off and on uneven ground | D6: 25-50 | E6: Slow | F6: Female | G6: Peroneal Tendinopathy | H6: Is the pain behind the bony bump on the outside of the ankle, and worse pushing off or on uneven ground? | I6: Tenderness along the peroneal tendons posterior to the lateral malleolus; pain on resisted EVERSION and on passive inversion stretch; single-leg heel raise reproduces it; ultrasound or MRI for tendon change, tears or a low-lying peroneus brevis muscle belly | J6: Tensile and compressive overload of the peroneal tendons as they turn around the lateral malleolus; a CAVOVARUS foot posture increases peroneal demand markedly; lateral ankle instability increases peroneal work as a dynamic stabiliser; a training volume or terrain change (cambered roads, trail); reduced ankle dorsiflexion; poor calf capacity | K6: Return to full running or dance volume, including uneven terrain, without lateral ankle pain | L6: ISOMETRIC eversion holds 5 x 30-45 s for analgesia; progressive isotonic peroneal loading (banded eversion, single-leg heel raise in slight eversion) 3-4 sets 8-12 RM 3x/week; calf complex heavy slow resistance; balance and proprioceptive work; then energy-storage hopping and graded return to running or dance volume | M6: Nociceptive - tensile and compressive tendon load | N6: Lateral group - tendinopathy continuum. Stage reactivity. ALWAYS assess for a CAVOVARUS foot and for lateral ankle instability - both drive it | O6: Screen: assess for peroneal tendon SUBLUXATION and for a tear (particularly peroneus brevis longitudinal split), and for an underlying cavovarus foot | P6: Progressive loading with staged reactivity, plus correction of the driver. If the foot is cavovarus or the ankle unstable, the tendon will keep failing unless that is addressed with orthoses and instability rehabilitation | Q6: Reactive: isometrics plus peak load reduction. Dysrepair/degenerative: heavy slow resistance 3x/week; then energy storage and graded return to volume and terrain | R6: Address the driver, not just the tendon: LATERAL WEDGE OR ORTHOTIC POSTING for a cavovarus foot to reduce peroneal demand, treat coexisting lateral ankle instability, restore ankle dorsiflexion, build calf and peroneal capacity, avoid cambered running surfaces during the settling phase, and grade terrain and volume | S6: Orthoses with lateral posting for cavovarus (the highest-yield adjunct here); activity and terrain modification; taping for comfort | T6: If stalled beyond 12 weeks: imaging for a tendon tear; ESWT as an adjunct; surgical debridement, tubularisation or repair for a confirmed significant tear | U6: FAAM; VISA-A adapted; NRS on push-off and uneven ground | V6: Resisted eversion pain; single-leg heel raise repetitions; running or dance volume tolerance; terrain tolerance | W6: 12 weeks minimum | X6: Suspected tendon tear or subluxation; failure after 12 weeks of correct loading with the driver addressed | Y6: Cook & Purdam continuum; peroneal tendon pathology literature
A7: Lateral | B7: Skiing, football, dance; forced dorsiflexion with eversion | C7: A snapping or popping sensation behind the lateral malleolus with a sense of instability | D7: 18-40 | E7: Sudden/Slow | F7: Male | G7: Peroneal Tendon Subluxation / Dislocation | H7: Does something snap or flick over the bone on the outside of the ankle when you move it? | I7: Visible or palpable subluxation of the peroneal tendons over the lateral malleolus on active dorsiflexion with eversion; tenderness over the superior peroneal retinaculum; DYNAMIC ULTRASOUND is the investigation of choice; CT if a fleck fracture of the fibula is suspected | J7: Disruption or attenuation of the SUPERIOR PERONEAL RETINACULUM allowing the tendons to sublux anteriorly over the fibula; a shallow retromalleolar groove and a low-lying peroneus brevis muscle belly are predisposing; forced dorsiflexion with sudden peroneal contraction is the classic mechanism | K7: Return to sport with the tendons stable in the retromalleolar groove and no snapping | L7: Acute: immobilisation in slight plantarflexion and inversion for 4-6 weeks may allow retinacular healing. Chronic: peroneal and calf strengthening, balance work and activity modification while awaiting surgical opinion; post-repair, progressive peroneal loading and balance work per surgeon | M7: Nociceptive - mechanical instability | N7: Lateral group; FREQUENTLY MISDIAGNOSED AS A RECURRENT LATERAL ANKLE SPRAIN. The snapping and the location behind rather than in front of the malleolus are the discriminators | O7: Screen: a fleck of avulsed fibular cortex on radiograph indicates retinacular avulsion and usually needs surgery | P7: Acute first-time: trial of immobilisation in plantarflexion and inversion for 4-6 weeks. Recurrent or chronic subluxation: SURGICAL retinacular repair with or without groove deepening - conservative management of chronic subluxation has a high failure rate | Q7: Post-repair per surgeon: protected weight bearing 4-6 weeks; progressive peroneal loading from 6-8 weeks; balance and hop progression from 10-12 weeks; sport 4-6 months | R7: Address the predisposing anatomy and the chain: correct a cavovarus posture with orthoses, build peroneal and calf capacity, restore ankle dorsiflexion, retrain balance and landing, and review ski boot or footwear fit | S7: Immobilisation in plantarflexion and inversion for an acute first-time episode; bracing during the interim | T7: Superior peroneal retinaculum repair with fibular groove deepening (see Post-Surgical Guide, category 1) | U7: FAAM; FAOS; snapping frequency; CAIT | V7: Snapping frequency and pain; peroneal strength; balance; sport tolerance | W7: 4-6 weeks immobilisation acutely; 4-6 months post surgical repair | X7: Recurrent subluxation, a fibular fleck fracture, or failure of conservative management | Y7: Peroneal tendon subluxation management literature
A8: Lateral | B8: Runner, court athlete; commonly follows an inversion sprain | C8: Persistent pain deep in the hollow just in front of the lateral malleolus, with a feeling of hindfoot instability | D8: 20-45 | E8: Slow after a sprain | F8: Equal | G8: Sinus Tarsi Syndrome | H8: Is the sore spot in the soft hollow just in front of and below the outer ankle bone, and did it start after a sprain? | I8: Focal tenderness in the SINUS TARSI (the soft hollow anterior to the lateral malleolus); pain on end-range inversion and supination; symptoms reproduced on uneven ground; a diagnostic local anaesthetic injection into the sinus tarsi is confirmatory; MRI shows synovitis or fibrosis | J8: Post-traumatic synovitis, fibrosis or instability within the sinus tarsi following an inversion injury; subtalar instability and impaired proprioception from the dense mechanoreceptor population in the sinus tarsi perpetuate it; excessive pronation or a hypermobile hindfoot increases sinus tarsi load | K8: Return to running and uneven terrain without lateral hindfoot pain or a sense of instability | L8: Subtalar and ankle proprioceptive and balance training (single-leg stance, unstable surface, dynamic perturbation) daily; peroneal and tibialis posterior loading 3-4 sets 8-12 RM 3x/week; calf complex loading; graded return to uneven terrain and running volume | M8: Nociceptive - synovitis and mechanical | N8: Lateral group; largely a DIAGNOSIS OF EXCLUSION after an inversion injury. Exclude osteochondral lesion, peroneal pathology and subtalar coalition first | O8: Screen: exclude an osteochondral lesion of the talus, peroneal tendon tear and subtalar coalition before settling on this label | P8: Proprioceptive and neuromuscular rehabilitation with control of excessive pronation. A diagnostic and therapeutic corticosteroid injection into the sinus tarsi is a reasonable adjunct. Arthroscopic debridement for genuinely refractory cases | Q8: Stage 2-3. Balance and proprioceptive loading daily; peroneal and tibialis posterior strengthening 3x/week; graded terrain and volume progression | R8: Control the hindfoot: orthoses with medial posting where excessive pronation loads the sinus tarsi, restore subtalar proprioception, build peroneal and tibialis posterior capacity, address coexisting lateral ankle instability, and grade uneven terrain exposure | S8: Orthoses with medial posting; taping for hindfoot control; activity modification | T8: Guided sinus tarsi injection (diagnostic and therapeutic); arthroscopic debridement for refractory cases | U8: FAAM; FAOS; CAIT; NRS on uneven ground | V8: Sinus tarsi tenderness; single-leg balance; uneven terrain tolerance; end-range inversion pain | W8: 8-12 weeks | X8: Failure after 3 months; suspected osteochondral lesion or coalition | Y8: Sinus tarsi syndrome literature
A9: Lateral | B9: Court and field sport, basketball, football; also cavovarus foot | C9: Lateral forefoot pain after an inversion injury, or a gradual ache that became acute | D9: 18-40 | E9: Sudden/Slow | F9: Male | G9: Fifth Metatarsal Base Fracture (Avulsion vs Jones) | H9: Is the sore spot on the bony bump on the outer edge of the midfoot, and had it been aching before it became acute? | I9: Focal tenderness at the fifth metatarsal base; ZONE MATTERS - Zone 1 (tuberosity avulsion) versus Zone 2 (JONES, at the metaphyseal-diaphyseal junction) versus Zone 3 (proximal diaphyseal stress fracture); AP, lateral and OBLIQUE radiographs; CT for union assessment | J9: ZONE 1 avulsion: peroneus brevis or lateral band traction during inversion - heals reliably. ZONE 2 (JONES): a watershed vascular zone loaded by lateral column forces during cutting and jumping - notorious for delayed union, non-union and refracture. A CAVOVARUS foot with a varus heel drives lateral column overload and is the key predisposing factor | K9: Achieve union and return to cutting and jumping sport without refracture | L9: Zone 1: protected weight bearing in a stiff-soled shoe or boot, early range, progressive peroneal and calf loading, graded return over 6-8 weeks. Zone 2 (Jones): NO impact until union - non-impact conditioning, then graded weight bearing, calf and peroneal loading, then hop and cutting progression | M9: Nociceptive - acute fracture or bone stress | N9: Lateral group - FRACTURE. Torg classification for Jones fractures (acute / delayed union / non-union). ZONE 2 IS A HIGH-RISK SITE | O9: YES for ZONE 2 (JONES) - a watershed zone with the highest refracture rate of any foot fracture. Orthopaedic referral; intramedullary screw fixation is standard in athletes | P9: ZONE 1: conservative with a stiff-soled shoe and graded return - reliable healing. ZONE 2 (JONES): orthopaedic referral. Intramedullary screw fixation is standard in athletes and gives a faster, more reliable return than strict non-weight-bearing casting. ADDRESS THE CAVOVARUS FOOT or it will refracture | Q9: Zone 1: weight bearing as tolerated in a stiff-soled shoe; progressive loading from 2-4 weeks. Zone 2: zero impact until radiological union; then graded weight bearing, loading, hop and cutting progression | R9: PREVENT THE REFRACTURE: prescribe a LATERAL FOREFOOT POST OR ORTHOSIS to redistribute load off the fifth ray in a cavovarus foot, build peroneal and calf capacity, restore ankle dorsiflexion, retrain cutting mechanics, and review footwear and playing surface | S9: Stiff-soled shoe or carbon plate; orthotic prescription is central to recurrence prevention; boot for a Jones fracture pending fixation | T9: Intramedullary screw fixation for Jones fractures in athletes; bone health and vitamin D review; CT to confirm union before clearance | U9: FAAM; FAOS; radiographic and CT union | V9: Focal tenderness; radiological union; hop symmetry; cutting tolerance | W9: Zone 1: 6-8 weeks. Zone 2: 8-12 weeks with fixation; 3-6 months conservatively with a high refracture rate | X9: Any Zone 2 (Jones) fracture - orthopaedic referral. Delayed union or refracture | Y9: Torg classification; Jones fracture management literature
A10: Medial | B10: Walker, runner; also sedentary. Middle-aged women are heavily over-represented | C10: Medial ankle and arch pain with progressive flattening of the arch and difficulty on single-leg heel raise | D10: 40-65 | E10: Slow | F10: Female | G10: Tibialis Posterior Tendinopathy / Progressive Collapsing Foot Deformity | H10: Can you do a single-leg heel raise on that side, and does the heel turn inwards when you do? | I10: SINGLE-LEG HEEL RAISE TEST is the key clinical test - inability, or absence of hindfoot inversion during the raise, is diagnostic; TOO MANY TOES SIGN from behind; tenderness along the tendon posterior to the medial malleolus; pain on resisted inversion in plantarflexion; weight-bearing radiographs for alignment; ultrasound or MRI for tendon change | J10: Progressive failure of the tibialis posterior as the primary dynamic arch support, allowing hindfoot valgus, midfoot abduction and arch collapse; obesity, diabetes, hypertension, inflammatory disease and corticosteroid exposure are risk factors; the deformity becomes progressively FIXED if untreated, which is why staging matters | K10: Restore single-leg heel raise capacity, walk without medial pain, and prevent progression of the deformity | L10: HEAVY SLOW RESISTANCE tibialis posterior loading in ADDUCTION (banded foot adduction with the forefoot, progressing to weighted) 3-4 sets 8-12 RM 3x/week - this specific exercise has the best support; eccentric and concentric heel raises progressing to SINGLE-LEG with hindfoot inversion cueing; intrinsic foot muscle work; calf complex loading; hip abductor and frontal-plane control; graded walking progression | M10: Nociceptive - tensile tendon load with progressive deformity | N10: Cluster 2 - Progressive Collapsing Foot Deformity (formerly adult acquired flatfoot). STAGE IT: Stage 1 tenderness with normal alignment; Stage 2 FLEXIBLE deformity; Stage 3 RIGID deformity; Stage 4 ankle involvement. FLEXIBLE versus RIGID determines everything | O10: Screen: STAGE THE DEFORMITY. A flexible deformity responds to orthoses and loading; a rigid one does not and needs surgical opinion | P10: Stage 1-2 (flexible): ORTHOSES WITH MEDIAL POSTING plus progressive tibialis posterior loading is the evidence-supported combination and works well. Stage 3-4 (rigid): orthoses and bracing for symptom control, with surgical opinion for reconstruction or arthrodesis. Early intervention prevents progression to a rigid deformity | Q10: Stage 1-2. Progressive tibialis posterior loading in adduction 3x/week; heel raise progression to single-leg; intrinsic and calf loading; graded walking volume increase | R10: Support the arch mechanically while you rebuild it dynamically: ORTHOSES WITH MEDIAL POSTING (or a custom device, or an ankle-foot orthosis in higher stages), build tibialis posterior and intrinsic foot capacity, restore calf capacity and ankle dorsiflexion, address hip abductor weakness and frontal-plane collapse, and support weight management where relevant | S10: ORTHOSES WITH MEDIAL POSTING are central, not optional; a UCBL or ankle-foot orthosis for higher stages; supportive footwear with a firm heel counter | T10: Surgical reconstruction (flexor digitorum longus transfer with medialising calcaneal osteotomy) for a flexible deformity that fails conservative care; triple arthrodesis for a rigid deformity | U10: FAAM; FAOS; single-leg heel raise repetitions; MOXFQ | V10: SINGLE-LEG HEEL RAISE repetitions and quality (does the heel invert?); too many toes sign; walking tolerance; arch height | W10: 12 weeks for meaningful change; ongoing management with orthoses | X10: Rigid deformity; failure of a genuine 3-6 month programme with orthoses; rapid progression | Y10: Progressive Collapsing Foot Deformity consensus (Myerson 2020); Kulig tibialis posterior loading protocol
A11: Medial | B11: Court and field sport; eversion or external rotation mechanism | C11: Medial ankle pain and swelling after an eversion injury | D11: 18-40 | E11: Sudden | F11: Male | G11: Deltoid Ligament Sprain | H11: Did the ankle roll outwards rather than inwards, with pain on the inside? | I11: Deltoid tenderness below the medial malleolus; pain and laxity on EVERSION stress; ALWAYS assess the SYNDESMOSIS and the PROXIMAL FIBULA - a deltoid injury with a proximal fibular fracture is a Maisonneuve injury; Ottawa rules; weight-bearing or gravity stress radiographs for medial clear space widening | J11: Eversion and external rotation force exceeding deltoid capacity; the deltoid is strong and isolated sprains are uncommon, so an isolated-looking deltoid injury should raise suspicion of a syndesmotic or proximal fibular injury; reduced dorsiflexion and poor frontal-plane control contribute | K11: Return to sport with a stable medial ankle and no residual instability | L11: Protected weight bearing early; ankle dorsiflexion mobility; tibialis posterior and calf loading 3-4 sets 3x/week; balance and proprioceptive training; then hop, landing and change-of-direction progression | M11: Nociceptive - traumatic ligamentous | N11: Medial group; an ISOLATED deltoid sprain is uncommon - always look for the associated injury | O11: YES - a deltoid injury demands assessment of the SYNDESMOSIS and PALPATION OF THE PROXIMAL FIBULA. A Maisonneuve fracture is easily missed and is unstable | P11: Protected mobilisation and progressive loading for an isolated low-grade sprain. Any medial clear space widening, syndesmotic involvement or proximal fibular fracture indicates an UNSTABLE ankle needing surgical fixation | Q11: Stage 1-4. Protected weight bearing early; progressive mobility, strength and balance; then hop, landing and sport-specific progression | R11: Rebuild frontal-plane control: tibialis posterior and calf capacity, ankle dorsiflexion range, balance and proprioception, hip abductor and landing mechanics, and external support during return to sport | S11: Boot or brace for the protected phase; taping for return to sport | T11: Surgical fixation where there is medial clear space widening, syndesmotic instability or a Maisonneuve fracture | U11: FAAM; FAOS; CAIT | V11: Medial tenderness; eversion stress pain; balance; hop symmetry; sport tolerance | W11: 4-8 weeks for an isolated low-grade sprain; longer if unstable | X11: Medial clear space widening, syndesmotic involvement, or proximal fibular tenderness | Y11: Ankle instability and Maisonneuve injury literature
A12: Medial | B12: Runner, walker; also pregnancy, diabetes, and after ankle trauma | C12: Burning, tingling or numbness in the sole of the foot, often worse at night and with prolonged standing | D12: 35-60 | E12: Slow | F12: Female | G12: Tarsal Tunnel Syndrome | H12: Is there burning or tingling in the SOLE of the foot rather than aching, and is it worse at night? | I12: Positive TINEL over the tarsal tunnel behind the medial malleolus; positive DORSIFLEXION-EVERSION TEST held 10 seconds; sensory change in the medial and lateral plantar nerve distributions; NERVE CONDUCTION STUDIES; MRI or ultrasound for a space-occupying lesion (ganglion, varicosity, accessory muscle) | J12: Compression of the posterior tibial nerve or its branches beneath the flexor retinaculum; a SPACE-OCCUPYING LESION is present in a substantial proportion and must be excluded; excessive pronation increases traction on the nerve; post-traumatic fibrosis, systemic conditions (diabetes, inflammatory disease) and fluid retention in pregnancy contribute | K12: Resolve the burning and numbness and return to standing, walking and running without symptoms | L12: Tibial nerve gliding within symptom tolerance; PRONATION CONTROL with orthoses to reduce nerve traction; tibialis posterior and intrinsic foot loading; calf loading; graded return to standing and walking volume; footwear modification | M12: Neuropathic | N12: Medial group - PERIPHERAL NERVE. Distinguish from plantar heel pain (which is mechanical and worst with first steps) and from lumbar radiculopathy and peripheral neuropathy | O12: YES - IMAGE TO EXCLUDE A SPACE-OCCUPYING LESION. A ganglion, varicosity or accessory muscle is present in a significant proportion and changes the management entirely | P12: Exclude a space-occupying lesion by imaging. Then conservative: orthoses to control pronation and reduce nerve traction, neural mobilisation, footwear change, and treatment of any systemic contributor. Surgical decompression for a confirmed lesion or genuinely refractory symptoms | Q12: Nerve-irritability-guided. Neural gliding first; progressive intrinsic, tibialis posterior and calf loading as symptoms allow; graded standing and walking volume | R12: Reduce the traction and compression: ORTHOSES TO CONTROL PRONATION, build tibialis posterior and intrinsic capacity to support the arch dynamically, review footwear for a firm heel counter and adequate medial support, modify prolonged standing, and address systemic contributors | S12: Orthoses with medial posting; footwear modification; night splinting in selected cases | T12: Imaging for a space-occupying lesion; nerve conduction studies; surgical tarsal tunnel release for a confirmed lesion or refractory symptoms | U12: FAAM; FAOS; symptom mapping; standing and walking tolerance | V12: Tinel and dorsiflexion-eversion test; symptom area and intensity; standing and walking tolerance | W12: 8-16 weeks conservatively | X12: A space-occupying lesion on imaging; progressive motor involvement; failure of 3-6 months of correct conservative care | Y12: Tarsal tunnel syndrome management literature
A13: Medial | B13: Classical ballet, gymnastics; repetitive extreme plantarflexion | C13: Pain behind the medial malleolus with rising on demi-pointe or en pointe, sometimes with triggering of the big toe | D13: 15-35 | E13: Slow | F13: Female | G13: Flexor Hallucis Longus Tenosynovitis (Dancer's Tendinitis) | H13: Does the pain sit behind the inner ankle bone and come on rising onto the ball of the foot or en pointe? | I13: Tenderness posterior to the medial malleolus over the FHL; pain on resisted great toe flexion; pain reproduced on demi-pointe and en pointe; TRIGGERING or crepitus of the hallux; a positive FHL stretch test (hallux dorsiflexion with the ankle dorsiflexed); ultrasound or MRI shows tenosynovitis | J13: Repetitive loading of the FHL as it passes through the fibro-osseous tunnel behind the talus during extreme plantarflexion; en pointe and demi-pointe volume, a poorly controlled roll-through, hallux valgus or a functional hallux limitus increasing FHL demand, and reduced ankle plantarflexion range forcing compensation. FREQUENTLY COEXISTS WITH POSTERIOR ANKLE IMPINGEMENT | K13: Return to full pointe and demi-pointe work without posteromedial ankle pain or hallux triggering | L13: Isometric hallux flexion holds for analgesia; progressive isotonic FHL and intrinsic foot loading 3-4 sets 8-12 RM 3x/week; calf complex heavy slow resistance; ankle plantarflexion and dorsiflexion range work; roll-through technique retraining; graded return to demi-pointe then pointe volume | M13: Nociceptive - tensile and friction tendon load | N13: Medial group; the classic DANCER'S diagnosis. ALWAYS assess for coexisting POSTERIOR ANKLE IMPINGEMENT and an os trigonum - they travel together | O13: Screen: assess for posterior ankle impingement and an os trigonum, which frequently coexist and may need addressing together | P13: Load management of pointe volume, progressive FHL and calf loading, technique correction, and pointe readiness assessment. Surgical tenolysis, often combined with os trigonum excision, for genuinely refractory cases | Q13: Stage 1-3. Isometrics for analgesia; progressive FHL, intrinsic and calf loading 3x/week; then graded demi-pointe and pointe volume progression | R13: Reduce the demand on the FHL: correct roll-through and pointe technique, restore ankle plantarflexion and dorsiflexion range, build calf and intrinsic capacity, address hallux mechanics and any functional hallux limitus, review pointe shoe fit and readiness, and cap pointe minutes | S13: Pointe shoe fit review; activity and volume modification; taping | T13: Guided injection into the sheath for refractory cases; surgical FHL tenolysis with os trigonum excision where both coexist (see Post-Surgical Guide, category 4) | U13: FAAM; FAOS; pointe minutes tolerance; NRS on demi-pointe | V13: Resisted hallux flexion pain; triggering frequency; demi-pointe and pointe tolerance; calf endurance | W13: 8-12 weeks | X13: Refractory after 3 months; persistent triggering; coexisting os trigonum needing excision | Y13: Dance medicine literature; FHL tenosynovitis management
A14: Medial | B14: Distance running, military recruit training; a sudden mileage increase | C14: Medial ankle pain with running that has become focal and persistent | D14: 18-40 | E14: Slow | F14: Equal | G14: Medial Malleolar Stress Fracture | H14: Is the pain on the bone at the inside of the ankle rather than along a tendon, and does it persist after you stop? | I14: Focal tenderness over the MEDIAL MALLEOLUS itself (not the tendon); pain on hop and on forced dorsiflexion; MRI or CT (radiograph may show a vertical lucency at the plafond junction) | J14: Repetitive impaction of the talus against the medial malleolus in dorsiflexion; high running and cutting volume, over-pronation, reduced ankle dorsiflexion, and a training volume spike; low energy availability reduces bone capacity | K14: Return to running with the load error corrected and bone health addressed | L14: NO impact until pain-free. Non-impact conditioning; then progressive weight bearing, calf and tibialis posterior loading, then a structured walk-run programme with weekly increments and volume logged | M14: Nociceptive - bone stress | N14: Medial group - BONE STRESS INJURY. A HIGH-RISK SITE: the vertical fracture line at the plafond junction has displacement and non-union potential | O14: YES - a HIGH-RISK bone stress site. Orthopaedic referral. Fixation is often indicated for a visible fracture line or in a competitive athlete needing a reliable timeline | P14: Orthopaedic referral. Conservative offloading (boot or protected weight bearing) for a low-grade lesion; SURGICAL FIXATION for a visible fracture line or a competitive athlete. The symptom window here is PAIN-FREE, not the usual tendon rule | Q14: PAIN-FREE loading only. No impact until cleared; non-impact conditioning; then protected walking, pain-free walking, walk-run, and cutting last | R14: Correct the cause: restore ankle dorsiflexion range, control over-pronation with orthoses where contributory, build calf and tibialis posterior capacity, retrain cutting and deceleration mechanics, and progress volume 10-15% weekly with an acute:chronic ceiling of 1.3 | S14: Boot or protected weight bearing; non-impact conditioning; orthoses where pronation is contributory | T14: Surgical fixation where indicated; bone health, nutrition and energy availability review | U14: FAAM; FAOS; radiological union; pain-free running volume | V14: Focal tenderness; pain-free walking and hopping; imaging healing; running volume tolerance | W14: 3-6 months | X14: Any suspected medial malleolar stress fracture - orthopaedic referral (high-risk site) | Y14: High-risk bone stress injury consensus; BJSM BSI guidance
... A44: Systemic / Referred | B44: High-energy trauma, tibial fracture, crush injury, or tight casting | C44: Escalating leg pain with tightness after trauma or casting, disproportionate to the injury | D44: Any | E44: Sudden | F44: Male | G44: Acute Compartment Syndrome of the Leg | H44: Is the leg pain escalating and out of proportion, with severe pain on passively stretching the toes? | I44: PAIN OUT OF PROPORTION and escalating despite analgesia; PAIN ON PASSIVE STRETCH OF THE TOES AND ANKLE is the most sensitive early sign; a tense swollen compartment; paraesthesia (first web space sensation in anterior compartment involvement); PULSES AND CAPILLARY REFILL ARE OFTEN NORMAL EARLY AND MUST NOT BE USED TO EXCLUDE IT; compartment pressure measurement | J44: Rising pressure within a closed fascial compartment after fracture, crush injury, reperfusion, bleeding or constrictive casting, compromising perfusion and causing muscle and nerve necrosis. The ANTERIOR compartment is most commonly affected in the leg. NOT a rehabilitation problem at any stage of its acute course | K44: Emergency decompression to preserve limb function and prevent permanent contracture and foot drop | L44: NONE. This is a surgical emergency. Post-fasciotomy and post-recovery: range maintenance, contracture prevention, splinting for foot drop, and progressive strengthening as tissue and nerve recovery allows | M44: Nociceptive - ischaemic | N44: Systemic group - SURGICAL EMERGENCY. Distinguish sharply from CHRONIC EXERTIONAL compartment syndrome, which is exercise-induced, resolves with rest, and is NOT an emergency | O44: YES - LIMB-THREATENING EMERGENCY. Pain out of proportion with pain on passive toe stretch requires IMMEDIATE surgical assessment. NORMAL PULSES DO NOT EXCLUDE IT. Delay causes permanent contracture, foot drop and disability | P44: IMMEDIATE surgical referral for fasciotomy. Remove any constrictive cast or dressing. Do NOT elevate above heart level (this reduces perfusion pressure). Do not treat locally under any circumstances | Q44: None during the acute episode. Post-fasciotomy: range maintenance, contracture prevention and progressive strengthening as recovery allows | R44: Post-recovery: prevent and manage contracture with splinting and range work, provide an ankle-foot orthosis for foot drop, rebuild strength in surviving muscle, and adapt for residual deficit | S44: None acutely. Post-recovery: splinting, ankle-foot orthosis and contracture management | T44: Emergency fasciotomy; secondary reconstruction and tendon transfers for established contracture or foot drop | U44: Determined by outcome; LEFS, FAAM and range post-recovery | V44: Post-recovery: range, contracture, strength, gait and functional performance | W44: Determined by the extent of muscle and nerve injury | X44: IMMEDIATE - this is a limb-threatening surgical emergency | Y44: Acute compartment syndrome guidelines

Sheet Rx Generator
A1: PRESCRIPTION GENERATOR
A2: Select a condition in the yellow cell. Every field below is pulled live from the Master Matrix.
A4: SELECT CONDITION → | B4: Plantar Heel Pain (Plantar Fasciopathy)
A6: Region | B6: =IFERROR(INDEX('Master Matrix'!A$4:A$44,MATCH($B$4,'Master Matrix'!$G$4:$G$44,0)),"") -> Plantar / Heel
A7: Activity level | B7: =IFERROR(INDEX('Master Matrix'!B$4:B$44,MATCH($B$4,'Master Matrix'!$G$4:$G$44,0)),"") -> Runner, walker, standing worker; also sedentary with raised body mass
A8: Common symptoms | B8: =IFERROR(INDEX('Master Matrix'!C$4:C$44,MATCH($B$4,'Master Matrix'!$G$4:$G$44,0)),"") -> Sharp pain under the heel with the first steps in the morning or after sitting, easing then returning after prolonged standing
A9: Age group | B9: =IFERROR(INDEX('Master Matrix'!D$4:D$44,MATCH($B$4,'Master Matrix'!$G$4:$G$44,0)),"") -> 40-60
A10: Onset | B10: =IFERROR(INDEX('Master Matrix'!E$4:E$44,MATCH($B$4,'Master Matrix'!$G$4:$G$44,0)),"") -> Slow
A11: Predominance | B11: =IFERROR(INDEX('Master Matrix'!F$4:F$44,MATCH($B$4,'Master Matrix'!$G$4:$G$44,0)),"") -> Female
A12: High-yield diagnostic question | B12: =IFERROR(INDEX('Master Matrix'!H$4:H$44,MATCH($B$4,'Master Matrix'!$G$4:$G$44,0)),"") -> Is it worst with the very first steps in the morning or after sitting, and does it ease as you walk then come back later?
A13: Special test + imaging | B13: =IFERROR(INDEX('Master Matrix'!I$4:I$44,MATCH($B$4,'Master Matrix'!$G$4:$G$44,0)),"") -> Focal tenderness at the MEDIAL CALCANEAL TUBERCLE; the FIRST-STEP PAIN PATTERN is characteristic; positive windlass test (pain on hallux dorsiflexion while weight bearing); reduced ankle dorsiflexion is a strong risk factor; imaging only if atypical or refractory - a heel spur is NOT the cause and is common in asymptomatic feet
A14: Underlying biomechanical cause | B14: =IFERROR(INDEX('Master Matrix'!J$4:J$44,MATCH($B$4,'Master Matrix'!$G$4:$G$44,0)),"") -> Tensile and compressive overload of the plantar fascia at its calcaneal origin, producing degenerative fasciopathy rather than inflammation; REDUCED ANKLE DORSIFLEXION is the strongest modifiable risk factor; raised body mass, prolonged standing occupations, a sudden increase in walking or running volume, reduced intrinsic foot capacity, and reduced calf capacity all contribute
A15: DESIRED ACTIVITY GOAL | B15: =IFERROR(INDEX('Master Matrix'!K$4:K$44,MATCH($B$4,'Master Matrix'!$G$4:$G$44,0)),"") -> Take the first steps of the morning and stand through a working day without heel pain
A16: PHYSIOTHERAPY SPECIFIC EXERCISE | B16: =IFERROR(INDEX('Master Matrix'!L$4:L$44,MATCH($B$4,'Master Matrix'!$G$4:$G$44,0)),"") -> PLANTAR FASCIA-SPECIFIC STRETCHING (toe dorsiflexion with cross-friction, 10 x 10 s, 3x/day) has good support; HIGH-LOAD STRENGTH TRAINING - single-leg heel raises with a towel under the toes to engage the windlass, 3-4 sets 8-12 RM every other day (Rathleff protocol); calf complex heavy slow resistance; INTRINSIC FOOT MUSCLE loading (short foot, toe yoga); ankle dorsiflexion mobility; graded walking and running progression
A17: Pain mechanism | B17: =IFERROR(INDEX('Master Matrix'!M$4:M$44,MATCH($B$4,'Master Matrix'!$G$4:$G$44,0)),"") -> Nociceptive - tensile and compressive; nociplastic overlay beyond 6 months
A18: Classification / cluster | B18: =IFERROR(INDEX('Master Matrix'!N$4:N$44,MATCH($B$4,'Master Matrix'!$G$4:$G$44,0)),"") -> Cluster 5 - Plantar heel pain: medial calcaneal tubercle tenderness + FIRST-STEP PAIN + reduced ankle dorsiflexion. Distinguish from Baxter's nerve entrapment and calcaneal stress fracture
A19: RED FLAG STATUS | B19: =IFERROR(INDEX('Master Matrix'!O$4:O$44,MATCH($B$4,'Master Matrix'!$G$4:$G$44,0)),"") -> Screen: distinguish from CALCANEAL STRESS FRACTURE (positive squeeze test, pain on every step rather than first steps) and BAXTER'S NERVE ENTRAPMENT (burning, more medial and proximal tenderness)
A20: MANAGEMENT EMPHASIS | B20: =IFERROR(INDEX('Master Matrix'!P$4:P$44,MATCH($B$4,'Master Matrix'!$G$4:$G$44,0)),"") -> Education, load management, ANKLE DORSIFLEXION RESTORATION, plantar fascia-specific stretching and HIGH-LOAD STRENGTH TRAINING. Taping and orthoses give useful short-term relief. Most resolve within 12 months but the course is slow - set that expectation explicitly
A21: Loading stage & entry dose | B21: =IFERROR(INDEX('Master Matrix'!Q$4:Q$44,MATCH($B$4,'Master Matrix'!$G$4:$G$44,0)),"") -> Stage 1-3. Plantar fascia-specific stretching 3x/day; high-load strength training every other day; calf and intrinsic loading; graded walking and running volume progression
A22: BIOMECHANICAL CORRECTIONS & KINETIC CHAIN | B22: =IFERROR(INDEX('Master Matrix'!R$4:R$44,MATCH($B$4,'Master Matrix'!$G$4:$G$44,0)),"") -> Address the strongest modifiable factor first: RESTORE ANKLE DORSIFLEXION. Then build calf and intrinsic foot capacity, control excessive pronation with orthoses where contributory, review footwear cushioning and age, modify prolonged standing with breaks and matting, support weight management where relevant, and grade walking and running volume
A23: FOOTWEAR, ORTHOSES & ADJUNCTS | B23: =IFERROR(INDEX('Master Matrix'!S$4:S$44,MATCH($B$4,'Master Matrix'!$G$4:$G$44,0)),"") -> Low-Dye or calcaneal taping for immediate short-term relief (useful diagnostically and to enable loading); prefabricated orthoses (equivalent to custom in most trials); night splints for persistent morning pain; footwear review
A24: Advanced / surgical options | B24: =IFERROR(INDEX('Master Matrix'!T$4:T$44,MATCH($B$4,'Master Matrix'!$G$4:$G$44,0)),"") -> If stalled beyond 12 weeks: ESWT has good support in plantar heel pain; corticosteroid injection gives short-term relief only and carries a fascia rupture and fat pad atrophy risk; surgery is rarely indicated
A25: Outcome measures | B25: =IFERROR(INDEX('Master Matrix'!U$4:U$44,MATCH($B$4,'Master Matrix'!$G$4:$G$44,0)),"") -> FAAM; FHSQ (Foot Health Status Questionnaire); FFI; first-step pain NRS
A26: Re-testable markers | B26: =IFERROR(INDEX('Master Matrix'!V$4:V$44,MATCH($B$4,'Master Matrix'!$G$4:$G$44,0)),"") -> FIRST-STEP PAIN NRS; standing and walking tolerance; ankle dorsiflexion (weight-bearing lunge in cm); heel raise repetitions
A27: Expected timeline | B27: =IFERROR(INDEX('Master Matrix'!W$4:W$44,MATCH($B$4,'Master Matrix'!$G$4:$G$44,0)),"") -> 6-12 months for full resolution; meaningful change by 12 weeks
A28: Referral / surgical trigger | B28: =IFERROR(INDEX('Master Matrix'!X$4:X$44,MATCH($B$4,'Master Matrix'!$G$4:$G$44,0)),"") -> No response after 12 months of correct management; suspected calcaneal stress fracture or nerve entrapment
A29: Evidence anchor | B29: =IFERROR(INDEX('Master Matrix'!Y$4:Y$44,MATCH($B$4,'Master Matrix'!$G$4:$G$44,0)),"") -> Rathleff high-load strength training RCT; Digiovanni plantar fascia-specific stretching; JOSPT heel pain CPG
A31: NOTES
A32: • Green text is pulled from the Master Matrix — edit the matrix, not this sheet.
A33: • Check RED FLAG STATUS first. A crimson entry means screen or refer before rehabilitating.
A34: • The DESIRED ACTIVITY GOAL and PHYSIOTHERAPY SPECIFIC EXERCISE rows are written to be handed straight to the patient.
A35: • The FOOTWEAR, ORTHOSES & ADJUNCTS row is often the most important line on the page — do not skip it.
A36: • Print this sheet (portrait, fit to one page wide) for the patient file.

Sheet Assessment Roadmap
A1: FIVE-GATE ASSESSMENT ROADMAP
A2: Work top to bottom. Gate 1 is the Ottawa Rules and the red flag list; Gate 4 — region, then tissue — does most of the diagnostic work.
A3: Gate | B3: Purpose | C3: What You Assess | D3: Findings That Matter | E3: Decision Rule
A4: GATE 1 | B4: Screen for serious and time-critical pathology | C4: Fracture; compartment syndrome; Achilles rupture; diabetic foot and Charcot; septic joint; high-risk bone stress | D4: APPLY THE OTTAWA ANKLE AND FOOT RULES to every acute injury. ESCALATING leg pain with pain on passive toe stretch = COMPARTMENT SYNDROME (normal pulses do NOT exclude it). Positive Thompson test = ACHILLES RUPTURE. A HOT SWOLLEN FOOT WITH INTACT SKIN in a neuropathic diabetic patient = CHARCOT until proven otherwise. Any ulcer in a diabetic foot = same-week multidisciplinary referral. Vague midfoot ache in a sprinting athlete = NAVICULAR STRESS FRACTURE until CT says otherwise | E4: Any positive -> image or refer BEFORE any local treatment
A5: GATE 2 | B5: Screen the lumbar spine and the vascular and neurological systems | C5: Lumbar screen; peripheral neuropathy; peripheral arterial disease | D5: Foot numbness, burning or unexplained weakness needs a LUMBAR SCREEN (dermatomal pattern, straight leg raise, myotomes - L5 great toe extension, S1 plantarflexion). In anyone over 50 or with diabetes, check MONOFILAMENT SENSATION and PEDAL PULSES. Bilateral stocking-distribution numbness suggests peripheral neuropathy, not a local foot problem | E5: The foot is frequently the messenger, not the message - clear the spine, the nerves and the circulation
A6: GATE 3 | B6: Traumatic or overuse? And is the athlete skeletally mature? | C6: Mechanism, timing, and skeletal maturity | D6: TRAUMATIC: inversion (lateral ligaments, fifth metatarsal, osteochondral lesion), eversion or external rotation (deltoid, syndesmosis - PALPATE THE PROXIMAL FIBULA), a pop at the back of the ankle (Achilles), forced hallux hyperextension (turf toe). OVERUSE: gradual onset with a load, footwear or surface change - tendinopathy, bone stress, nerve entrapment. SKELETALLY IMMATURE: the apophysis fails first (Sever's), and a rigid flatfoot with recurrent sprains means coalition | E6: A pop with functional loss is a surgical question, not a rehabilitation one
A7: GATE 4 | B7: Which region, and is it TENDON, LIGAMENT, BONE, NERVE or JOINT? | C7: Localise by region, then by tissue - the branch that does most of the diagnostic work | D7: LATERAL: ligament (sprain, instability), tendon (peroneal), bone (fifth metatarsal). MEDIAL: tendon (tibialis posterior, FHL), nerve (tarsal tunnel), bone (medial malleolus, navicular). ANTERIOR: syndesmosis, impingement, osteochondral lesion. POSTERIOR: Achilles (midportion versus insertional - the distinction changes the exercise), impingement, calf. PLANTAR/HEEL: fascia (first-step pain), bone (squeeze test), nerve (burning, night pain). FOREFOOT: neuroma (interspace), stress fracture (bone, dorsal swelling), plantar plate (drawer, toe drift), first MTP (rigidus, turf toe, sesamoid) | E7: Region plus tissue type gives the working diagnosis in most presentations
A8: GATE 5 | B8: Quantify range, capacity and control | C8: ANKLE DORSIFLEXION; single-leg heel raise; balance; foot posture; footwear | D8: WEIGHT-BEARING LUNGE TEST in cm (ankle dorsiflexion is a risk factor for almost every condition in this region and is the single most modifiable). SINGLE-LEG HEEL RAISE repetitions (target 25+) and quality (does the heel invert?). Single-leg balance time, eyes open and closed. Foot Posture Index. ALWAYS EXAMINE THE FOOTWEAR - wear pattern, age, heel counter, toe box width and sole stiffness | E8: These become the baseline re-testable markers. ANKLE DORSIFLEXION and SINGLE-LEG HEEL RAISE CAPACITY are the two highest-yield measures in the foot and ankle
A10: DIAGNOSTIC ALGORITHM — NARRATIVE FLOW
A11: • Foot or ankle pain → Ottawa Rules and red flags? (fracture, compartment syndrome, Achilles rupture, diabetic foot, high-risk bone stress) → YES: image or refer. NO ↓
A12: • Numbness, burning or unexplained weakness? → Screen the LUMBAR SPINE, and check MONOFILAMENT and PULSES. ↓
A13: • Traumatic or overuse? And is the athlete SKELETALLY MATURE? ↓
A14: • LATERAL → inversion mechanism = ligament. Behind the malleolus = peroneal. Snapping = subluxation. Fifth metatarsal base = fracture. Recurrent giving way = instability.
A15: • MEDIAL → cannot single-leg heel raise = tibialis posterior. Burning in the sole = tarsal tunnel. Behind the malleolus in a dancer = FHL. Bone tenderness = medial malleolar or navicular stress.
A16: • ANTERIOR → pain ABOVE the joint line = syndesmosis. Pinching at end-range dorsiflexion = impingement. Deep ache with swelling after a sprain = osteochondral lesion.
A17: • POSTERIOR → LOCATE THE ACHILLES PAIN (midportion versus insertional — it changes the exercise). Positive Thompson = rupture. Forced plantarflexion pain = posterior impingement.
A18: • PLANTAR/HEEL → first-step pain = fasciopathy. Every-step pain with a positive squeeze = calcaneal stress fracture. Burning at rest and at night = Baxter's nerve.
A19: • FOREFOOT → burning between the toes with a Mulder's click = neuroma. Focal bone tenderness with dorsal swelling = stress fracture. Toe drift with a positive drawer = plantar plate. First MTP = rigidus, turf toe or sesamoid.
A20: • Then quantify DORSIFLEXION, SINGLE-LEG HEEL RAISE, balance and foot posture, EXAMINE THE FOOTWEAR → set baseline markers → enter the Phased Programme.
A22: CLINICAL PEARL
... A24: • If those markers do not improve over 4-6 weeks of appropriate loading, RECONSIDER THE DIAGNOSIS. Bone stress, nerve entrapment and osteochondral lesions all mimic tendinopathy in this region.

Sheet Subjective Exam
A1: SUBJECTIVE EXAMINATION TEMPLATE
A2: Yellow column is the input column. In the foot, the history plus the footwear history makes most of the diagnosis.
A3: Domain | B3: What to Ask | C3: Why It Matters | D3: Findings (fill in)
A4: Demographics & context | B4: Age; occupation (standing, walking, surfaces); sport and level; weekly volume | C4: Occupational standing load is a major driver of heel and forefoot pain and is often not asked about | D4: e.g. 46 y, nurse, 10 h standing on hard floors, runs 25 km/week
A5: Onset & mechanism | B5: Traumatic (inversion, eversion, external rotation, a pop, forced hallux extension) or gradual overuse? | C5: Mechanism localises the tissue - inversion for lateral ligaments, external rotation for syndesmosis, a pop at the back for Achilles
A6: Pain location | B6: Point with one finger: lateral / medial / anterior / posterior / heel / forefoot | C6: The region is the first branch. Then ask whether it is on bone, along a tendon, at a joint line, or in a nerve distribution
A7: PAIN PATTERN | B7: FIRST STEPS of the morning? EVERY step? Warms up then worsens? Only during activity? At rest and at night? | C7: THE HIGHEST-YIELD QUESTION IN THE HEEL. First-step = fasciopathy. Every-step = bone stress. Warms up = tendinopathy. Rest and night = nerve or something sinister
A8: NERVE SYMPTOMS | B8: Numbness, burning or tingling - and exactly WHERE? Any weakness or foot drop? | C8: Burning and numbness point to nerve, not tendon. Distribution localises it. Weakness changes urgency
A9: Mechanical symptoms | B9: Giving way, locking, catching, clicking or snapping? | C9: Giving way = instability. Locking = osteochondral lesion or loose body. Snapping behind the malleolus = peroneal subluxation
A10: FOOTWEAR HISTORY | B10: What do you wear for work, sport and at home? Any recent change? How old are the running shoes? Do you go barefoot indoors? | C10: FREQUENTLY THE HIGHEST-YIELD MODIFIABLE FACTOR IN THE WHOLE REGION - and the one most often never asked about
A11: Load & training change | B11: Recent change in volume, surface, terrain, speed work, hills, or standing hours | C11: Most overuse foot and ankle pain is a load, surface or footwear change on an unprepared foot
A12: Prior injury | B12: Previous sprains (how many?), fractures, surgery, injections | C12: A PRIOR SPRAIN IS THE STRONGEST RISK FACTOR FOR ANOTHER. Repeated heel injections raise fascia rupture and fat pad atrophy risk
A13: DIABETES SCREEN | B13: Do you have diabetes? For how long? Any numbness? Do you check your feet? Any wound, however small? | C13: CHANGES EVERYTHING. Loss of protective sensation means painless injury. Any ulcer is a same-week referral
A14: Vascular screen | B14: Any calf pain on walking that eases with rest? Cold feet? Slow-healing wounds? Smoking history? | C14: Perfusion determines healing and is commonly under-recognised in older patients
A15: RED FLAG SCREEN | B15: Escalating leg pain with tightness? Fever or unwell? A pop with functional loss? Constant night pain unrelated to movement? A hot swollen foot? | C15: GATE 1 - compartment syndrome, sepsis, Achilles rupture, Charcot and malignancy all present here
A16: Skeletal maturity | B16: In anyone under 18: growth plates open? What sport and volume? One team or several? | C16: The apophysis fails before the tendon. A rigid flatfoot with recurrent sprains means coalition
... A20: Baseline outcome measure | B20: Which PROM will you use? (see Outcome Measures sheet) | C20: One PROM plus dorsiflexion and heel raise capacity is the minimum dataset
A22: HOW TO FILL THIS SHEET
A23: • Row 4 shows an example entry in grey — overwrite it.
A24: • Four questions triage most foot and ankle pain fast: "Point to it with one finger", "Is it worst with the FIRST steps or EVERY step?", "What shoes do you wear, and has anything changed?", and "Do you have diabetes?"
A25: • The PAIN PATTERN question does most of the work in the heel and is the single most efficient question in the region.
A26: • If nothing in the physical examination reproduces the presenting pain, stop and refer.

Sheet Objective Exam
A1: PHYSICAL EXAMINATION TEMPLATE
A2: Yellow columns are input columns. Weight-bearing lunge and single-leg heel raise are the two highest-yield measures — and always examine the shoes.
A3: Section | B3: Item | C3: How to Test / What to Look For | D3: Involved (fill in) | E3: Uninvolved (fill in) | F3: Interpretation
A4: Observation | B4: Foot posture in standing | C4: Foot Posture Index; cavovarus, neutral or pronated; arch height | D4: e.g. pronated, FPI +8 | E4: FPI +6 | F4: CAVOVARUS overloads the lateral column; PRONATED overloads the medial
A5: Observation | B5: Hindfoot alignment from behind | C5: Heel valgus or varus; TOO MANY TOES sign | F5: Too many toes = hindfoot valgus and arch collapse
A6: Observation | B6: Swelling and bruising | C6: Location and extent; effusion versus localised swelling | F6: Effusion = intra-articular; local dorsal swelling over a metatarsal = stress fracture
A7: Observation | B7: Toe alignment | C7: Hallux valgus; second toe drift or elevation; clawing | F7: Second toe drift = plantar plate failure
A8: Observation | B8: Skin, nails and callus | C8: Callus pattern (a map of load distribution); ulcers; nail changes | F8: Callus shows where load actually goes. ANY ulcer in a diabetic foot = urgent referral
A9: FOOTWEAR | B9: EXAMINE THE SHOES | C9: Wear pattern, age, toe box width, heel counter stiffness, sole stiffness, drop, cushioning | F9: FREQUENTLY THE HIGHEST-YIELD FINDING IN THE ENTIRE EXAMINATION
A10: Gait | B10: Walking observation | C10: Antalgia; foot slap; early heel rise; abductory twist; propulsion quality | F10: Foot slap = dorsiflexor weakness. Early heel rise = calf or ankle restriction
A11: Palpation | B11: Lateral: ATFL, CFL, peroneals, fifth metatarsal base, sinus tarsi | C11: Focal tenderness by structure | F11: Localises the lateral diagnosis
A12: Palpation | B12: Medial: tibialis posterior, deltoid, tarsal tunnel, navicular, medial malleolus | C12: Focal tenderness by structure | F12: N-SPOT tenderness in a sprinter = navicular stress fracture
A13: Palpation | B13: Posterior: Achilles midportion, insertion, retrocalcaneal space, calf belly | C13: LOCATE PRECISELY - midportion versus insertion | F13: THIS DISTINCTION CHANGES THE EXERCISE PRESCRIPTION ENTIRELY
A14: Palpation | B14: Plantar: medial calcaneal tubercle, central heel pad, Baxter's nerve course | C14: Focal tenderness by structure | F14: Medial tubercle = fasciopathy; centre of pad = fat pad; proximal-medial = Baxter's
A15: Palpation | B15: Forefoot: metatarsal shafts, intermetatarsal spaces, MTP joints, sesamoids | C15: Bone versus interspace versus joint | F15: Bone with dorsal swelling = stress fracture; interspace = neuroma; joint = plantar plate
A16: Range | B16: WEIGHT-BEARING LUNGE TEST (cm) | C16: Knee-to-wall distance, heel down, both sides | F16: THE most modifiable regional risk factor - measure it in every patient
... A36: Function | B36: Functional task performance | C36: Walking distance; stairs; single-leg hop; running; standing tolerance | F36: What the patient actually cares about - use as a re-test marker
A38: HOW TO FILL THIS SHEET
A39: • THE TWO MEASURES THAT MATTER MOST: WEIGHT-BEARING LUNGE (ankle dorsiflexion - the most modifiable regional risk factor) and SINGLE-LEG HEEL RAISE (calf endurance AND tibialis posterior function in one test).
A40: • LOCATE ACHILLES PAIN PRECISELY. Midportion (2-6 cm above) and insertional (at the bone) need OPPOSITE loading approaches. Getting this wrong is the commonest management error in the region.
A41: • EXAMINE THE FOOTWEAR. It is part of the physical examination, not an afterthought, and in forefoot and heel presentations it is frequently the most important finding.
A42: • Transfer dorsiflexion, heel raise, balance and strength figures into the Progress Tracker, which calculates symmetry and generates the readiness verdict automatically.
A43: • Row 4 shows an example entry in grey — overwrite it.

Sheet Special Tests
A1: SPECIAL TESTS
A2: No single test is definitive. The Ottawa Rules, the Thompson test and the monofilament are the exceptions — each is decision-changing on its own.
A3: Category | B3: Test | C3: Targets | D3: Positive Finding | E3: Clinical Note
A4: Screening | B4: OTTAWA ANKLE RULES | C4: Ankle fracture | D4: Malleolar tenderness at the posterior edge or tip, OR inability to weight bear four steps | E4: Highly sensitive - apply to EVERY acute ankle injury
A5: Screening | B5: OTTAWA FOOT RULES | C5: Midfoot fracture | D5: Fifth metatarsal base or navicular tenderness, OR inability to weight bear four steps | E5: The two named sites are both high-risk bone stress sites too
A6: Range | B6: WEIGHT-BEARING LUNGE TEST | C6: Ankle dorsiflexion | D6: Reduced knee-to-wall distance in cm compared with the other side | E6: THE single most modifiable risk factor across the whole region - measure it in every foot and ankle
A7: Range | B7: First MTP dorsiflexion | C7: Hallux rigidus; windlass function | D7: Under 65 degrees is reduced; under 30 degrees is significant | E7: Loss of the windlass alters push-off across the whole foot
A8: Capacity | B8: SINGLE-LEG HEEL RAISE | C8: Calf and tibialis posterior capacity | D8: Repetitions to fatigue (target 25+); note whether the HEEL INVERTS | E8: Two findings in one test: calf endurance AND tibialis posterior function
A9: Lateral ligament | B9: Anterior drawer test | C9: ATFL | D9: Increased anterior talar translation with a soft endpoint | E9: Perform at 10-15 degrees plantarflexion; far more accurate at 4-5 days than acutely
A10: Lateral ligament | B10: Talar tilt test | C10: CFL | D10: Increased inversion with a soft endpoint | E10: Compare with the other side
A11: Lateral ligament | B11: Anterolateral drawer test | C11: ATFL | D11: Anterolateral rotational translation | E11: More sensitive than the straight anterior drawer
A12: Syndesmosis | B12: SQUEEZE TEST | C12: Syndesmosis | D12: Pain at the syndesmosis on compressing the tibia and fibula proximally | E12: Part of the syndesmotic cluster
A13: Syndesmosis | B13: EXTERNAL ROTATION STRESS TEST | C13: Syndesmosis | D13: Pain above the joint line on external rotation of the dorsiflexed foot | E13: The most useful syndesmotic test
A14: Syndesmosis | B14: Tenderness length | C14: Syndesmotic severity | D14: Measure how far proximally tenderness extends | E14: Correlates with severity and predicts return-to-play time
... A33: Systemic | B33: 10 g MONOFILAMENT TESTING | C33: Protective sensation in the diabetic foot | D33: Inability to feel the monofilament at defined sites | E33: Loss of protective sensation defines the at-risk foot - test annually at minimum

Sheet Clusters & Classification
A1: DIAGNOSTIC CLUSTERS & CLASSIFICATION FRAMEWORKS
A2: Clustering beats any single test. Then match the label to a management pathway.
A3: Cluster | B3: Feature 1 | C3: Feature 2 | D3: Feature 3 | E3: Working Diagnosis
A4: CLUSTER 1 | B4: Inversion mechanism with immediate lateral swelling and difficulty weight-bearing | C4: ATFL and CFL tenderness with a positive anterior drawer at 4-5 days (not acutely) | D4: OTTAWA ANKLE RULES NEGATIVE, excluding fracture | E4: Lateral ankle sprain
A5: CLUSTER 2 | B5: Medial ankle and arch pain with progressive arch flattening | C5: INABILITY TO PERFORM A SINGLE-LEG HEEL RAISE, or absence of hindfoot inversion during the raise | D5: TOO MANY TOES sign from behind; tenderness along the tibialis posterior | E5: Tibialis posterior tendinopathy / Progressive Collapsing Foot Deformity
A6: CLUSTER 3 | B6: Pain ABOVE the ankle joint line after an external rotation injury | C6: Positive SQUEEZE TEST and EXTERNAL ROTATION STRESS TEST | D6: Tenderness length above the joint line correlates with severity; PALPATE THE PROXIMAL FIBULA | E6: Syndesmotic (high ankle) sprain
A7: CLUSTER 4 | B7: Posterior heel or tendon pain with MORNING STIFFNESS | C7: Focal tenderness 2-6 cm above the insertion (midportion) or AT the insertion (insertional) | D7: Pain WARMS UP with activity then worsens afterwards; Thompson test NEGATIVE | E7: Achilles tendinopathy (locate midportion versus insertional - it changes the exercise)
A8: CLUSTER 5 | B8: Plantar heel pain worst with the FIRST STEPS of the morning or after sitting | C8: Focal tenderness at the MEDIAL CALCANEAL TUBERCLE | D8: Reduced ankle dorsiflexion (the strongest modifiable risk factor); positive windlass test | E8: Plantar heel pain (plantar fasciopathy)
A9: CLUSTER 6 | B9: Forefoot burning and numbness with a 'pebble underfoot' sensation | C9: Tenderness in the INTERMETATARSAL SPACE with a positive Mulder's click | D9: Relieved by removing the shoe; symptoms in the adjacent toe web | E9: Morton's neuroma
A10: CLUSTER 7 | B10: Recurrent giving way on uneven ground after multiple sprains | C10: CAIT score under 24; deficits on single-leg balance and Star Excursion testing | D10: Delayed peroneal reaction and reduced dorsiflexion, with or without mechanical laxity | E10: Chronic ankle instability
A12: THE ONE-LINE DIFFERENTIATORS
A13: • Heel pain worst with the FIRST STEPS of the morning = plantar fasciopathy
A14: • Heel pain on EVERY step with a positive SQUEEZE TEST = calcaneal stress fracture
A15: • BURNING heel pain present at REST and at NIGHT = Baxter's nerve entrapment
A16: • Deep bruised ache in the CENTRE of the heel, better in cushioned shoes = fat pad syndrome
A17: • Achilles pain 2-6 cm above the heel = midportion (load off a step is fine)
A18: • Achilles pain AT the heel bone = insertional (NEVER load off a step or stretch - it compresses)
A19: • A pop at the back of the ankle with a POSITIVE THOMPSON TEST = Achilles rupture
A20: • Pain ABOVE the ankle joint line after external rotation = syndesmosis, not a lateral sprain
A21: • Inability to perform a SINGLE-LEG HEEL RAISE = tibialis posterior failure until proven otherwise
A22: • A vague dorsal MIDFOOT ache in a sprinter = navicular stress fracture until CT says otherwise
A23: • Burning between the toes with a Mulder's click = Morton's neuroma
... A27: • ESCALATING leg pain with pain on passive toe stretch = compartment syndrome - EMERGENCY
A29: Framework | B29: Category / Stage | C29: What It Means | D29: Management Implication
A30: Tendinopathy continuum (Cook & Purdam) | B30: Reactive / Dysrepair / Degenerative | C30: Stage determines how aggressively to load | D30: Reactive: isometrics and peak load reduction. Dysrepair/degenerative: heavy slow resistance to build capacity around the pathology
A31: Tendon load type | B31: TENSILE versus COMPRESSIVE | C31: Midportion Achilles and midportion tibialis posterior are TENSILE. Insertional Achilles, retrocalcaneal bursa and proximal hamstring are COMPRESSIVE | D31: THE SINGLE MOST IMPORTANT DISTINCTION IN ACHILLES MANAGEMENT: compressive presentations must be loaded in REDUCED DORSIFLEXION - no stretching, no eccentrics off a step
A32: Ottawa Ankle and Foot Rules | B32: Ankle series indicated | C32: Malleolar zone pain PLUS bony tenderness at the posterior edge or tip of either malleolus, OR inability to weight bear four steps | D32: Highly sensitive for excluding fracture - apply to every acute ankle injury
A33: Ottawa Ankle and Foot Rules | B33: Foot series indicated | C33: Midfoot zone pain PLUS bony tenderness at the fifth metatarsal base or navicular, OR inability to weight bear four steps | D33: The navicular and fifth metatarsal base are named for good reason - both are high-risk sites
A34: Bone stress injury risk | B34: HIGH RISK sites in the foot and ankle | C34: NAVICULAR, medial malleolus, proximal fifth metatarsal (Jones), sesamoid, base of the second metatarsal, anterior tibial cortex | D34: These need imaging and orthopaedic referral, not a rehabilitation trial. The symptom window is PAIN-FREE, not the tendon rule
A35: Bone stress injury risk | B35: LOW RISK sites | C35: Posteromedial tibia, calcaneus, metatarsal shafts 2-4, cuboid, cuneiforms | D35: Heal reliably with load removal and a graded return-to-run programme
A36: Progressive Collapsing Foot Deformity | B36: Stage 1 / 2 (FLEXIBLE) / 3 (RIGID) / 4 (ankle involvement) | C36: Flexible versus rigid determines everything | D36: Flexible: orthoses plus tibialis posterior loading works well. Rigid: orthoses for symptom control and surgical opinion
A37: Ankle instability | B37: MECHANICAL versus FUNCTIONAL | C37: Mechanical = ligamentous laxity on testing. Functional = proprioceptive, balance and neuromuscular deficit | D37: MOST CASES ARE PREDOMINANTLY FUNCTIONAL and respond to balance and neuromuscular training. Surgery addresses only the mechanical component
A38: Foot posture | B38: Cavovarus / Neutral / Pronated | C38: Foot posture predicts which structures are overloaded | D38: CAVOVARUS: lateral column overload - peroneal tendinopathy, fifth metatarsal stress, lateral ankle instability, sesamoid. PRONATED: medial overload - tibialis posterior, tarsal tunnel, plantar fascia, navicular
A39: Pain mechanism | B39: Nociceptive / Neuropathic / Nociplastic | C39: Load-related; nerve territory; disproportionate and spreading | D39: Nociceptive responds to load management; neuropathic needs the nerve source addressed; nociplastic needs education and graded exposure
A41: CLINICAL PEARL
A42: • THE TENSILE-VERSUS-COMPRESSIVE DISTINCTION is the most consequential framework on this sheet. Compressive tendon presentations - insertional Achilles, retrocalcaneal bursa - must be loaded in REDUCED DORSIFLEXION. No stretching, no eccentrics off a step. Applying a midportion protocol to insertional disease makes it worse.
A43: • BONE STRESS RISK STRATIFICATION changes the pathway entirely. Navicular, medial malleolus, proximal fifth metatarsal, sesamoid and second metatarsal base are HIGH RISK - image and refer. The symptom window for bone stress is PAIN-FREE, not the tendon rule.
A44: • MECHANICAL VERSUS FUNCTIONAL INSTABILITY: most chronic ankle instability is predominantly functional and responds to balance and neuromuscular training. Surgery addresses only the mechanical component.
A45: • FOOT POSTURE predicts which structures overload. Cavovarus feeds lateral column problems; pronated feeds medial ones. It tells you which orthotic posting to use.

Sheet Imaging Guide
A1: IMAGING GUIDE
A2: The Ottawa Rules exist to help you avoid imaging. But there are sites where imaging is mandatory and delay is costly.
A3: Modality | B3: When to Request | C3: What It Answers | D3: Interpretation Caution
A4: Clinical examination with the Ottawa Rules | B4: Every acute ankle and midfoot injury | C4: Whether a radiograph is needed at all | D4: Highly sensitive for excluding fracture - use it to AVOID unnecessary imaging, not to replace examination
A5: Weight-bearing radiographs | B5: Suspected fracture; alignment; arthritis; deformity assessment | C5: Fracture, joint space, alignment, osteophytes, accessory ossicles, syndesmotic clear space | D5: WEIGHT-BEARING views are essential for alignment and deformity - non-weight-bearing films mislead
A6: Specific radiographic views | B6: Axial sesamoid; oblique foot; lateral in maximal plantarflexion or dorsiflexion | C6: Sesamoid fracture; fifth metatarsal base and coalition; os trigonum and anterior osteophytes | D6: The right view matters - a standard series misses the os trigonum, the sesamoid and the coalition
A7: Ultrasound | B7: Tendinopathy and tears; bursal distension; neuroma; DYNAMIC assessment of subluxation | C7: Tendon change, tears, bursae, neuroma size, dynamic peroneal subluxation | D7: The investigation of choice for Morton's neuroma and for dynamic peroneal subluxation
A8: MRI | B8: Bone stress; osteochondral lesion stability; ligament and tendon integrity; plantar plate; soft-tissue mass | C8: Marrow oedema, lesion stability, tendon and ligament tears, plantar plate integrity | D8: The reference standard for early bone stress and for osteochondral lesion stability
A9: CT | B9: NAVICULAR stress fracture; fifth metatarsal union; tarsal coalition; fracture planning | C9: Cortical detail, fracture line, sclerosis, union, coalition anatomy | D9: SUPERIOR TO MRI for the navicular and for assessing union - and the investigation of choice for coalition
A10: Nerve conduction studies / EMG | B10: Tarsal tunnel; Baxter's nerve; suspected peripheral neuropathy; foot drop | C10: Localisation, severity and a baseline for tracking recovery | D10: Also distinguishes a local entrapment from a generalised peripheral neuropathy
A11: Vascular assessment (ABPI, Doppler) | B11: Any diabetic foot; suspected peripheral arterial disease; non-healing wound | C11: Perfusion adequacy for healing | D11: Perfusion determines healing potential - assess it before planning any wound or surgical management
A12: Aspiration | B12: Acute hot swollen joint | C12: Cell count, Gram stain, culture, crystals | D12: URGENT where sepsis is suspected - gout and sepsis present identically
A14: WHEN TO IMAGE
A15: • Ottawa Ankle or Foot Rules POSITIVE after an acute injury
A16: • A vague midfoot ache in a sprinting athlete — CT for the NAVICULAR (radiograph is unreliable, CT beats MRI)
A17: • Any suspected HIGH-RISK bone stress site: navicular, medial malleolus, proximal fifth metatarsal, sesamoid, second metatarsal base
A18: • Persistent deep ankle pain and swelling months after a sprain — MRI for an osteochondral lesion
A19: • A rigid flatfoot with recurrent sprains in an adolescent — CT for TARSAL COALITION
A20: • A hot swollen foot in a neuropathic patient — imaging for CHARCOT, but do not delay offloading while waiting
A21: • Failure to respond to appropriate loaded rehabilitation over 3 months
A23: IMAGING TRAPS
A24: • A HEEL SPUR IS NOT THE CAUSE OF PLANTAR HEEL PAIN. Spurs are common in asymptomatic feet and their presence changes nothing about management.
A25: • RADIOGRAPHS ARE UNRELIABLE FOR THE NAVICULAR and insensitive for the first 2-3 weeks of any bone stress injury. A normal film never excludes it.
A26: • CT IS SUPERIOR TO MRI for the navicular, for assessing union, and for tarsal coalition.
... A28: • WEIGHT-BEARING views are essential for alignment and deformity assessment. Non-weight-bearing films mislead.

Sheet Phased Programme
A1: PHASED MANAGEMENT PROGRAMME
A2: Progress by capacity, not calendar. Protected weight bearing beats immobilisation wherever it is safe.
A3: Phase | B3: Name | C3: Typical Timing | D3: Goal | E3: Content | F3: Markers Tracked | G3: Exit Criteria
A4: Phase 0 | B4: Screen & Protect | C4: 0 - as required | D4: Exclude fracture and emergencies; protect healing tissue; control swelling | E4: Ottawa Rules and red flag screen; PROTECTED WEIGHT BEARING rather than immobilisation wherever safe; compression and elevation; early pain-free range; isometric loading for analgesia; footwear and offloading decisions; education on the load-capacity model and realistic timelines | F4: Swelling; weight-bearing status; pain at rest; available range | G4: Fracture excluded; swelling controlled; weight bearing progressing; the patient understands the plan
A5: Phase 1 | B5: Restore Range & Activate | C5: Weeks 0-4 | D5: Restore ANKLE DORSIFLEXION, re-establish basic capacity, begin balance work | E5: ANKLE DORSIFLEXION mobility (weight-bearing lunge mobilisation, Mulligan mobilisation with movement); pain-free range in all planes; isometric calf, peroneal and tibialis posterior loading 5 x 30-45 s; INTRINSIC FOOT muscle activation; BALANCE TRAINING starting single-leg stance; gait normalisation | F5: Weight-bearing lunge distance; single-leg balance time; swelling; pain-free range | G5: Full or near-full dorsiflexion restored; loading into acceptable pain; single-leg stance achieved
A6: Phase 2 | B6: Build Capacity | C6: Weeks 4-12 | D6: Build calf, peroneal, tibialis posterior and intrinsic capacity, and progress balance | E6: HEAVY SLOW RESISTANCE calf raises (straight and bent knee) 3-4 sets 6-12 RM 3x/week; peroneal and tibialis posterior loading; intrinsic foot loading; PROGRESSIVE BALANCE AND NEUROMUSCULAR TRAINING on unstable surfaces with perturbation; proximal hip and trunk work | F6: SINGLE-LEG HEEL RAISE repetitions; balance progression; strength symmetry | G6: Single-leg heel raise repetitions approaching 25 and symmetrical; balance progressed to unstable surface; full range under load
A7: Phase 3 | B7: Energy Storage & Impact | C7: Weeks 8-20 | D7: Restore spring, landing and push-off capacity | E7: Progressive hopping, skipping and bounding; landing mechanics; double-leg to single-leg progression; RETURN-TO-RUN programme (walk-run intervals building to continuous); continued heavy calf loading 2x/week | F7: Hop test symmetry; landing quality; running volume tolerance | G7: Hop symmetry >=90%; landing controlled without collapse; running progression completed without symptom escalation
A8: Phase 4 | B8: Sport / Occupation-Specific & Discharge | C8: Weeks 12+ (6-9 months post major surgery) | D8: Replicate sport and occupational demands and prove readiness | E8: CHANGE OF DIRECTION and cutting progression; uneven terrain and sport-specific drills; occupational standing and walking simulation; EXTERNAL SUPPORT (brace or tape) for return to sport after ankle sprain; load monitoring throughout | F8: Full return-to-sport battery; CAIT; cutting and terrain tolerance | G8: Strength and hop symmetry >=90%; full dorsiflexion; balance restored; sport progression completed; external support in place
A10: MASTER TREATMENT ALGORITHM
A11: • SCREEN with the Ottawa Rules and the red flag list, and clear the spine, nerves and circulation
A12: • CONFIRM the diagnosis by region and tissue, and set re-testable markers (weight-bearing lunge, single-leg heel raise, balance, primary task pain)
A13: • EDUCATE: load-capacity model, realistic timelines (plantar heel pain and Achilles take 6-12 months), and footwear
A14: • CORE CARE (0-12 weeks): restore ANKLE DORSIFLEXION, progressive loading of the affected tissue, BALANCE AND NEUROMUSCULAR TRAINING where instability features, plus footwear and orthotic modification
A15: • REASSESS at 4-6 weeks against baseline markers. Improving -> progress toward impact and sport. Not improving -> audit adherence, dosage, diagnosis and the footwear and load exposure
A16: • STALLED (>12 weeks): reconsider the diagnosis (bone stress, nerve entrapment, osteochondral lesion all mimic tendinopathy); add ESWT while CONTINUING to load
A17: • REFRACTORY (6-12 months): surgical opinion for tendinopathy only after a genuinely well-delivered loading programme
A18: • TIME-CRITICAL EXCEPTIONS that bypass this sequence entirely: compartment syndrome, Achilles rupture, unstable syndesmosis, high-risk bone stress (navicular, medial malleolus, Jones, sesamoid), any diabetic foot ulcer or suspected Charcot, and septic arthritis
A20: PRINCIPLES OF LOAD MANAGEMENT
A21: • PROTECTED WEIGHT BEARING beats immobilisation wherever it is safe - the foot deconditions and stiffens quickly.
A22: • MATCH INTENSITY TO IRRITABILITY. Reactive tendons need isometrics and peak load reduction; settled tendons need heavy slow resistance.
... A27: • SET THE TIMELINE ON DAY ONE. Plantar heel pain and Achilles tendinopathy have favourable but slow natural histories over 6-12 months.

Sheet Exercise & Dosage
A1: EXERCISE PRESCRIPTION & DOSAGE LIBRARY
A2: Match the diagnosis to a loading strategy and a stage. Note where OFFLOADING, not loading, is the intervention.
A3: Loading Category | B3: Purpose | C3: Example Exercises | D3: Dosage | E3: Best Suited To
A4: Isometric | B4: Analgesia; irritable or reactive stage; early activation | C4: Isometric calf holds, peroneal and tibialis posterior holds, intrinsic short-foot holds | D4: 5 x 30-45 s holds, 1-2x/day | E4: Reactive Achilles and tibialis posterior tendinopathy; acute post-injury
A5: Heavy slow resistance (calf) | B5: Build calf and Achilles capacity - the core Achilles intervention | C5: Bilateral to single-leg heel raises, straight AND bent knee (gastrocnemius and soleus), on the floor or off a step depending on the diagnosis | D5: 3-4 sets, 6-12 RM, 3 s up / 3 s down, 3x/week | E5: Midportion Achilles tendinopathy (off a step is fine). INSERTIONAL: ON THE FLOOR ONLY, in reduced dorsiflexion
A6: High-load strength (plantar fascia) | B6: Build plantar fascia and intrinsic capacity | C6: Single-leg heel raise with a TOWEL UNDER THE TOES to engage the windlass, progressive load | D6: 3-4 sets, 8-12 RM, every other day (Rathleff protocol) | E6: Plantar heel pain
A7: Tibialis posterior loading | B7: Restore the primary dynamic arch support | C7: Banded foot ADDUCTION (not just inversion), progressing to weighted; heel raises with hindfoot inversion cueing | D7: 3-4 sets, 8-12 RM, 3x/week | E7: Tibialis posterior tendinopathy and Progressive Collapsing Foot Deformity
A8: Peroneal loading | B8: Lateral dynamic stability | C8: Banded eversion; single-leg heel raise in slight eversion; lateral hop control | D8: 3-4 sets, 8-12 RM, 3x/week | E8: Peroneal tendinopathy; lateral ankle instability; cavovarus foot
A9: Intrinsic foot loading | B9: Support the arch dynamically and improve forefoot control | C9: Short foot exercise, toe splay, toe yoga, doming, towel scrunch progressing to resisted | D9: 3 sets, 10-15 reps, daily to 3x/week | E9: Plantar heel pain, PCFD, plantar plate, hallux valgus, general foot capacity
A10: BALANCE & NEUROMUSCULAR | B10: THE key intervention in ankle instability and its prevention | C10: Single-leg stance progressing to unstable surface, eyes closed, dynamic perturbation, hop-and-hold, sport-specific | D10: 10-20 min daily for 4-6 weeks minimum | E10: Acute ankle sprain, chronic ankle instability, sinus tarsi - and as PREVENTION in all court and field sport
A11: Ankle dorsiflexion mobility | B11: Restore the single most modifiable risk factor in the region | C11: Weight-bearing lunge mobilisation, Mulligan mobilisation with movement, calf loading through range | D11: 3-5 sets, 30 s, daily | E11: Almost every foot and ankle condition - a near-universal contributor
A12: Energy storage / plyometric | B12: Restore spring, landing and push-off capacity | C12: Pogo hops, skipping, bounding, single-leg hops, drop landings, lateral hops | D12: 2-3x/week with 48 h between sessions | E12: Achilles tendinopathy stage 3; return to running and court sport
A13: Return-to-run programme | B13: Graded reintroduction of impact | C13: Walk-run intervals building to continuous running, then speed, then hills LAST | D13: Alternate days; progress only if pain-free during and for 24 h after | E13: All bone stress injuries and lower-limb conditions returning to running
A14: Offloading (not loading) | B14: Where the tissue cannot tolerate load at all | C14: Total contact casting, boot, sesamoid cut-out, metatarsal dome, heel cup, toe taping | D14: Continuous during the protection phase | E14: Diabetic ulceration, sesamoid stress fracture, plantar plate, fat pad atrophy, navicular stress fracture
A15: Proximal chain | B15: Reduce the load reaching the foot and control frontal-plane collapse | C15: Hip abductor and external rotator loading; single-leg squat and landing control; trunk work | D15: 3-4 sets, 8-12 RM, 3x/week | E15: Ankle instability, PCFD, plantar heel pain, running-related conditions
A17: THE GENERIC LOADING PROGRESSION
A18: • Stage 1 — Isometric loading for pain and early activation; restore ankle dorsiflexion.
A19: • Stage 2 — Heavy slow resistance for the affected tissue, plus intrinsic and balance work.
A20: • Stage 3 — Energy storage, hopping and the return-to-run programme.
A21: • Stage 4 — Sport or occupation-specific loading with external support in place.
A22: • ANKLE DORSIFLEXION MOBILITY and BALANCE TRAINING run through all four stages - they are near-universal contributors.
A23: • NOTE THE OFFLOADING ROW. In diabetic ulceration, sesamoid stress fracture, navicular stress fracture and plantar plate injury, the intervention is taking load OFF, not putting load on.

Sheet Adjuncts & Advanced
A1: FOOTWEAR, ORTHOSES, ADJUNCTS & REFERRAL OPTIONS
A2: In the foot and ankle, adjuncts are not peripheral — footwear and offloading are frequently the primary intervention.
A3: Tier | B3: Intervention | C3: Role | D3: Evidence Position | E3: Practical Note
A4: Adjunct | B4: Education & load management | C4: Foundational for all overuse presentations | D4: A high-value intervention in its own right | E4: Set the timeline honestly - plantar heel pain and Achilles tendinopathy take 6-12 months
A5: Adjunct | B5: FOOTWEAR ASSESSMENT AND MODIFICATION | C5: Often the highest-yield single change in the foot | D5: Central to forefoot, heel and Achilles presentations | E5: ALWAYS EXAMINE THE SHOES. Toe box width, heel counter stiffness, sole stiffness, heel-to-toe drop, cushioning and age
A6: Adjunct | B6: Prefabricated orthoses | C6: Pronation control; arch support; medial or lateral posting | D6: Equivalent to custom devices in most trials for most conditions | E6: Try prefabricated first; reserve custom for complex deformity, diabetic feet and failures
A7: Adjunct | B7: Metatarsal dome / pad | C7: Forefoot offloading | D7: Effective for neuroma, metatarsalgia and plantar plate | E7: PLACEMENT MATTERS - proximal to the metatarsal heads, not under them
A8: Adjunct | B8: Heel lift | C8: Reduce dorsiflexion demand and Achilles insertional compression | D8: Practical short-term relief | E8: Particularly useful in insertional Achilles tendinopathy and retrocalcaneal bursitis
A9: Adjunct | B9: Taping (low-Dye, calcaneal, toe) | C9: Short-term symptom relief and a test of the mechanical hypothesis | D9: Good short-term effect in plantar heel pain and plantar plate injury | E9: If taping helps, an orthosis probably will too - use it diagnostically
A10: Adjunct | B10: EXTERNAL ANKLE SUPPORT (brace or tape) | C10: Re-injury prevention after ankle sprain | D10: One of the BEST-EVIDENCED interventions in the region for preventing recurrence | E10: Use for 6-12 months on return to sport after a lateral ankle sprain
A11: Adjunct | B11: Stiff-soled shoe / carbon plate / rocker sole | C11: Reduce first MTP and forefoot loading demand | D11: Highly effective in hallux rigidus, turf toe, sesamoid and metatarsal stress | E11: Reduces the range and load the joint cannot supply - often more effective than any exercise
A12: Adjunct | B12: Night splints | C12: Persistent morning pain in plantar heel pain | D12: Modest benefit; tolerance is the limiting factor | E12: Worth a trial where morning pain dominates
A13: Adjunct | B13: Walking boot | C13: Protection for bone stress, acute rupture and severe sprain | D13: Protection without full immobilisation where possible | E13: Use for the shortest safe period - stiffness and deconditioning follow
A14: Advanced | B14: ESWT | C14: Plantar heel pain; Achilles tendinopathy (midportion and insertional) | D14: Good support in plantar heel pain and reasonable in Achilles when loading alone stalls | E14: Typically 3-5 weekly sessions; CONTINUE loading throughout
... A20: Referral | B20: Multidisciplinary diabetic foot team | C20: ANY ulcer, suspected Charcot, infection or ischaemia | D20: Same-week referral is the standard | E20: Delay costs limbs - this is the highest-consequence referral pathway in the region
A22: SEQUENCING NOTE
A23: • FOOTWEAR ASSESSMENT IS PART OF THE EXAMINATION, not an adjunct to be added later. In forefoot and heel presentations a shoe change frequently outperforms any exercise.
A24: • EXTERNAL ANKLE SUPPORT for 6-12 months after a lateral ankle sprain is one of the best-evidenced re-injury prevention measures available - prescribe it routinely, not selectively.
A25: • CORTICOSTEROID INJECTION IN THE HEEL carries real risk: plantar fascia rupture and fat pad atrophy. Use sparingly and counsel explicitly. NEVER inject the Achilles or tibialis posterior tendon.
A26: • THE DIABETIC FOOT PATHWAY IS THE HIGHEST-CONSEQUENCE REFERRAL IN THE REGION. Any ulcer, suspected Charcot, infection or ischaemia is a same-week multidisciplinary referral. Delay costs limbs.
A27: • Optimise loading, footwear and education for 8-12 weeks first; if stalled, RECONSIDER THE DIAGNOSIS before adding modalities.

Sheet Post-Surgical Guide
A1: FOOT & ANKLE SURGERY — PROTECTION & RETURN-TO-SPORT GUIDE
A2: 33 procedures across 9 categories. ALWAYS follow the operating surgeon's protocol. Note the procedures carrying PERMANENT restrictions — these must be discussed before surgery.
A3: # | B3: Procedure Category | C3: Procedure | D3: Indication | E3: MOVEMENTS TO AVOID | F3: Protection (period) | G3: Range Progression | H3: Loading From | I3: Return to Sport
A4: 1 | B4: Ligament & Instability | C4: Brostrom-Gould Lateral Ligament Repair | D4: Chronic mechanical lateral ankle instability | E4: Inversion; supination; uneven terrain | F4: 2-6 weeks (boot) | G4: Protected 0-2 weeks | H4: 6-8 weeks | I4: 4-6 months
A5: 1 | B5: Ligament & Instability | C5: Lateral Ligament Reconstruction (graft) | D5: Failed repair; poor tissue; high-demand athlete | E5: Inversion; supination; pivoting | F5: 6 weeks (boot) | G5: Protected 0-6 weeks | H5: 12 weeks | I5: 6-9 months
A6: 1 | B6: Ligament & Instability | C6: Syndesmotic Fixation (suture button or screw) | D6: Unstable syndesmotic injury | E6: External rotation; weight-bearing dorsiflexion; cutting | F6: 6 weeks | G6: Protected 0-6 weeks | H6: 12 weeks | I6: 3-6 months
A7: 1 | B7: Ligament & Instability | C7: Peroneal Retinaculum Repair with Groove Deepening | D7: Recurrent peroneal tendon subluxation | E7: Dorsiflexion with eversion; resisted eversion | F7: 4-6 weeks | G7: Protected 0-4 weeks | H7: 8-12 weeks | I7: 4-6 months
A8: 2 | B8: Tendon Procedures | C8: Achilles Tendon Repair (open or percutaneous) | D8: Achilles rupture in selected patients | E8: Dorsiflexion beyond neutral early; push-off; sudden loading | F8: 6-8 weeks (boot with wedges) | G8: Protocol-driven from week 2 | H8: 12 weeks | I8: 6-9 months
A9: 2 | B9: Tendon Procedures | C9: Achilles Debridement / Gastrocnemius Recession | D9: Refractory midportion Achilles tendinopathy | E9: Push-off; heavy calf loading | F9: 2-6 weeks | G9: Early gentle range | H9: 12 weeks | I9: 4-6 months
A10: 2 | B10: Tendon Procedures | C10: Insertional Achilles Debridement with Haglund Resection | D10: Refractory insertional Achilles tendinopathy | E10: Dorsiflexion; push-off; heel counter pressure | F10: 6 weeks (boot) | G10: Protected 0-6 weeks | H10: 12-16 weeks | I10: 6-9 months
A11: 2 | B11: Tendon Procedures | C11: FDL Transfer with Medialising Calcaneal Osteotomy | D11: Flexible Progressive Collapsing Foot Deformity | E11: Weight bearing until union; resisted inversion | F11: 6-8 weeks (NWB then protected) | G11: Protected 0-6 weeks | H11: 16 weeks | I11: 6-12 months
A12: 2 | B12: Tendon Procedures | C12: FHL Tenolysis (often with os trigonum excision) | D12: Refractory dancer's tendinitis | E12: Resisted hallux flexion; extreme plantarflexion early | F12: 1-2 weeks | G12: Early range | H12: 6-8 weeks | I12: 3-4 months
A13: 2 | B13: Tendon Procedures | C13: Tibialis Anterior Repair | D13: Tibialis anterior rupture | E13: Plantarflexion beyond neutral; resisted dorsiflexion | F13: 4-6 weeks (slight dorsiflexion) | G13: Protected 0-4 weeks | H13: 12 weeks | I13: 3-4 months
A14: 3 | B14: Cartilage & Joint | C14: Arthroscopic Microfracture (talar dome) | D14: Small osteochondral lesion of the talus | E14: Impact; weight bearing per surgeon | F14: 4-6 weeks | G14: Early range, protected weight bearing | H14: 12 weeks | I14: 6-9 months
A15: 3 | B15: Cartilage & Joint | C15: Osteochondral Autograft / Allograft (talus) | D15: Large or failed osteochondral lesion | E15: Impact; weight bearing | F15: 6-8 weeks | G15: Protected 0-6 weeks | H15: 16 weeks | I15: 9-12 months
... A36: 9 | B36: Diabetic & Limb Salvage | C36: Charcot Reconstruction | D36: Unstable Charcot deformity | E36: Weight bearing until union; PERMANENT bespoke footwear | F36: 12+ weeks | G36: Per surgeon | H36: 16-24 weeks | I36: Protected walking only
A38: Restriction | B38: What It Means | C38: Applies To
A39: INVERSION AND SUPINATION | B39: Avoid inversion, supination and uneven terrain - it loads the lateral repair directly | C39: Brostrom-Gould repair, lateral ligament reconstruction
A40: EXTERNAL ROTATION AND WEIGHT-BEARING DORSIFLEXION | B40: Avoid external rotation and loaded dorsiflexion, which splay the mortise | C40: Syndesmotic fixation
A41: DORSIFLEXION BEYOND NEUTRAL | B41: Avoid stretching the repair; heel wedges are removed progressively, not all at once | C41: Achilles repair, insertional Achilles debridement
A42: IMPACT AND WEIGHT BEARING | B42: No axial impact through the healing cartilage or bone | C42: Talar dome cartilage procedures, navicular and medial malleolar fixation, Jones fixation
A43: FOREFOOT WEIGHT BEARING | B43: Offload the forefoot - a post-operative shoe transfers load to the heel | C43: Hallux valgus correction, plantar plate repair, sesamoidectomy, Weil osteotomy
A44: RESISTED INVERSION | B44: Avoid loading the tibialis posterior at its insertion | C44: FDL transfer with calcaneal osteotomy, Kidner procedure
A45: NO RESTRICTION - EARLY MOTION IS THE PRIORITY | B45: The risk is stiffness and re-adhesion; early range work IS the treatment | C45: Anterior ankle debridement, cheilectomy, os trigonum excision, tarsal coalition resection
A46: PERMANENT RESTRICTION | B46: A lasting limitation the patient must be counselled about BEFORE surgery | C46: Ankle arthrodesis (no ankle motion), first MTP arthrodesis (no toe motion), total ankle arthroplasty (no impact), neuroma excision (permanent numbness), Charcot reconstruction (bespoke footwear for life)
A48: GENERAL REHABILITATION PRINCIPLES
A49: • PROTECTED WEIGHT BEARING beats immobilisation wherever it is safe - the foot and ankle deconditions and stiffens quickly
A50: • RESTORE ANKLE DORSIFLEXION - it is the single most modifiable factor across the whole region
A51: • Control swelling early; persistent effusion inhibits muscle and delays everything downstream
A52: • Rebuild SINGLE-LEG HEEL RAISE capacity - it is the functional benchmark for the whole foot and ankle
A53: • BALANCE AND NEUROMUSCULAR TRAINING is not optional after any ankle injury - it is what prevents recurrence
A54: • ALWAYS ADDRESS FOOTWEAR - it is frequently the highest-yield single change and is often never examined
A55: • Return to sport on criteria - strength and hop symmetry, full dorsiflexion, restored balance - with external support in place
A57: IMPORTANT
A58: • Timelines are general guidelines and vary with tissue quality, fixation, patient factors and surgeon preference
A59: • ALWAYS follow the specific post-operative protocol provided by the operating surgeon - it overrides everything here
A60: • SEVERAL PROCEDURES CARRY PERMANENT RESTRICTIONS that must be discussed BEFORE surgery, not discovered after it - arthrodesis eliminates motion, neuroma excision leaves permanent numbness, and total ankle arthroplasty precludes impact
... A62: • Diabetic foot surgery sits within multidisciplinary team management, not standalone orthopaedic care

Sheet Sport Profiles
A1: SPORTING FOOT & ANKLE — DEMANDS & INJURY RISK COMPARISON
A2: Twenty sports and populations: what the foot is asked to do, what breaks, and what to manage on the way back.
A3: Sport / Population | B3: Primary Foot & Ankle Demands | C3: Common Injury Risks | D3: RETURN & LOAD CONSIDERATIONS
A4: Distance Running | B4: Repetitive impact absorption and push-off; high cumulative load | C4: Achilles tendinopathy, plantar heel pain, tibial and metatarsal bone stress, tibialis posterior tendinopathy | D4: Volume and surface change are the usual load errors. Progress 10-15% weekly with an ACWR of 0.8-1.3; increase step rate to reduce loading rate; rotate footwear and surfaces; screen energy availability in any bone stress presentation
A5: Sprinting & Track Athletics | B5: Explosive push-off through the forefoot; extreme plantarflexion loading | C5: NAVICULAR stress fracture, sesamoid injury, Achilles tendinopathy, turf toe | D5: Any vague midfoot ache warrants CT, not a rehabilitation trial. Cap spike-shod volume; progress plyometrics in a ladder; log sprint volume
A6: Football / Soccer | B6: Cutting, kicking and impact on variable surfaces | C6: Lateral ankle sprain, SYNDESMOTIC sprain, anterior ankle impingement, fifth metatarsal fracture, turf toe | D6: Pain ABOVE the joint line means syndesmosis and roughly double the recovery time. Use external ankle support for 6-12 months after a sprain; balance training is the best-evidenced prevention
A7: Basketball & Volleyball | B7: High jump and landing volume; repeated cutting | C7: Lateral ankle sprain, chronic instability, Achilles tendinopathy, osteochondral lesion of the talus | D7: The highest ankle sprain incidence of any sport. External support plus a balance programme is the evidence-based prevention package; count jumps as the load metric
A8: Classical Ballet & Dance | B8: Extreme plantarflexion (en pointe) and forefoot loading | C8: FHL tenosynovitis, posterior ankle impingement and os trigonum, sesamoid injury, SECOND METATARSAL BASE stress fracture | D8: Pointe readiness by criteria not age; cap pointe minutes; screen energy availability routinely; posterior ankle pain plus hallux triggering means FHL and impingement together
A9: Gymnastics | B9: High-impact landing and extreme range demands | C9: Osteochondral lesion of the talus, Sever's disease, ankle sprain, calcaneal apophysitis | D9: Landing volume is the load metric; screen skeletally immature athletes for apophysitis; build calf and landing capacity before increasing skill volume
A10: Tennis & Racquet Sports | B10: Rapid multidirectional loading, deceleration and lateral cutting | C10: Lateral ankle sprain, Achilles tendinopathy, plantar heel pain, peroneal tendinopathy | D10: Court surface changes the load profile markedly; review shoe outsole for the surface; balance training and external support for recurrent sprains
A11: Cricket | B11: Fast bowling front-foot impact; repeated running between wickets | C11: Bone stress (tibia, navicular, metatarsal), plantar heel pain, ankle impingement | D11: Front-foot impact loads are very high in fast bowlers - apply age-appropriate over limits; screen for bone stress in any persistent foot pain
A12: Rugby / American Football | B12: Collision, cutting and scrummaging on variable surfaces | C12: SYNDESMOTIC sprain, lateral ankle sprain, turf toe, fifth metatarsal fracture | D12: TURF TOE is a hard-surface plus flexible-shoe problem - review shoe stiffness for the playing surface; syndesmotic injuries need honest timeline expectations
A13: Trail & Ultra Running | B13: Prolonged loading on uneven terrain | C13: Lateral ankle sprain, peroneal tendinopathy, metatarsal stress fracture, plantar heel pain | D13: Terrain exposure must be graded like volume; balance and peroneal capacity are protective; check for a cavovarus foot in recurrent lateral problems
A14: Military & Occupational Marching | B14: High-volume load carriage on hard surfaces | C14: Calcaneal and metatarsal stress fracture, plantar heel pain, tibialis posterior tendinopathy | D14: Graded entry programmes and boot fit are the interventions; screen for bone stress early in recruits with persistent foot pain
... A23: Older Adults & General Population | B23: Walking, standing and stair loading; falls risk | C23: Plantar heel pain, tibialis posterior tendinopathy, hallux rigidus and valgus, fat pad atrophy, diabetic foot | D23: FOOTWEAR AND FALLS PREVENTION are the priorities; screen every diabetic foot with a monofilament; balance and calf capacity reduce falls risk
A25: CROSS-CUTTING THEMES
A26: • COURT AND FIELD SPORT: the highest ankle sprain burden. Balance training plus external ankle support is the evidence-based prevention package - use both, routinely.
A27: • RUNNING AND ENDURANCE SPORT: bone stress and tendinopathy dominate. Volume, surface and footwear change are the usual errors; screen energy availability in every bone stress presentation.
A28: • SPRINT, JUMP AND DANCE: the HIGH-RISK bone stress sites cluster here - navicular, sesamoid, second metatarsal base. Any vague midfoot ache needs CT, not a rehabilitation trial.
A29: • HARD SURFACES AND FLEXIBLE SHOES: the turf toe combination. Review shoe stiffness against the playing surface.
A30: • OLDER ADULTS AND OCCUPATIONAL STANDING: footwear, falls prevention and diabetic foot screening are the priorities, and they matter more than any exercise prescription.

Sheet Return to Sport
A1: RETURN-TO-SPORT & WORK CRITERIA
A2: Discharge on capacity and control, not comfort. Dorsiflexion, heel raise capacity and balance are the anchors.
A3: Criterion | B3: Target | C3: How to Measure
A4: Pain and swelling | B4: No pain at rest or with daily walking; no persistent effusion after loading | C4: NRS; swelling comparison; figure-of-eight measurement
A5: ANKLE DORSIFLEXION | B5: Symmetrical weight-bearing lunge test distance | C5: Knee-to-wall distance in cm, both sides
A6: SINGLE-LEG HEEL RAISE | B6: >=25 repetitions and symmetrical with the other side; heel inverts during the raise | C6: Standardised cadence, to fatigue, both sides
A7: Strength symmetry | B7: >=90% for plantarflexion, dorsiflexion, inversion and eversion | C7: Handheld dynamometry or standardised loading
A8: Balance and postural control | B8: Symmetrical single-leg balance (eyes open and closed) and Star Excursion reach | C8: Timed balance; Star Excursion Balance Test
A9: Hop test battery | B9: >=90% symmetry on single, triple, crossover and side hop | C9: Best of three per limb
A10: Landing and cutting quality | B10: Controlled landing without collapse; confident change of direction | C10: Observation, video where available
A11: Sport or terrain-specific progression | B11: Running, cutting, uneven terrain and sport drills completed at full intensity | C11: Documented staged progression without symptom escalation
A12: Perceived stability and confidence | B12: CAIT score restored; no sense of giving way | C12: CAIT; patient-reported confidence
A13: EXTERNAL SUPPORT IN PLACE | B13: Brace or tape organised for 6-12 months after a lateral ankle sprain | C13: One of the best-evidenced re-injury prevention measures
A15: CLINICAL PEARL
A16: • An athlete who feels better but still has a 4 cm dorsiflexion deficit and reduced single-leg balance is primed to sprain the ankle again.
A17: • BALANCE AND EXTERNAL SUPPORT ARE THE TWO PREVENTION LEVERS after an ankle sprain - neither is optional, and both are frequently omitted.
A18: • For standing workers, ENDURANCE matters more than peak strength - test heel raise repetitions to fatigue, not maximum force.
A19: • Use the Progress Tracker to calculate symmetry and generate an automatic pass/fail against these criteria.
A20: • Cross-reference the Sport Profiles sheet for what the athlete's specific sport will ask of the foot on return.

Sheet Progress Tracker
A1: PROGRESS TRACKER & READINESS CALCULATOR
A2: Enter values in the yellow cells only. Dorsiflexion deficit, heel raise symmetry, balance and strength symmetry calculate automatically.
A4: PATIENT & CASE DETAILS
A5: Patient ID / initials | B5: e.g. PR-063 | F5: Desired activity goal for this condition:
A6: Condition (as listed in Master Matrix) | B6: Plantar Heel Pain (Plantar Fasciopathy) | F6: =IFERROR(INDEX('Master Matrix'!K$4:K$44,MATCH($B$6,'Master Matrix'!$G$4:$G$44,0)),"Enter a condition exactly as listed in the Master Matrix") -> Take the first steps of the morning and stand through a working day without heel pain
A7: Involved side | B7: Right
A8: Assessment date
A10: RANGE OF MOTION — target: symmetrical
A11: Measure | B11: Involved | C11: Uninvolved | D11: Unit | E11: Deficit | F11: Status | G11: Note
A12: WEIGHT-BEARING LUNGE (dorsiflexion) | B12: 6 | C12: 11 | D12: cm | E12: =IF(OR(B12="",C12=""),"",ABS(C12-B12)) -> 5 | F12: =IF(E12="","",IF(E12<=1,"SYMMETRICAL",IF(E12<=3,"MILD DEFICIT","RESTRICTED"))) -> RESTRICTED | G12: THE most modifiable risk factor in the whole region — heel down, knee to wall, measure in cm
A13: Ankle plantarflexion | D13: deg | E13: =IF(OR(B13="",C13=""),"",ABS(C13-B13)) | F13: =IF(E13="","",IF(E13<=1,"SYMMETRICAL",IF(E13<=3,"MILD DEFICIT","RESTRICTED"))) | G13: Status thresholds here are in cm for the lunge test; interpret the degree-based rows against normal values
A14: Subtalar inversion/eversion | D14: deg | E14: =IF(OR(B14="",C14=""),"",ABS(C14-B14)) | F14: =IF(E14="","",IF(E14<=1,"SYMMETRICAL",IF(E14<=3,"MILD DEFICIT","RESTRICTED")))
A15: First MTP dorsiflexion | D15: deg | E15: =IF(OR(B15="",C15=""),"",ABS(C15-B15)) | F15: =IF(E15="","",IF(E15<=1,"SYMMETRICAL",IF(E15<=3,"MILD DEFICIT","RESTRICTED")))
A17: SINGLE-LEG HEEL RAISE — THE FUNCTIONAL BENCHMARK
A18: Measure | B18: Involved | C18: Uninvolved | D18: Unit | E18: LSI | F18: Status | G18: Note
A19: SINGLE-LEG HEEL RAISE (repetitions) | B19: 12 | C19: 26 | D19: reps | E19: =IF(N(C19)=0,"",B19/C19) -> 0.46153846 | F19: =IF(E19="","",IF(AND(E19>=0.9,B19>=25),"PASS","NOT YET")) -> NOT YET | G19: Requires BOTH >=90% symmetry AND >=25 repetitions to pass
A20: Does the heel INVERT during the raise? | B20: YES | D20: NO inversion = tibialis posterior dysfunction, even if the repetition count looks acceptable
A22: BALANCE & NEUROMUSCULAR CONTROL
A23: Measure | B23: Involved | C23: Uninvolved | D23: Unit | E23: LSI | F23: Status | G23: Note
A24: Single-leg balance (eyes open) | B24: 22 | C24: 30 | D24: sec | E24: =IF(N(C24)=0,"",B24/C24) -> 0.73333333 | F24: =IF(E24="","",IF(E24>=0.9,"PASS","NOT YET")) -> NOT YET
A25: Single-leg balance (eyes CLOSED) | D25: sec | E25: =IF(N(C25)=0,"",B25/C25) | F25: =IF(E25="","",IF(E25>=0.9,"PASS","NOT YET")) | G25: Eyes-closed balance is the more sensitive marker in chronic ankle instability
A26: Star Excursion — anterior reach | D26: cm | E26: =IF(N(C26)=0,"",B26/C26) | F26: =IF(E26="","",IF(E26>=0.9,"PASS","NOT YET"))
A28: STRENGTH — LIMB SYMMETRY INDEX
A29: Measure | B29: Involved | C29: Uninvolved | D29: Unit | E29: LSI | F29: Status | G29: Note
A30: Plantarflexion | B30: 18 | C30: 24 | D30: kg | E30: =IF(N(C30)=0,"",B30/C30) -> 0.75 | F30: =IF(E30="","",IF(E30>=$B$45,"PASS","NOT YET")) -> NOT YET
A31: Dorsiflexion | D31: kg | E31: =IF(N(C31)=0,"",B31/C31) | F31: =IF(E31="","",IF(E31>=$B$45,"PASS","NOT YET"))
A32: Inversion | D32: kg | E32: =IF(N(C32)=0,"",B32/C32) | F32: =IF(E32="","",IF(E32>=$B$45,"PASS","NOT YET"))
A33: Eversion | D33: kg | E33: =IF(N(C33)=0,"",B33/C33) | F33: =IF(E33="","",IF(E33>=$B$45,"PASS","NOT YET"))
A35: RE-TESTABLE MARKERS — BASELINE vs CURRENT
A36: Marker | B36: Baseline | C36: Current | D36: Unit | E36: Change | F36: % Change | G36: Direction of improvement
A37: Primary task pain (NRS 0-10) | B37: 7 | C37: 3 | D37: /10 | E37: =IF(OR(B37="",C37=""),"",C37-B37) -> -4 | F37: =IF(OR(N(B37)=0,C37=""),"",(C37-B37)/B37) -> -0.57142857 | G37: Lower is better
A38: FIRST-STEP pain (heel presentations) | D38: /10 | E38: =IF(OR(B38="",C38=""),"",C38-B38) | F38: =IF(OR(N(B38)=0,C38=""),"",(C38-B38)/B38) | G38: Lower is better
A39: Standing / walking tolerance | D39: min or km | E39: =IF(OR(B39="",C39=""),"",C39-B39) | F39: =IF(OR(N(B39)=0,C39=""),"",(C39-B39)/B39) | G39: Higher is better
A40: Running or sport volume tolerance | D40: km or min | E40: =IF(OR(B40="",C40=""),"",C40-B40) | F40: =IF(OR(N(B40)=0,C40=""),"",(C40-B40)/B40) | G40: Higher is better
A41: Swelling after loading (0-3) | D41: grade | E41: =IF(OR(B41="",C41=""),"",C41-B41) | F41: =IF(OR(N(B41)=0,C41=""),"",(C41-B41)/B41) | G41: Lower is better
A42: PROM score (FAAM / VISA-A / CAIT / FHSQ) | D42: points | E42: =IF(OR(B42="",C42=""),"",C42-B42) | F42: =IF(OR(N(B42)=0,C42=""),"",(C42-B42)/B42) | G42: Check the PROM's scoring direction
A44: RETURN-TO-SPORT / WORK READINESS
A45: LSI target threshold (editable) | B45: 0.9
A46: Strength tests entered | B46: =COUNT(E30:E33) -> 1
A47: Strength tests passed | B47: =COUNTIF(F30:F33,"PASS") -> 0
A48: Balance measures passed | B48: =COUNTIF(F24:F26,"PASS") -> 0
A49: Heel raise passed | B49: =COUNTIF(F19:F19,"PASS") -> 0
A50: Range measures symmetrical or mild | B50: =COUNTIF(F12:F15,"SYMMETRICAL")+COUNTIF(F12:F15,"MILD DEFICIT") -> 0
A51: Hop test battery symmetrical (>=90%) where relevant | B51: NO
A52: Sport or work-specific progression completed (running / cutting / terrain / standing hours) | B52: NO
A53: The load error has been identified and corrected (volume, surface, FOOTWEAR or training) | B53: NO
A54: EXTERNAL ANKLE SUPPORT organised for return where indicated (6-12 months post sprain) | B54: NO
A56: OVERALL READINESS STATUS → | C56: =IF(COUNT(E19:E19,E30:E33)=0,"Enter test data to calculate",IF(AND(COUNTIF(F19:F19,"NOT YET")=0,COUNT(E30:E33)>=3,COUNTIF(F30:F33,"NOT YET")=0,COUNTIF(F24:F26,"NOT YET")=0,COUNTIF(F12:F15,"RESTRICTED")=0,COUNTIF(B51:B54,"YES")=4),"READY — all criteria met","NOT YET — criteria outstanding: continue loading and re-test")) -> NOT YET — criteria outstanding: continue loading and re-test
A58: HOW TO USE THIS SHEET
A59: • Yellow cells are inputs. Every other cell is a formula — do not overwrite them.
A60: • THE WEIGHT-BEARING LUNGE deficit is measured in cm. A deficit above 3 cm reads as RESTRICTED and blocks the readiness verdict, because reduced dorsiflexion predicts re-injury.
A61: • THE SINGLE-LEG HEEL RAISE requires BOTH >=90% symmetry AND >=25 repetitions to pass — symmetry alone is not enough if both sides are weak.
A62: • RECORD WHETHER THE HEEL INVERTS during the raise. Absent inversion means tibialis posterior dysfunction even where the repetition count looks acceptable.
A63: • EYES-CLOSED BALANCE is the more sensitive marker in chronic ankle instability — do not skip it.
A64: • Discharge criteria include correcting the load error AND organising external ankle support. Returning an athlete to the same surface, shoe and volume that broke them is why these injuries recur.
A65: • Example values are pre-filled in the first row of each block — overwrite them.

Sheet Outcome Measures
A1: OUTCOME MEASURES
A2: One patient-reported measure plus dorsiflexion and heel raise capacity is the minimum baseline dataset.
A3: Measure | B3: Full Name | C3: What It Captures | D3: Scoring | E3: Best Suited To
A4: FAAM and FAAM-Sport | B4: Foot and Ankle Ability Measure | C4: Function in daily activity and sport | D4: 0-100% (higher = better) | E4: The general foot and ankle standard; the Sport subscale for athletes
A5: FAOS | B5: Foot and Ankle Outcome Score | C5: Pain, symptoms, function, sport and quality of life | D5: 0-100 (higher = better) | E5: Ankle instability, osteochondral lesions, post-surgical
A6: VISA-A | B6: Victorian Institute of Sport Assessment - Achilles | C6: Achilles tendinopathy severity and monitoring | D6: 0-100 (higher = better) | E6: Achilles tendinopathy - the condition-specific standard
A7: CAIT | B7: Cumberland Ankle Instability Tool | C7: Perceived ankle instability | D7: 0-30 (higher = better; under 24 indicates instability) | E7: Chronic ankle instability - both diagnostic and a tracking measure
A8: ATRS | B8: Achilles Tendon Total Rupture Score | C8: Recovery after Achilles rupture | D8: 0-100 (higher = better) | E8: Achilles rupture, operative and non-operative
A9: MOXFQ | B9: Manchester-Oxford Foot Questionnaire | C9: Pain, walking and social interaction | D9: 0-100 (lower = better) | E9: Forefoot surgery, hallux pathology, general foot
A10: FHSQ | B10: Foot Health Status Questionnaire | C10: Foot pain, function, footwear and general health | D10: 0-100 (higher = better) | E10: Plantar heel pain, general foot health
A11: FFI | B11: Foot Function Index | C11: Pain, disability and activity limitation | D11: 0-100 (lower = better) | E11: Plantar heel pain, general foot conditions
A12: OxAFQ-C | B12: Oxford Ankle Foot Questionnaire for Children | C12: Paediatric foot and ankle function | D12: 0-100 (higher = better) | E12: Sever's disease, coalition, paediatric presentations
A13: WEIGHT-BEARING LUNGE TEST | B13: Knee-to-wall dorsiflexion measure | C13: Ankle dorsiflexion range | D13: cm; compare both sides | E13: EVERY foot and ankle condition - the most modifiable regional risk factor
A14: SINGLE-LEG HEEL RAISE | B14: Repetitions to fatigue with standardised cadence | C14: Calf endurance and tibialis posterior function | D14: Repetitions; target 25+; compare both sides | E14: Achilles, tibialis posterior, calf, post-rupture - the functional benchmark
... A18: 10 g monofilament | B18: Protective sensation testing | C18: Loss of protective sensation | D18: Present or absent at defined sites | E18: EVERY diabetic foot - defines the at-risk foot
A20: NOTES
A21: • Scoring DIRECTION differs between measures — FAAM, FAOS, VISA-A, CAIT and ATRS improve as they RISE; MOXFQ and FFI improve as they FALL.
A22: • CAIT under 24 both diagnoses instability and tracks it — it is one of the few measures that does both jobs.
A23: • The WEIGHT-BEARING LUNGE and SINGLE-LEG HEEL RAISE are not PROMs but they are the two most useful objective markers in the region — record them every session.
A24: • The 10 g MONOFILAMENT is a screening test that changes the entire management pathway. Use it in every diabetic foot.

Sheet Whole-Person Screen
A1: WHOLE-PERSON, FOOTWEAR & SYSTEMIC SCREEN
A2: A refractory foot is a cue to widen the lens — starting with the shoes, then the spine, the circulation and the metabolism.
A3: Factor | B3: Relevance to Foot & Ankle Pain | C3: What to Screen | D3: Clinical Action | E3: Findings (fill in)
A4: FOOTWEAR | B4: Frequently the highest-yield modifiable factor in the entire region, and frequently never examined | C4: LOOK AT THE SHOES at every assessment - toe box width, heel counter, sole stiffness, drop, cushioning, age and wear pattern | D4: Specific footwear prescription for the specific condition; a shoe change can outperform any exercise in forefoot and heel presentations
A5: Lumbar spine and proximal chain | B5: The lumbar spine refers to the foot; hip and trunk deficits load the foot distally | C5: Screen the lumbar spine in any foot numbness, burning or unexplained weakness; assess hip abductor capacity and frontal-plane control | D5: Treat the source and address proximal capacity as part of the plan
A6: Diabetes and metabolic health | B6: Diabetes changes everything in the foot - neuropathy, ulceration risk, Charcot, impaired healing, tendinopathy risk | C6: MONOFILAMENT AND PULSES in every diabetic foot; ask about glycaemic control | D6: Risk-stratify, educate on daily inspection, never prescribe barefoot activity, and refer any ulcer urgently
A7: Peripheral vascular status | B7: Perfusion determines healing; peripheral arterial disease is common and under-recognised | C7: Pedal pulses and ABPI in older adults, smokers, diabetics and any non-healing wound | D7: Vascular referral where perfusion is compromised - it changes the whole management plan
A8: Bone health and energy availability | B8: Central to all bone stress injury; recurrent injury signals a systemic problem | C8: Screen energy availability, menstrual status and prior bone stress injuries in every athlete | D8: Refer for bone health, nutrition and endocrine assessment; a recurrent injury is a systemic problem in local disguise
A9: Body mass and metabolic factors | B9: Associated with plantar heel pain, tibialis posterior tendinopathy and Achilles tendinopathy | C9: Screen where progress stalls or the presentation is bilateral | D9: Support weight management alongside loading; set realistic timelines
A10: Systemic tendon risk factors | B10: Fluoroquinolones, corticosteroid exposure, diabetes and inflammatory disease raise rupture risk | C10: Ask directly in any Achilles or tibialis posterior presentation | D10: Medical review; counsel explicitly against corticosteroid injection near these tendons
A11: Inflammatory disease | B11: Bilateral enthesitis, dactylitis or polyarticular pain suggests seronegative spondyloarthropathy | C11: Ask about back pain, morning stiffness, psoriasis, eye and bowel symptoms | D11: Rheumatology referral - the foot is often the first presentation of axial spondyloarthritis
A12: Falls risk in older adults | B12: Foot pain, reduced sensation and poor balance are independent falls risk factors | C12: Balance testing, sensation, footwear and home hazards | D12: Balance and calf capacity training, appropriate footwear, and falls prevention referral
A13: Occupational and standing load | B13: Prolonged standing on hard surfaces is a major driver of heel and forefoot pain | C13: Hours standing, surface, footwear permitted at work, and break structure | D13: Anti-fatigue matting, footwear change, break structure and task rotation
A15: CLINICAL ACTIONS
A16: • FOOTWEAR IS THE FIRST THING TO WIDEN THE LENS TO, not the last. In forefoot and heel presentations it is frequently the highest-yield modifiable factor in the entire case.
A17: • DIABETES CHANGES EVERYTHING IN THE FOOT. Monofilament and pulses in every diabetic foot; any ulcer is a same-week multidisciplinary referral; never prescribe barefoot activity in an insensate foot.
A18: • PERFUSION DETERMINES HEALING. Check pedal pulses in older adults, smokers, diabetics and any non-healing wound before planning any intervention.
A19: • A RECURRENT BONE STRESS INJURY IS A SYSTEMIC PROBLEM IN LOCAL DISGUISE — screen energy availability, menstrual status and bone health.
A20: • BILATERAL HEEL ENTHESITIS is a classic first presentation of axial spondyloarthritis — ask about back pain, morning stiffness, psoriasis, eye and bowel symptoms.

Sheet Red Flags
A1: RED FLAGS & TIME-SENSITIVE PRESENTATIONS
A2: Twelve presentations where a rehabilitation trial is the wrong first move.
A3: Presentation | B3: Features | C3: Action Required | D3: Why It Cannot Wait
A4: Acute compartment syndrome of the leg | B4: ESCALATING pain out of proportion; PAIN ON PASSIVE TOE STRETCH; tense compartment; paraesthesia | C4: IMMEDIATE surgical referral; remove constrictive casts; do NOT elevate above heart level | D4: NORMAL PULSES DO NOT EXCLUDE IT. Delay causes permanent contracture and foot drop
A5: Diabetic foot ulceration | B5: ANY break in the skin of a neuropathic or ischaemic foot, however small or painless | C5: SAME-WEEK multidisciplinary diabetic foot team referral | D5: Painless ulcers progress silently; delay costs limbs
A6: Charcot neuroarthropathy | B6: HOT, SWOLLEN, RED FOOT WITH INTACT SKIN in a neuropathic patient, often painless | C6: IMMEDIATE immobilisation, non-weight-bearing and urgent referral | D6: Frequently misdiagnosed as infection or gout; continued weight bearing destroys the foot
A7: Septic arthritis | B7: Hot swollen joint with fever and pain on all movement | C7: URGENT aspiration and antibiotics | D7: Gout and sepsis present identically - aspirate
A8: Achilles tendon rupture | B8: A pop at the back of the ankle; POSITIVE THOMPSON TEST; inability to perform a single-leg heel raise | C8: Prompt orthopaedic referral | D8: UP TO 25% ARE MISSED at first presentation because patients can still walk
A9: High-risk bone stress injury | B9: NAVICULAR, medial malleolus, proximal fifth metatarsal, sesamoid, second metatarsal base, anterior tibial cortex | C9: Imaging (CT for navicular) and orthopaedic referral - not a rehabilitation trial | D9: These are watershed or tension-side sites prone to non-union and refracture
A10: Unstable syndesmotic injury | B10: Pain above the joint line; positive squeeze and external rotation tests; clear space widening | C10: Orthopaedic referral for fixation | D10: Missed instability causes chronic pain and early ankle arthritis
A11: Maisonneuve fracture | B11: Medial ankle injury WITH PROXIMAL FIBULAR TENDERNESS | C11: Radiograph the whole fibula; orthopaedic referral | D11: PALPATE THE PROXIMAL FIBULA in every medial ankle injury
A12: Progressive foot drop | B12: Weak great toe and ankle dorsiflexion, with or without back pain | C12: Urgent spinal or neurological assessment; ankle-foot orthosis meanwhile | D12: Distinguish L5 radiculopathy from common peroneal palsy and from tibialis anterior rupture
A13: Peripheral arterial disease | B13: Claudication, rest pain, absent pulses, non-healing wound, cool discoloured foot | C13: Vascular referral and ABPI | D13: Perfusion determines healing - assess it before planning any intervention
A14: Inflammatory arthropathy | B14: BILATERAL heel enthesitis, dactylitis, or polyarticular foot pain with prolonged morning stiffness | C14: Rheumatology referral | D14: The foot is frequently the first presentation of axial spondyloarthritis
A15: Malignancy or infection | B15: Constant unremitting night pain unrelated to movement; systemic features; a non-mechanical pattern | C15: Urgent medical referral and imaging | D15: Pain that does not behave mechanically is a referral, not a rehabilitation problem
A17: SCREENING RULES
A18: • THE HIGHEST-CONSEQUENCE MISS IN THIS REGION IS THE DIABETIC FOOT. A hot swollen foot with intact skin in a neuropathic patient is CHARCOT until proven otherwise — immobilise, stop weight bearing and refer the same day.
A19: • APPLY THE OTTAWA ANKLE AND FOOT RULES to every acute injury — they are highly sensitive and cost nothing.
A20: • PERFORM THE THOMPSON TEST in every posterior ankle presentation — up to 25% of Achilles ruptures are missed at first presentation because patients can still walk.
A21: • PALPATE THE PROXIMAL FIBULA in every medial ankle injury — the Maisonneuve fracture is unstable and easily missed.
A22: • NORMAL PULSES DO NOT EXCLUDE COMPARTMENT SYNDROME. Pain out of proportion with pain on passive toe stretch is the finding.

Sheet Case-Based Learning
A1: CASE-BASED LEARNING
A2: Five worked cases integrating reasoning from presentation to plan.
A3: Case | B3: Presentation | C3: Reasoning | D3: Plan
A4: Case 1 - The runner whose heel pain will not settle | B4: 44-year-old recreational runner, eight months of plantar heel pain. Has been stretching the calf and plantar fascia diligently and had one corticosteroid injection. Now describes the pain as BURNING rather than sharp, present at rest and waking her at night. Tenderness is more proximal and medial than the plantar fascia origin. | C4: The change in symptom QUALITY is the finding. Burning pain present at rest and at night is not plantar fasciopathy - it is BAXTER'S NERVE ENTRAPMENT (first branch of the lateral plantar nerve), which accounts for a meaningful proportion of chronic heel pain that has failed correct fasciopathy treatment. | D4: Reconsider the diagnosis rather than escalating the same treatment. Neural mobilisation, orthoses with medial posting to reduce nerve traction, intrinsic foot loading, and footwear review. Also note the corticosteroid injection - counsel on the plantar fascia rupture and fat pad atrophy risk before any repeat. If refractory after 3-6 months, nerve conduction studies and surgical decompression opinion.
A5: Case 2 - The sprinter with a vague midfoot ache | B5: 21-year-old sprinter, six weeks of a vague ache across the top of the midfoot. Hard to point to. Worse with sprinting and blocks, settles within a day of rest so he has kept training. Radiographs reported as normal. Tenderness over the dorsal proximal navicular. | C5: This is a NAVICULAR STRESS FRACTURE until CT says otherwise. It is the most commonly missed high-risk bone stress site precisely because the ache is vague and settles quickly with rest, and because RADIOGRAPHS ARE UNRELIABLE. The N-spot tenderness in a sprinting athlete is the finding. | D5: Stop training immediately. CT (not radiograph, and CT is superior to MRI here) and orthopaedic referral. If managed conservatively the protocol is STRICT NON-WEIGHT-BEARING CAST IMMOBILISATION FOR 6 WEEKS - partial weight bearing fails and is the commonest cause of non-union. Address ankle dorsiflexion, first-ray function and sprint volume before return, and screen energy availability.
A6: Case 3 - The netballer who keeps rolling her ankle | B6: 19-year-old netballer, fourth lateral ankle sprain in two years. Each time she rested two weeks and returned. Now feels the ankle is unreliable on landing and on uneven ground. Anterior drawer shows only mild laxity. CAIT score 18. Single-leg balance with eyes closed is markedly reduced. Weight-bearing lunge is 4 cm less than the other side. | C6: CHRONIC ANKLE INSTABILITY, and predominantly FUNCTIONAL rather than mechanical - the laxity is mild but the balance deficit and dorsiflexion restriction are marked. The recurrence pattern reflects that each sprain was rested rather than rehabilitated. | D6: BALANCE AND NEUROMUSCULAR TRAINING is the primary intervention - daily, for 4-6 weeks minimum, progressing to unstable surface, eyes closed and perturbation. Restore ankle dorsiflexion (a known re-injury risk factor) with mobilisation with movement. Peroneal and calf loading. Landing and cutting retraining with hip and frontal-plane control. And EXTERNAL SUPPORT - brace or tape - for 6-12 months on return, which is one of the best-evidenced re-injury prevention measures available.
A7: Case 4 - The man with insertional Achilles pain who got worse | B7: 52-year-old, six months of pain at the back of the heel. Was given eccentric heel drops off a step and a calf stretching programme. Symptoms have worsened. Tenderness is AT the calcaneal insertion, not 2-6 cm above. Pain is worse on hills, stairs and in stiff-backed shoes. | C7: INSERTIONAL Achilles tendinopathy, treated with a MIDPORTION protocol. Eccentric drops off a step and calf stretching both take the ankle into DORSIFLEXION, which COMPRESSES the insertion against the calcaneus. The treatment has been the aggravator. | D7: Stop the step drops and the stretching immediately. Load ON THE FLOOR in REDUCED DORSIFLEXION - heavy slow resistance heel raises within a tolerated range, progressively increasing dorsiflexion as tolerance builds. Add a HEEL LIFT, change to footwear with a soft or open heel counter, and avoid hills and stairs early. Expect 3-6 months - insertional disease is slower and less predictable than midportion, and saying so upfront prevents the next round of frustration.
A8: Case 5 - The diabetic patient with a swollen foot | B8: 61-year-old with type 2 diabetes of 14 years, referred with a swollen, warm, red right foot. He recalls no injury. He is systemically well and afebrile. The skin is intact. Monofilament sensation is absent at multiple sites. He has continued walking on it for three weeks. | C8: A HOT, SWOLLEN, RED FOOT WITH INTACT SKIN IN A NEUROPATHIC PATIENT IS CHARCOT NEUROARTHROPATHY UNTIL PROVEN OTHERWISE. It is commonly misdiagnosed as cellulitis, gout or a sprain. He is systemically well and afebrile, and he has no protective sensation - which is precisely why he has kept walking on a foot that is destroying itself. | D8: IMMEDIATE immobilisation and NON-WEIGHT-BEARING, and urgent referral to the multidisciplinary diabetic foot team. Do not rehabilitate, do not mobilise, do not wait for imaging to arrange offloading. Every day of continued weight bearing produces further bony destruction and moves him closer to a rocker-bottom deformity, ulceration and amputation. This is the highest-consequence miss in the entire foot and ankle region.
A10: WHAT THE CASES TEACH
A11: • ANKLE DORSIFLEXION and SINGLE-LEG HEEL RAISE capacity are the two highest-yield measures in the region - take them in every assessment
A12: • LOCATE ACHILLES PAIN PRECISELY: midportion tolerates loading through dorsiflexion; INSERTIONAL does not, and treating it as midportion makes it worse
A13: • When heel pain changes QUALITY to burning, or appears at rest and at night, RECONSIDER THE DIAGNOSIS - it is not fasciopathy
A14: • A vague midfoot ache in a sprinting athlete is a NAVICULAR STRESS FRACTURE until CT says otherwise - and a normal radiograph means nothing
A15: • RESTING an ankle sprain is not REHABILITATING it - balance training and external support are what prevent the next one
A16: • A HOT SWOLLEN FOOT WITH INTACT SKIN in a neuropathic patient is CHARCOT until proven otherwise - immobilise and refer the same day
A17: • ALWAYS EXAMINE THE FOOTWEAR - in the forefoot and heel it is frequently more powerful than any exercise you can prescribe
A18: • PALPATE THE PROXIMAL FIBULA in every medial ankle injury - the Maisonneuve fracture is unstable and easily missed

Sheet References
A1: KEY REFERENCES & FURTHER READING
A2: Guidelines evolve — verify currency for high-stakes decisions and apply within your scope of practice.
A4: 1 | B4: Vuurberg G, Hoorntje A, Wink LM, et al. Diagnosis, treatment and prevention of ankle sprains: update of an evidence-based clinical guideline. Br J Sports Med. 2018;52(15):956
A5: 2 | B5: Stiell IG, Greenberg GH, McKnight RD, et al. Decision rules for the use of radiography in acute ankle injuries (Ottawa Ankle Rules). JAMA. 1993;269(9):1127-1132
A6: 3 | B6: Delahunt E, Bleakley CM, Bossard DS, et al. Clinical assessment of acute lateral ankle sprain injuries (ROAST): 2019 consensus statement. Br J Sports Med. 2018;52(20):1304-1310
A7: 4 | B7: Gribble PA, Delahunt E, Bleakley CM, et al. Selection criteria for patients with chronic ankle instability in controlled research: International Ankle Consortium. Br J Sports Med. 2014
A8: 5 | B8: Alfredson H, Pietila T, Jonsson P, Lorentzon R. Heavy-load eccentric calf muscle training for the treatment of chronic Achilles tendinosis. Am J Sports Med. 1998;26(3):360-366
A9: 6 | B9: Beyer R, Kongsgaard M, Hougs Kjaer B, et al. Heavy slow resistance versus eccentric training as treatment for Achilles tendinopathy: a randomized controlled trial. Am J Sports Med. 2015;43(7):1704-1711
A10: 7 | B10: Rathleff MS, Molgaard CM, Fredberg U, et al. High-load strength training improves outcome in patients with plantar fasciitis: a randomized controlled trial. Scand J Med Sci Sports. 2015;25(3):e292-300
A11: 8 | B11: Digiovanni BF, Nawoczenski DA, Malay DP, et al. Plantar fascia-specific stretching exercise improves outcomes in patients with chronic plantar fasciitis. J Bone Joint Surg Am. 2006;88(8):1775-1781
A12: 9 | B12: Martin RL, Davenport TE, Reischl SF, et al. Heel pain - plantar fasciitis: Clinical Practice Guidelines. J Orthop Sports Phys Ther. 2014;44(11):A1-33
A13: 10 | B13: Costa ML, Achten J, Marian IR, et al. Plaster cast versus functional bracing for Achilles tendon rupture: the UKSTAR RCT. Lancet. 2020;395(10222):441-448
A14: 11 | B14: Keene DJ, Alsousou J, Harrison P, et al. Platelet rich plasma injection for acute Achilles tendon rupture: PATH-2 randomised, placebo controlled trial. BMJ. 2019;367:l6132
A15: 12 | B15: Kulig K, Reischl SF, Pomrantz AB, et al. Nonsurgical management of posterior tibial tendon dysfunction with orthoses and resistive exercise: a randomized controlled trial. Phys Ther. 2009;89(1):26-37
... A21: 18 | B21: Cook JL, Purdam CR. Is tendon pathology a continuum? Br J Sports Med. 2009;43(6):409-416
A23: NOTES
A24: • This workbook is a companion to the Knee, Bone Stress, Shoulder, Hip and Elbow modules, and follows the same structure and conventions.
A25: • It is an educational and clinical-reasoning companion. It does not replace individualised assessment, local protocols, or the operating surgeon's protocol.
A26: • Two areas of active evolution: operative versus non-operative Achilles rupture management (both now protocol-driven with comparable outcomes), and the role of injectables in plantar heel pain and Achilles tendinopathy.
